Workbook

Sheet Spryinterior
A1: URL | B1: Content Type | C1: Traffic (%) | D1: Number of Keywords | E1: Traffic | F1: Adwords Positions | G1: Positions with commercial intents in top 20 | H1: Positions with informational intents in top 20 | I1: Positions with navigational intents in top 20 | J1: Positions with transactional intents in top 20 | K1: Positions with unknown intents in top 20 | L1: Traffic with commercial intents in top 20 | M1: Traffic with informational intents in top 20 | N1: Traffic with navigational intents in top 20 | O1: Traffic with transactional intents in top 20 | P1: Traffic with unknown intents in top 20 | Q1: Traffic Change | R1: Answer Engines | S1: Top Keyword | T1: Primary Intent | U1: LLM Prompts | V1: Check ranking trùng top 10 | W1: Note
A2: https://www.spryinterior.com/blogs/news/are-corner-shelves-a-good-idea | B2: Blog | C2: 4.51 | D2: 27 | E2: 986 | F2: 0 | G2: 21 | H2: 9 | I2: 1 | J2: 3 | K2: 0 | L2: 956 | M2: 33 | N2: 0 | O2: 1 | P2: 0 | Q2: 965 | R2: google-ai | S2: corner bookshelf | T2: Commercial | U2: 7 | V2: =VLOOKUP(S2,'Keyword cả 2 web trong top 10'!A:H,8,0) -> #N/A | W2: Top traffic
A3: https://www.spryinterior.com/blogs/news/corner-tree-bookcase-a-stylish-space-saving-solution | B3: Blog | C3: 2.72 | D3: 2 | E3: 596 | F3: 0 | G3: 2 | H3: 0 | I3: 0 | J3: 0 | K3: 0 | L3: 596 | M3: 0 | N3: 0 | O3: 0 | P3: 0 | Q3: 596 | S3: corner bookshelf | T3: Commercial | U3: 0 | V3: =VLOOKUP(S3,'Keyword cả 2 web trong top 10'!A:H,8,0) -> #N/A | W3: Top traffic
A4: https://www.spryinterior.com/blogs/news/tree-branch-corner-shelf | B4: Blog | C4: 2.26 | D4: 8 | E4: 494 | F4: 0 | G4: 7 | H4: 3 | I4: 0 | J4: 0 | K4: 0 | L4: 494 | M4: 6 | N4: 0 | O4: 0 | P4: 0 | Q4: 488 | S4: corner shelf | T4: Commercial | U4: 0 | V4: =VLOOKUP(S4,'Keyword cả 2 web trong top 10'!A:H,8,0) -> #N/A | W4: Top traffic
A5: https://www.spryinterior.com/blogs/news/hanging-shelves-with-command-strips | B5: Blog | C5: 1.63 | D5: 117 | E5: 358 | F5: 0 | G5: 72 | H5: 67 | I5: 1 | J5: 7 | K5: 0 | L5: 265 | M5: 231 | N5: 0 | O5: 7 | P5: 0 | Q5: -25 | R5: google, google-ai, search-gpt | S5: command strip shelf | T5: Commercial | U5: 58 | V5: =VLOOKUP(S5,'Keyword cả 2 web trong top 10'!A:H,8,0) -> #N/A | W5: Top traffic
A6: https://www.spryinterior.com/collections/corner-floating-shelves | B6: Collection | C6: 6.65 | D6: 536 | E6: 1453 | F6: 0 | G6: 203 | H6: 206 | I6: 0 | J6: 56 | K6: 0 | L6: 1146 | M6: 377 | N6: 0 | O6: 81 | P6: 0 | Q6: -103 | R6: google | S6: corner shelf | T6: Informational | U6: 1 | V6: =VLOOKUP(S6,'Keyword cả 2 web trong top 10'!A:H,8,0) -> #N/A | W6: Top traffic
A7: https://www.spryinterior.com/collections/console-tables | B7: Collection | C7: 4.56 | D7: 1173 | E7: 997 | F7: 0 | G7: 172 | H7: 132 | I7: 0 | J7: 23 | K7: 0 | L7: 702 | M7: 328 | N7: 0 | O7: 45 | P7: 0 | Q7: 151 | S7: wooden console table | T7: Commercial | U7: 0 | V7: =VLOOKUP(S7,'Keyword cả 2 web trong top 10'!A:H,8,0) -> #N/A | W7: Top traffic
A8: https://www.spryinterior.com/collections/tree-bookshelves | B8: Collection | C8: 3.94 | D8: 96 | E8: 861 | F8: 0 | G8: 29 | H8: 72 | I8: 1 | J8: 5 | K8: 0 | L8: 313 | M8: 837 | N8: 0 | O8: 30 | P8: 0 | Q8: -884 | S8: tree shaped bookshelf | T8: Informational | U8: 0 | V8: =VLOOKUP(S8,'Keyword cả 2 web trong top 10'!A:H,8,0) -> 1 | W8: Top traffic
A9: https://www.spryinterior.com/collections/tree-coat-racks | B9: Collection | C9: 3.84 | D9: 136 | E9: 841 | F9: 0 | G9: 48 | H9: 45 | I9: 0 | J9: 4 | K9: 0 | L9: 601 | M9: 286 | N9: 0 | O9: 115 | P9: 0 | Q9: 462 | R9: google | S9: coat tree | T9: Commercial | U9: 1 | V9: =VLOOKUP(S9,'Keyword cả 2 web trong top 10'!A:H,8,0) -> #N/A | W9: Top traffic
A10: https://www.spryinterior.com/collections/coat-racks-hangers | B10: Collection | C10: 3.12 | D10: 371 | E10: 682 | F10: 0 | G10: 80 | H10: 55 | I10: 0 | J10: 9 | K10: 0 | L10: 312 | M10: 402 | N10: 0 | O10: 18 | P10: 0 | Q10: -1086 | R10: google | S10: coat rack with coats | T10: Commercial | U10: 1 | V10: =VLOOKUP(S10,'Keyword cả 2 web trong top 10'!A:H,8,0) -> #N/A | W10: Top traffic
A11: https://www.spryinterior.com/collections/table-aquarium | B11: Collection | C11: 2.86 | D11: 127 | E11: 627 | F11: 0 | G11: 52 | H11: 72 | I11: 0 | J11: 15 | K11: 0 | L11: 287 | M11: 431 | N11: 0 | O11: 122 | P11: 0 | Q11: 162 | R11: google-ai | S11: fish coffee table aquarium | T11: Informational | U11: 4 | V11: =VLOOKUP(S11,'Keyword cả 2 web trong top 10'!A:H,8,0) -> #N/A | W11: Top traffic
A12: https://www.spryinterior.com/collections/cat-tree-towers | B12: Collection | C12: 2.21 | D12: 700 | E12: 484 | F12: 0 | G12: 125 | H12: 98 | I12: 0 | J12: 7 | K12: 0 | L12: 320 | M12: 205 | N12: 0 | O12: 5 | P12: 0 | Q12: -139 | S12: tree cat furniture | T12: Commercial | U12: 0 | V12: =VLOOKUP(S12,'Keyword cả 2 web trong top 10'!A:H,8,0) -> #N/A | W12: Top traffic
A13: https://www.spryinterior.com/collections/floating-desks | B13: Collection | C13: 1.71 | D13: 96 | E13: 375 | F13: 0 | G13: 32 | H13: 62 | I13: 0 | J13: 6 | K13: 0 | L13: 195 | M13: 365 | N13: 0 | O13: 13 | P13: 0 | Q13: -334 | R13: google, google-ai, search-gpt | S13: floating desk | T13: Informational | U13: 5 | V13: =VLOOKUP(S13,'Keyword cả 2 web trong top 10'!A:H,8,0) -> 10 | W13: Top traffic
A14: https://www.spryinterior.com/collections/wall-floating-shelves | B14: Collection | C14: 1.07 | D14: 174 | E14: 234 | F14: 0 | G14: 105 | H14: 59 | I14: 0 | J14: 8 | K14: 0 | L14: 88 | M14: 188 | N14: 0 | O14: 33 | P14: 0 | Q14: 69 | R14: google, google-ai | S14: shelves floating wall | T14: Commercial | U14: 2 | V14: =VLOOKUP(S14,'Keyword cả 2 web trong top 10'!A:H,8,0) -> #N/A | W14: Top traffic
A15: https://www.spryinterior.com/collections/mushroom-floating-shelves | B15: Collection | C15: 1.06 | D15: 15 | E15: 232 | F15: 0 | G15: 3 | H15: 13 | I15: 0 | J15: 2 | K15: 0 | L15: 41 | M15: 212 | N15: 0 | O15: 32 | P15: 0 | Q15: -85 | R15: gemini | S15: mushroom shelves | T15: Informational | U15: 1 | V15: =VLOOKUP(S15,'Keyword cả 2 web trong top 10'!A:H,8,0) -> 2 | W15: Top traffic
A16: https://www.spryinterior.com/products/black-tree-branch-bookshelf-wall-mount-mid-century-sinltb079 | B16: Product | C16: 2.18 | D16: 45 | E16: 477 | F16: 0 | G16: 16 | H16: 43 | I16: 0 | J16: 3 | K16: 0 | L16: 62 | M16: 472 | N16: 0 | O16: 4 | P16: 0 | Q16: -146 | S16: tree bookshelf | T16: Informational | U16: 0 | V16: =VLOOKUP(S16,'Keyword cả 2 web trong top 10'!A:H,8,0) -> 3 | W16: Top traffic
A17: https://www.spryinterior.com/products/modern-abstract-wood-wall-art-for-living-room-decor-sithwa018 | B17: Product | C17: 1.56 | D17: 32 | E17: 342 | F17: 0 | G17: 9 | H17: 29 | I17: 0 | J17: 4 | K17: 0 | L17: 34 | M17: 335 | N17: 0 | O17: 3 | P17: 0 | Q17: 37 | S17: wooden wall accessories | T17: Informational | U17: 0 | V17: =VLOOKUP(S17,'Keyword cả 2 web trong top 10'!A:H,8,0) -> #N/A | W17: Top traffic
A18: https://www.spryinterior.com/ | B18: Trang chủ | C18: 3.08 | D18: 46 | E18: 675 | F18: 20 | G18: 7 | H18: 1 | I18: 9 | J18: 0 | K18: 0 | L18: 11 | M18: 0 | N18: 668 | O18: 0 | P18: 0 | Q18: 270 | S18: spry interiors | T18: Navigational | U18: 0 | V18: =VLOOKUP(S18,'Keyword cả 2 web trong top 10'!A:H,8,0) -> #N/A | W18: Top traffic
A19: https://www.spryinterior.com/blogs/news/weatherproof-outdoor-cat-tree | B19: Blog | C19: 0.96 | D19: 43 | E19: 211 | F19: 0 | G19: 40 | H19: 6 | I19: 0 | J19: 0 | K19: 0 | L19: 202 | M19: 19 | N19: 0 | O19: 0 | P19: 0 | Q19: -174 | R19: google, google-ai, search-gpt | S19: outdoor cat tower | T19: Commercial | U19: 7 | V19: =VLOOKUP(S19,'Keyword cả 2 web trong top 10'!A:H,8,0) -> #N/A
A20: https://www.spryinterior.com/collections/record-player-stands | B20: Collection | C20: 0.85 | D20: 338 | E20: 187 | F20: 0 | G20: 96 | H20: 59 | I20: 0 | J20: 16 | K20: 0 | L20: 100 | M20: 51 | N20: 0 | O20: 10 | P20: 0 | Q20: -50 | R20: google, google-ai | S20: corner record player stand | T20: Commercial | U20: 3 | V20: =VLOOKUP(S20,'Keyword cả 2 web trong top 10'!A:H,8,0) -> #N/A
A21: https://www.spryinterior.com/collections/bar-floating-shelves | B21: Collection | C21: 0.83 | D21: 102 | E21: 183 | F21: 0 | G21: 34 | H21: 46 | I21: 0 | J21: 7 | K21: 0 | L21: 91 | M21: 101 | N21: 0 | O21: 28 | P21: 0 | Q21: -32 | S21: bar shelves wall mounted | T21: Informational | U21: 0 | V21: =VLOOKUP(S21,'Keyword cả 2 web trong top 10'!A:H,8,0) -> #N/A
A22: https://www.spryinterior.com/blogs/news/small-corner-sink-unit | B22: Blog | C22: 0.81 | D22: 19 | E22: 179 | F22: 0 | G22: 6 | H22: 2 | I22: 0 | J22: 1 | K22: 0 | L22: 179 | M22: 0 | N22: 0 | O22: 0 | P22: 0 | Q22: 178 | R22: google | S22: corner vanity | T22: Commercial | U22: 1 | V22: =VLOOKUP(S22,'Keyword cả 2 web trong top 10'!A:H,8,0) -> #N/A
A23: https://www.spryinterior.com/products/rustic-arched-wood-frame-for-living-room-entryway-sithach003 | B23: Product | C23: 0.73 | D23: 24 | E23: 160 | F23: 0 | G23: 6 | H23: 21 | I23: 0 | J23: 1 | K23: 0 | L23: 16 | M23: 160 | N23: 0 | O23: 1 | P23: 0 | Q23: -4 | S23: arch with wood | T23: Informational | U23: 0 | V23: =VLOOKUP(S23,'Keyword cả 2 web trong top 10'!A:H,8,0) -> #N/A
A24: https://www.spryinterior.com/products/rustic-wall-decor-and-large-wooden-art-for-living-room-and-bedroom-decor-sithtvc001 | B24: Product | C24: 0.69 | D24: 38 | E24: 151 | F24: 0 | G24: 22 | H24: 27 | I24: 0 | J24: 0 | K24: 0 | L24: 73 | M24: 117 | N24: 0 | O24: 0 | P24: 0 | Q24: -24 | S24: rustic wall art | T24: Informational | U24: 0 | V24: =VLOOKUP(S24,'Keyword cả 2 web trong top 10'!A:H,8,0) -> #N/A
A25: https://www.spryinterior.com/blogs/news/how-to-hang-coat-rack-on-wall | B25: Blog | C25: 0.67 | D25: 90 | E25: 148 | F25: 0 | G25: 36 | H25: 37 | I25: 0 | J25: 7 | K25: 0 | L25: 128 | M25: 22 | N25: 0 | O25: 14 | P25: 0 | Q25: 71 | R25: gemini, google, google-ai, search-gpt | S25: wall coat rack | T25: Informational | U25: 31 | V25: =VLOOKUP(S25,'Keyword cả 2 web trong top 10'!A:H,8,0) -> #N/A
A26: https://www.spryinterior.com/blogs/news/how-high-to-hang-coat-rack-on-wall | B26: Blog | C26: 0.67 | D26: 113 | E26: 148 | F26: 0 | G26: 18 | H26: 73 | I26: 0 | J26: 3 | K26: 0 | L26: 25 | M26: 144 | N26: 0 | O26: 2 | P26: 0 | Q26: -123 | R26: google, google-ai, search-gpt | S26: coat hook height | T26: Informational | U26: 23 | V26: =VLOOKUP(S26,'Keyword cả 2 web trong top 10'!A:H,8,0) -> 9
A27: https://www.spryinterior.com/products/reclaimed-wood-entryway-console-table-sildtcs073 | B27: Product | C27: 0.66 | D27: 38 | E27: 146 | F27: 0 | G27: 21 | H27: 20 | I27: 0 | J27: 5 | K27: 0 | L27: 73 | M27: 108 | N27: 0 | O27: 2 | P27: 0 | Q27: -20 | S27: wood entry tables | T27: Commercial | U27: 0 | V27: =VLOOKUP(S27,'Keyword cả 2 web trong top 10'!A:H,8,0) -> #N/A
A28: https://www.spryinterior.com/blogs/news/what-is-the-ideal-bookshelf-shelf-spacing | B28: Blog | C28: 0.61 | D28: 170 | E28: 135 | F28: 0 | G28: 8 | H28: 104 | I28: 0 | J28: 0 | K28: 0 | L28: 7 | M28: 130 | N28: 0 | O28: 0 | P28: 0 | Q28: -1 | R28: google, google-ai | S28: standard bookshelf height | T28: Informational | U28: 47 | V28: =VLOOKUP(S28,'Keyword cả 2 web trong top 10'!A:H,8,0) -> 4
A29: https://www.spryinterior.com/blogs/news/bathroom-vanities-32-inch | B29: Blog | C29: 0.6 | D29: 43 | E29: 132 | F29: 0 | G29: 39 | H29: 3 | I29: 0 | J29: 0 | K29: 0 | L29: 130 | M29: 1 | N29: 0 | O29: 0 | P29: 0 | Q29: -93 | R29: google-ai | S29: 32 inch bathroom vanity | T29: Commercial | U29: 2 | V29: =VLOOKUP(S29,'Keyword cả 2 web trong top 10'!A:H,8,0) -> #N/A
A30: https://www.spryinterior.com/blogs/news/what-is-the-bookshelf-rule | B30: Blog | C30: 0.57 | D30: 55 | E30: 126 | F30: 0 | G30: 27 | H30: 32 | I30: 1 | J30: 10 | K30: 0 | L30: 53 | M30: 89 | N30: 0 | O30: 5 | P30: 0 | Q30: -1691 | R30: google, google-ai | S30: bookcase lighting | T30: Informational | U30: 5 | V30: =VLOOKUP(S30,'Keyword cả 2 web trong top 10'!A:H,8,0) -> #N/A
A31: https://www.spryinterior.com/products/tree-bookshelf-driftwood-branch-wall-mount-sinltb017 | B31: Product | C31: 0.55 | D31: 28 | E31: 121 | F31: 0 | G31: 12 | H31: 26 | I31: 0 | J31: 3 | K31: 0 | L31: 44 | M31: 117 | N31: 0 | O31: 0 | P31: 0 | Q31: 14 | S31: tree shelf | T31: Informational | U31: 0 | V31: =VLOOKUP(S31,'Keyword cả 2 web trong top 10'!A:H,8,0) -> 2
A32: https://www.spryinterior.com/products/rustic-wine-rack-for-furniture-home-bar-wall-design-sildttrwh022 | B32: Product | C32: 0.54 | D32: 34 | E32: 118 | F32: 0 | G32: 22 | H32: 20 | I32: 0 | J32: 2 | K32: 0 | L32: 82 | M32: 100 | N32: 0 | O32: 1 | P32: 0 | Q32: -61 | S32: wall wine holder wood | T32: Commercial | U32: 0 | V32: =VLOOKUP(S32,'Keyword cả 2 web trong top 10'!A:H,8,0) -> #N/A
A33: https://www.spryinterior.com/blogs/news/black-unique-coffee-table | B33: Blog | C33: 0.54 | D33: 6 | E33: 118 | F33: 0 | G33: 3 | H33: 0 | I33: 0 | J33: 0 | K33: 0 | L33: 118 | M33: 0 | N33: 0 | O33: 0 | P33: 0 | Q33: 118 | R33: google-ai | S33: black coffee table | T33: Commercial | U33: 3 | V33: =VLOOKUP(S33,'Keyword cả 2 web trong top 10'!A:H,8,0) -> #N/A
A34: https://www.spryinterior.com/collections/tv-cabinets | B34: Collection | C34: 0.53 | D34: 170 | E34: 117 | F34: 0 | G34: 44 | H34: 14 | I34: 1 | J34: 2 | K34: 0 | L34: 104 | M34: 33 | N34: 0 | O34: 0 | P34: 0 | Q34: 5 | R34: google, google-ai | S34: living room tv console | T34: Commercial | U34: 2 | V34: =VLOOKUP(S34,'Keyword cả 2 web trong top 10'!A:H,8,0) -> #N/A
A35: https://www.spryinterior.com/blogs/news/what-is-the-standard-size-of-a-bookshelf | B35: Blog | C35: 0.53 | D35: 171 | E35: 116 | F35: 0 | G35: 11 | H35: 80 | I35: 0 | J35: 0 | K35: 0 | L35: 66 | M35: 50 | N35: 0 | O35: 0 | P35: 0 | Q35: -91 | R35: gemini, google, google-ai | S35: standard bookshelf | T35: Informational | U35: 23 | V35: =VLOOKUP(S35,'Keyword cả 2 web trong top 10'!A:H,8,0) -> #N/A
A36: https://www.spryinterior.com/blogs/news/whats-the-difference-between-a-tree-branch-and-a-tree-limb | B36: Blog | C36: 0.52 | D36: 20 | E36: 115 | F36: 0 | G36: 0 | H36: 15 | I36: 1 | J36: 0 | K36: 0 | L36: 0 | M36: 115 | N36: 0 | O36: 0 | P36: 0 | Q36: 74 | R36: google, search-gpt | S36: tree limbs | T36: Informational | U36: 10 | V36: =VLOOKUP(S36,'Keyword cả 2 web trong top 10'!A:H,8,0) -> #N/A
A37: https://www.spryinterior.com/blogs/news/natural-floating-wood-shelves | B37: Blog | C37: 0.49 | D37: 19 | E37: 108 | F37: 0 | G37: 8 | H37: 11 | I37: 0 | J37: 3 | K37: 0 | L37: 76 | M37: 32 | N37: 0 | O37: 0 | P37: 0 | Q37: 23 | R37: google, google-ai, search-gpt | S37: natural wood floating shelves | T37: Informational | U37: 3 | V37: =VLOOKUP(S37,'Keyword cả 2 web trong top 10'!A:H,8,0) -> #N/A
A38: https://www.spryinterior.com/blogs/news/what-are-entryway-tables-called | B38: Blog | C38: 0.47 | D38: 56 | E38: 104 | F38: 0 | G38: 34 | H38: 30 | I38: 0 | J38: 3 | K38: 0 | L38: 80 | M38: 52 | N38: 0 | O38: 12 | P38: 0 | Q38: -47 | R38: gemini, google, google-ai | S38: entryway tables | T38: Commercial | U38: 10 | V38: =VLOOKUP(S38,'Keyword cả 2 web trong top 10'!A:H,8,0) -> #N/A
A39: https://www.spryinterior.com/blogs/news/best-cat-furniture-for-large-cats | B39: Blog | C39: 0.46 | D39: 38 | E39: 102 | F39: 0 | G39: 14 | H39: 0 | I39: 0 | J39: 0 | K39: 0 | L39: 98 | M39: 0 | N39: 0 | O39: 0 | P39: 0 | Q39: -23 | R39: google, google-ai | S39: top rated cat furniture | T39: Commercial | U39: 11 | V39: =VLOOKUP(S39,'Keyword cả 2 web trong top 10'!A:H,8,0) -> #N/A
A40: https://www.spryinterior.com/blogs/news/what-is-the-weight-limit-for-a-floating-wall | B40: Blog | C40: 0.43 | D40: 26 | E40: 95 | F40: 0 | G40: 5 | H40: 7 | I40: 0 | J40: 1 | K40: 0 | L40: 64 | M40: 95 | N40: 0 | O40: 0 | P40: 0 | Q40: 37 | R40: google, google-ai | S40: wall storage | T40: Informational | U40: 6 | V40: =VLOOKUP(S40,'Keyword cả 2 web trong top 10'!A:H,8,0) -> #N/A
A41: https://www.spryinterior.com/products/tree-branch-floating-shelf-driftwood-art-decor-sinltb035 | B41: Product | C41: 0.43 | D41: 24 | E41: 95 | F41: 0 | G41: 7 | H41: 22 | I41: 0 | J41: 1 | K41: 0 | L41: 41 | M41: 91 | N41: 0 | O41: 1 | P41: 0 | Q41: 7 | S41: wall tree decor | T41: Informational | U41: 0 | V41: =VLOOKUP(S41,'Keyword cả 2 web trong top 10'!A:H,8,0) -> #N/A
A42: https://www.spryinterior.com/collections/wood-benches | B42: Collection | C42: 0.43 | D42: 87 | E42: 94 | F42: 0 | G42: 30 | H42: 29 | I42: 0 | J42: 8 | K42: 0 | L42: 37 | M42: 58 | N42: 0 | O42: 23 | P42: 0 | Q42: 18 | S42: natural wood bench | T42: Commercial | U42: 0 | V42: =VLOOKUP(S42,'Keyword cả 2 web trong top 10'!A:H,8,0) -> #N/A
A43: https://www.spryinterior.com/products/rustic-wooden-tree-stump-planter-various-sizes-for-indoor-and-outdoor-plant-display-sithpt002 | B43: Product | C43: 0.43 | D43: 37 | E43: 94 | F43: 0 | G43: 15 | H43: 29 | I43: 0 | J43: 0 | K43: 0 | L43: 51 | M43: 92 | N43: 0 | O43: 0 | P43: 0 | Q43: -36 | S43: stump planter | T43: Informational | U43: 0 | V43: =VLOOKUP(S43,'Keyword cả 2 web trong top 10'!A:H,8,0) -> #N/A
A44: https://www.spryinterior.com/products/curved-wood-coffee-table-low-coffee-table-sildtcf086 | B44: Product | C44: 0.4 | D44: 28 | E44: 89 | F44: 0 | G44: 14 | H44: 23 | I44: 0 | J44: 4 | K44: 0 | L44: 37 | M44: 71 | N44: 0 | O44: 17 | P44: 0 | Q44: -7 | S44: natural wooden coffee table | T44: Informational | U44: 0 | V44: =VLOOKUP(S44,'Keyword cả 2 web trong top 10'!A:H,8,0) -> #N/A
A45: https://www.spryinterior.com/products/live-edge-vanity-vessel-sildtbrv002 | B45: Product | C45: 0.38 | D45: 3 | E45: 85 | F45: 0 | G45: 2 | H45: 3 | I45: 0 | J45: 0 | K45: 0 | L45: 0 | M45: 85 | N45: 0 | O45: 0 | P45: 0 | Q45: 0 | S45: vessel vanity | T45: Informational | U45: 0 | V45: =VLOOKUP(S45,'Keyword cả 2 web trong top 10'!A:H,8,0) -> #N/A
A46: https://www.spryinterior.com/products/solid-wood-entryway-coat-rack-driftwood-branch-coat-hanger-sinltb097 | B46: Product | C46: 0.38 | D46: 29 | E46: 85 | F46: 0 | G46: 14 | H46: 16 | I46: 0 | J46: 5 | K46: 0 | L46: 47 | M46: 45 | N46: 0 | O46: 2 | P46: 0 | Q46: -34 | S46: coat rack wooden | T46: Informational | U46: 0 | V46: =VLOOKUP(S46,'Keyword cả 2 web trong top 10'!A:H,8,0) -> #N/A
A47: https://www.spryinterior.com/blogs/news/entryway-console-table-mid-century-modern | B47: Blog | C47: 0.38 | D47: 62 | E47: 84 | F47: 0 | G47: 32 | H47: 11 | I47: 0 | J47: 3 | K47: 0 | L47: 50 | M47: 31 | N47: 0 | O47: 4 | P47: 0 | Q47: -65 | R47: google-ai | S47: console tables for entryway | T47: Commercial | U47: 1 | V47: =VLOOKUP(S47,'Keyword cả 2 web trong top 10'!A:H,8,0) -> #N/A
A48: https://www.spryinterior.com/blogs/news/what-are-the-disadvantages-of-a-floating-vanity | B48: Blog | C48: 0.35 | D48: 2 | E48: 78 | F48: 0 | G48: 2 | H48: 1 | I48: 0 | J48: 0 | K48: 0 | L48: 78 | M48: 78 | N48: 0 | O48: 0 | P48: 0 | Q48: 78 | S48: floating cabinets | T48: Commercial | U48: 0 | V48: =VLOOKUP(S48,'Keyword cả 2 web trong top 10'!A:H,8,0) -> #N/A
A49: https://www.spryinterior.com/blogs/news/entryway-console-table-with-mirror | B49: Blog | C49: 0.35 | D49: 67 | E49: 77 | F49: 0 | G49: 20 | H49: 21 | I49: 0 | J49: 2 | K49: 0 | L49: 61 | M49: 46 | N49: 0 | O49: 1 | P49: 0 | Q49: -44 | R49: google | S49: entryway table and mirror | T49: Informational | U49: 2 | V49: =VLOOKUP(S49,'Keyword cả 2 web trong top 10'!A:H,8,0) -> #N/A
A50: https://www.spryinterior.com/collections/floating-shelves | B50: Collection | C50: 0.34 | D50: 266 | E50: 76 | F50: 0 | G50: 51 | H50: 37 | I50: 0 | J50: 13 | K50: 0 | L50: 8 | M50: 40 | N50: 0 | O50: 37 | P50: 0 | Q50: 25 | R50: google-ai | S50: shelf floating | T50: Commercial | U50: 2 | V50: =VLOOKUP(S50,'Keyword cả 2 web trong top 10'!A:H,8,0) -> #N/A
A51: https://www.spryinterior.com/products/floating-bathroom-corner-shelf-vanity-sildtbrv085 | B51: Product | C51: 0.33 | D51: 31 | E51: 74 | F51: 0 | G51: 11 | H51: 26 | I51: 0 | J51: 9 | K51: 0 | L51: 41 | M51: 68 | N51: 0 | O51: 8 | P51: 0 | Q51: -24 | S51: vanity shelf | T51: Informational | U51: 0 | V51: =VLOOKUP(S51,'Keyword cả 2 web trong top 10'!A:H,8,0) -> #N/A
A52: https://www.spryinterior.com/products/handmade-wooden-cat-tree-modern-large-climbing-tree-unique-sinltt013 | B52: Product | C52: 0.33 | D52: 20 | E52: 73 | F52: 0 | G52: 14 | H52: 9 | I52: 0 | J52: 1 | K52: 0 | L52: 51 | M52: 63 | N52: 0 | O52: 1 | P52: 0 | Q52: 55 | S52: wood cat tower | T52: Commercial | U52: 0 | V52: =VLOOKUP(S52,'Keyword cả 2 web trong top 10'!A:H,8,0) -> #N/A
A53: https://www.spryinterior.com/blogs/news/why-living-room-is-called-drawing-room | B53: Blog | C53: 0.33 | D53: 37 | E53: 73 | F53: 0 | G53: 1 | H53: 35 | I53: 0 | J53: 0 | K53: 0 | L53: 0 | M53: 73 | N53: 0 | O53: 0 | P53: 0 | Q53: -1 | R53: google, google-ai | S53: what is a drawing room | T53: Informational | U53: 22 | V53: =VLOOKUP(S53,'Keyword cả 2 web trong top 10'!A:H,8,0) -> #N/A
A54: https://www.spryinterior.com/blogs/news/what-is-the-rule-for-floating-shelves | B54: Blog | C54: 0.32 | D54: 124 | E54: 72 | F54: 0 | G54: 18 | H54: 46 | I54: 0 | J54: 1 | K54: 0 | L54: 1 | M54: 71 | N54: 0 | O54: 0 | P54: 0 | Q54: -37 | R54: gemini, google, google-ai, search-gpt | S54: height of floating shelves | T54: Informational | U54: 22 | V54: =VLOOKUP(S54,'Keyword cả 2 web trong top 10'!A:H,8,0) -> #N/A
A55: https://www.spryinterior.com/blogs/news/unfinished-oak-coffee-table | B55: Blog | C55: 0.3 | D55: 4 | E55: 66 | F55: 0 | G55: 4 | H55: 0 | I55: 0 | J55: 0 | K55: 0 | L55: 66 | M55: 0 | N55: 0 | O55: 0 | P55: 0 | Q55: 66 | S55: oak coffee table | T55: Commercial | U55: 0 | V55: =VLOOKUP(S55,'Keyword cả 2 web trong top 10'!A:H,8,0) -> #N/A
A56: https://www.spryinterior.com/products/rustic-kitchen-bar-counter-for-farmhouse-or-industrial-style-homes-sithhnbta008 | B56: Product | C56: 0.28 | D56: 3 | E56: 63 | F56: 0 | G56: 1 | H56: 1 | I56: 0 | J56: 0 | K56: 0 | L56: 62 | M56: 1 | N56: 0 | O56: 0 | P56: 0 | Q56: 63 | S56: industrial kitchen bar | T56: Commercial, Informational | U56: 0 | V56: =VLOOKUP(S56,'Keyword cả 2 web trong top 10'!A:H,8,0) -> #N/A
A57: https://www.spryinterior.com/products/wooden-floating-bathroom-vanity-shelf-sildtbrv088 | B57: Product | C57: 0.27 | D57: 25 | E57: 60 | F57: 0 | G57: 11 | H57: 18 | I57: 0 | J57: 3 | K57: 0 | L57: 32 | M57: 58 | N57: 0 | O57: 2 | P57: 0 | Q57: 11 | S57: vanity shelf | T57: Informational | U57: 0 | V57: =VLOOKUP(S57,'Keyword cả 2 web trong top 10'!A:H,8,0) -> #N/A
A58: https://www.spryinterior.com/blogs/news/hanging-shelves-from-ceiling | B58: Blog | C58: 0.27 | D58: 40 | E58: 60 | F58: 0 | G58: 14 | H58: 32 | I58: 0 | J58: 4 | K58: 0 | L58: 10 | M58: 51 | N58: 0 | O58: 10 | P58: 0 | Q58: 51 | R58: google, google-ai, search-gpt | S58: hanging shelves from ceiling | T58: Informational | U58: 9 | V58: =VLOOKUP(S58,'Keyword cả 2 web trong top 10'!A:H,8,0) -> #N/A
A59: https://www.spryinterior.com/blogs/news/what-is-an-entryway-dresser-called | B59: Blog | C59: 0.27 | D59: 30 | E59: 59 | F59: 0 | G59: 21 | H59: 6 | I59: 0 | J59: 1 | K59: 0 | L59: 47 | M59: 13 | N59: 0 | O59: 2 | P59: 0 | Q59: -12 | R59: google, google-ai | S59: furniture for the hall | T59: Commercial | U59: 4 | V59: =VLOOKUP(S59,'Keyword cả 2 web trong top 10'!A:H,8,0) -> #N/A
A60: https://www.spryinterior.com/blogs/news/what-sizes-do-floating-shelves-come-in | B60: Blog | C60: 0.26 | D60: 25 | E60: 58 | F60: 0 | G60: 6 | H60: 1 | I60: 0 | J60: 1 | K60: 0 | L60: 58 | M60: 0 | N60: 0 | O60: 0 | P60: 0 | Q60: 58 | R60: google-ai, search-gpt | S60: small shelves | T60: Commercial | U60: 5 | V60: =VLOOKUP(S60,'Keyword cả 2 web trong top 10'!A:H,8,0) -> #N/A
A61: https://www.spryinterior.com/products/console-table-unique-art-solid-wood-handmade-narrow-wood-sinlcs042 | B61: Product | C61: 0.26 | D61: 18 | E61: 58 | F61: 0 | G61: 6 | H61: 11 | I61: 0 | J61: 2 | K61: 0 | L61: 10 | M61: 51 | N61: 0 | O61: 4 | P61: 0 | Q61: 1 | S61: artistic table | T61: Informational | U61: 0 | V61: =VLOOKUP(S61,'Keyword cả 2 web trong top 10'!A:H,8,0) -> #N/A
A62: https://www.spryinterior.com/blogs/news/can-you-put-2-single-vanities-side-by-side | B62: Blog | C62: 0.26 | D62: 32 | E62: 58 | F62: 0 | G62: 1 | H62: 23 | I62: 0 | J62: 0 | K62: 0 | L62: 1 | M62: 57 | N62: 0 | O62: 0 | P62: 0 | Q62: -46 | R62: google | S62: two seprate vanities kittie corner | T62: Informational | U62: 2 | V62: =VLOOKUP(S62,'Keyword cả 2 web trong top 10'!A:H,8,0) -> 2
A63: https://www.spryinterior.com/blogs/news/dark-wood-bath-vanity | B63: Blog | C63: 0.26 | D63: 12 | E63: 57 | F63: 0 | G63: 8 | H63: 5 | I63: 0 | J63: 0 | K63: 0 | L63: 57 | M63: 0 | N63: 0 | O63: 0 | P63: 0 | Q63: 23 | R63: google-ai | S63: dark wood bathroom vanity | T63: Commercial | U63: 1 | V63: =VLOOKUP(S63,'Keyword cả 2 web trong top 10'!A:H,8,0) -> #N/A
A64: https://www.spryinterior.com/blogs/news/unusual-small-coffee-tables | B64: Blog | C64: 0.26 | D64: 43 | E64: 57 | F64: 0 | G64: 21 | H64: 16 | I64: 0 | J64: 2 | K64: 0 | L64: 39 | M64: 22 | N64: 0 | O64: 2 | P64: 0 | Q64: -29 | R64: google-ai | S64: unique small coffee tables | T64: Commercial | U64: 4 | V64: =VLOOKUP(S64,'Keyword cả 2 web trong top 10'!A:H,8,0) -> #N/A
A65: https://www.spryinterior.com/blogs/news/what-is-a-tree-branch | B65: Blog | C65: 0.26 | D65: 37 | E65: 57 | F65: 0 | G65: 5 | H65: 25 | I65: 0 | J65: 0 | K65: 0 | L65: 39 | M65: 57 | N65: 0 | O65: 0 | P65: 0 | Q65: 51 | R65: gemini, google, google-ai, search-gpt | S65: tree branch | T65: Informational | U65: 12 | V65: =VLOOKUP(S65,'Keyword cả 2 web trong top 10'!A:H,8,0) -> #N/A
A66: https://www.spryinterior.com/blogs/news/living-room-farmhouse-wall-decor-ideas | B66: Blog | C66: 0.25 | D66: 6 | E66: 56 | F66: 0 | G66: 2 | H66: 6 | I66: 0 | J66: 0 | K66: 0 | L66: 56 | M66: 56 | N66: 0 | O66: 0 | P66: 0 | Q66: 56 | R66: google, google-ai, search-gpt | S66: modern farmhouse interior decor | T66: Informational | U66: 6 | V66: =VLOOKUP(S66,'Keyword cả 2 web trong top 10'!A:H,8,0) -> #N/A
A67: https://www.spryinterior.com/blogs/news/solid-black-wood-coffee-table | B67: Blog | C67: 0.25 | D67: 24 | E67: 56 | F67: 0 | G67: 9 | H67: 9 | I67: 0 | J67: 3 | K67: 0 | L67: 37 | M67: 16 | N67: 0 | O67: 4 | P67: 0 | Q67: 8 | R67: google-ai | S67: black hardwood coffee table | T67: Commercial, Informational | U67: 1 | V67: =VLOOKUP(S67,'Keyword cả 2 web trong top 10'!A:H,8,0) -> #N/A
A68: https://www.spryinterior.com/blogs/news/modern-cat-tree-without-carpet | B68: Blog | C68: 0.25 | D68: 25 | E68: 55 | F68: 0 | G68: 20 | H68: 9 | I68: 0 | J68: 0 | K68: 0 | L68: 50 | M68: 22 | N68: 0 | O68: 0 | P68: 0 | Q68: -8 | R68: google, google-ai | S68: no carpet cat tree | T68: Commercial | U68: 6 | V68: =VLOOKUP(S68,'Keyword cả 2 web trong top 10'!A:H,8,0) -> #N/A
A69: https://www.spryinterior.com/blogs/news/the-charm-of-low-contemporary-coffee-tables | B69: Blog | C69: 0.24 | D69: 2 | E69: 54 | F69: 0 | G69: 2 | H69: 0 | I69: 0 | J69: 0 | K69: 0 | L69: 54 | M69: 0 | N69: 0 | O69: 0 | P69: 0 | Q69: 0 | R69: google-ai, search-gpt | S69: low coffee table | T69: Commercial | U69: 2 | V69: =VLOOKUP(S69,'Keyword cả 2 web trong top 10'!A:H,8,0) -> #N/A
A70: https://www.spryinterior.com/blogs/news/unusual-bathroom-vanities | B70: Blog | C70: 0.24 | D70: 14 | E70: 54 | F70: 0 | G70: 10 | H70: 4 | I70: 0 | J70: 0 | K70: 0 | L70: 50 | M70: 4 | N70: 0 | O70: 0 | P70: 0 | Q70: -2 | R70: google, google-ai | S70: unusual bathroom vanities | T70: Commercial | U70: 3 | V70: =VLOOKUP(S70,'Keyword cả 2 web trong top 10'!A:H,8,0) -> #N/A
A71: https://www.spryinterior.com/products/rustic-live-edge-wooden-dining-table-for-open-kitchen-sildtdn002 | B71: Product | C71: 0.24 | D71: 32 | E71: 54 | F71: 0 | G71: 19 | H71: 15 | I71: 0 | J71: 8 | K71: 0 | L71: 27 | M71: 34 | N71: 0 | O71: 20 | P71: 0 | Q71: 13 | S71: rustic wood dining table | T71: Commercial | U71: 0 | V71: =VLOOKUP(S71,'Keyword cả 2 web trong top 10'!A:H,8,0) -> #N/A
A72: https://www.spryinterior.com/products/modern-curved-bookshelf-with-tiered-design-and-drawers-for-living-room-or-office-sithttbs025 | B72: Product | C72: 0.24 | D72: 11 | E72: 53 | F72: 0 | G72: 3 | H72: 9 | I72: 0 | J72: 1 | K72: 0 | L72: 4 | M72: 52 | N72: 0 | O72: 6 | P72: 0 | Q72: -26 | S72: tiered bookcase | T72: Informational | U72: 0 | V72: =VLOOKUP(S72,'Keyword cả 2 web trong top 10'!A:H,8,0) -> #N/A
A73: https://www.spryinterior.com/blogs/news/floating-shelf-above-toilet | B73: Blog | C73: 0.23 | D73: 45 | E73: 52 | F73: 0 | G73: 14 | H73: 28 | I73: 0 | J73: 4 | K73: 0 | L73: 21 | M73: 36 | N73: 0 | O73: 2 | P73: 0 | Q73: -33 | R73: google, google-ai | S73: above toilet shelf | T73: Informational | U73: 7 | V73: =VLOOKUP(S73,'Keyword cả 2 web trong top 10'!A:H,8,0) -> #N/A
A74: https://www.spryinterior.com/blogs/news/small-bathroom-sink-dimensions | B74: Blog | C74: 0.23 | D74: 61 | E74: 51 | F74: 0 | G74: 10 | H74: 20 | I74: 0 | J74: 0 | K74: 0 | L74: 10 | M74: 47 | N74: 0 | O74: 0 | P74: 0 | Q74: 16 | R74: google, google-ai | S74: bathroom sinks for small spaces | T74: Informational | U74: 9 | V74: =VLOOKUP(S74,'Keyword cả 2 web trong top 10'!A:H,8,0) -> #N/A
A75: https://www.spryinterior.com/blogs/news/is-it-cheaper-to-buy-or-build-a-bookshelf | B75: Blog | C75: 0.22 | D75: 42 | E75: 50 | F75: 0 | G75: 23 | H75: 18 | I75: 1 | J75: 4 | K75: 0 | L75: 32 | M75: 17 | N75: 4 | O75: 7 | P75: 0 | Q75: -102 | R75: google | S75: custom built bookcases | T75: Commercial | U75: 2 | V75: =VLOOKUP(S75,'Keyword cả 2 web trong top 10'!A:H,8,0) -> #N/A
A76: https://www.spryinterior.com/products/wood-shower-bench-shower-stool-with-shelf-sildtsb003 | B76: Product | C76: 0.22 | D76: 14 | E76: 50 | F76: 0 | G76: 9 | H76: 5 | I76: 0 | J76: 1 | K76: 0 | L76: 5 | M76: 45 | N76: 0 | O76: 10 | P76: 0 | Q76: 25 | S76: small shower bench | T76: Commercial | U76: 0 | V76: =VLOOKUP(S76,'Keyword cả 2 web trong top 10'!A:H,8,0) -> #N/A
A77: https://www.spryinterior.com/collections/corner-tree-bookshelves | B77: Collection | C77: 0.22 | D77: 29 | E77: 50 | F77: 0 | G77: 12 | H77: 14 | I77: 0 | J77: 1 | K77: 0 | L77: 31 | M77: 46 | N77: 0 | O77: 0 | P77: 0 | Q77: -46 | S77: corner tree shelf | T77: Informational | U77: 0 | V77: =VLOOKUP(S77,'Keyword cả 2 web trong top 10'!A:H,8,0) -> 2
A78: https://www.spryinterior.com/blogs/news/small-funky-coffee-table | B78: Blog | C78: 0.22 | D78: 24 | E78: 49 | F78: 0 | G78: 15 | H78: 7 | I78: 0 | J78: 1 | K78: 0 | L78: 32 | M78: 17 | N78: 0 | O78: 2 | P78: 0 | Q78: -5 | R78: google-ai, search-gpt | S78: funky coffee table | T78: Commercial | U78: 4 | V78: =VLOOKUP(S78,'Keyword cả 2 web trong top 10'!A:H,8,0) -> #N/A
A79: https://www.spryinterior.com/blogs/news/corner-vanity-units-for-small-bathrooms | B79: Blog | C79: 0.21 | D79: 23 | E79: 47 | F79: 0 | G79: 7 | H79: 0 | I79: 0 | J79: 0 | K79: 0 | L79: 47 | M79: 0 | N79: 0 | O79: 0 | P79: 0 | Q79: 44 | R79: google, google-ai, search-gpt | S79: corner vanity bathroom | T79: Commercial | U79: 4 | V79: =VLOOKUP(S79,'Keyword cả 2 web trong top 10'!A:H,8,0) -> #N/A
A80: https://www.spryinterior.com/products/mid-century-wooden-tilt-out-trash-can-for-home-furniture-decor-sildttrb007 | B80: Product | C80: 0.21 | D80: 22 | E80: 47 | F80: 0 | G80: 12 | H80: 16 | I80: 0 | J80: 4 | K80: 0 | L80: 22 | M80: 44 | N80: 0 | O80: 10 | P80: 0 | Q80: -31 | R80: gemini | S80: wood garbage can | T80: Informational | U80: 1 | V80: =VLOOKUP(S80,'Keyword cả 2 web trong top 10'!A:H,8,0) -> #N/A
A81: https://www.spryinterior.com/blogs/news/what-did-a-1970s-bedroom-look-like | B81: Blog | C81: 0.21 | D81: 23 | E81: 46 | F81: 0 | G81: 8 | H81: 17 | I81: 0 | J81: 0 | K81: 0 | L81: 21 | M81: 36 | N81: 0 | O81: 0 | P81: 0 | Q81: 34 | R81: google, google-ai, search-gpt | S81: 70s bed frame | T81: Informational | U81: 9 | V81: =VLOOKUP(S81,'Keyword cả 2 web trong top 10'!A:H,8,0) -> #N/A
A82: https://www.spryinterior.com/products/tree-branch-bookshelf-floating-bookshelf-living-room-sinltb118 | B82: Product | C82: 0.21 | D82: 7 | E82: 46 | F82: 0 | G82: 4 | H82: 7 | I82: 0 | J82: 0 | K82: 0 | L82: 10 | M82: 46 | N82: 0 | O82: 0 | P82: 0 | Q82: 44 | S82: tree bookshelves | T82: Informational | U82: 0 | V82: =VLOOKUP(S82,'Keyword cả 2 web trong top 10'!A:H,8,0) -> 1
A83: https://www.spryinterior.com/products/custom-live-edge-wood-bathroom-vanity-for-modern-rustic-bathroom-designs-sildtbrv138 | B83: Product | C83: 0.2 | D83: 19 | E83: 45 | F83: 0 | G83: 13 | H83: 4 | I83: 0 | J83: 0 | K83: 0 | L83: 25 | M83: 20 | N83: 0 | O83: 0 | P83: 0 | Q83: 28 | S83: rustic bath sinks | T83: Commercial | U83: 0 | V83: =VLOOKUP(S83,'Keyword cả 2 web trong top 10'!A:H,8,0) -> #N/A
A84: https://www.spryinterior.com/products/mid-century-wine-rack-for-kitchen-bar-wall-shelf-sildttrwh025 | B84: Product | C84: 0.2 | D84: 19 | E84: 45 | F84: 0 | G84: 12 | H84: 11 | I84: 0 | J84: 3 | K84: 0 | L84: 26 | M84: 35 | N84: 0 | O84: 3 | P84: 0 | Q84: -17 | S84: mid century wine rack | T84: Commercial | U84: 0 | V84: =VLOOKUP(S84,'Keyword cả 2 web trong top 10'!A:H,8,0) -> #N/A
A85: https://www.spryinterior.com/products/rustic-wooden-floating-vanity-for-cozy-bathroom-style-sildtbrv191 | B85: Product | C85: 0.2 | D85: 14 | E85: 45 | F85: 0 | G85: 9 | H85: 7 | I85: 0 | J85: 1 | K85: 0 | L85: 34 | M85: 17 | N85: 0 | O85: 0 | P85: 0 | Q85: 7 | S85: rustic bath sinks | T85: Commercial | U85: 0 | V85: =VLOOKUP(S85,'Keyword cả 2 web trong top 10'!A:H,8,0) -> #N/A
A86: https://www.spryinterior.com/blogs/news/when-do-bathroom-vanities-go-on-sale | B86: Blog | C86: 0.2 | D86: 5 | E86: 44 | F86: 0 | G86: 2 | H86: 0 | I86: 0 | J86: 3 | K86: 0 | L86: 11 | M86: 0 | N86: 0 | O86: 33 | P86: 0 | Q86: 29 | R86: search-gpt | S86: bathroom vanities sale | T86: Transactional | U86: 3 | V86: =VLOOKUP(S86,'Keyword cả 2 web trong top 10'!A:H,8,0) -> #N/A
A87: https://www.spryinterior.com/blogs/news/bathroom-ideas-with-two-separate-vanities | B87: Blog | C87: 0.2 | D87: 3 | E87: 44 | F87: 0 | G87: 0 | H87: 2 | I87: 0 | J87: 0 | K87: 0 | L87: 0 | M87: 44 | N87: 0 | O87: 0 | P87: 0 | Q87: -39 | R87: search-gpt | S87: two seprate vanities kittie corner | T87: Informational | U87: 1 | V87: =VLOOKUP(S87,'Keyword cả 2 web trong top 10'!A:H,8,0) -> 2
A88: https://www.spryinterior.com/products/rustic-garden-arbor-archway-for-outdoor-pathway-entrance-sithper003 | B88: Product | C88: 0.19 | D88: 11 | E88: 43 | F88: 0 | G88: 6 | H88: 9 | I88: 0 | J88: 2 | K88: 0 | L88: 27 | M88: 42 | N88: 0 | O88: 9 | P88: 0 | Q88: 17 | S88: garden entry arch | T88: Informational | U88: 0 | V88: =VLOOKUP(S88,'Keyword cả 2 web trong top 10'!A:H,8,0) -> #N/A
A89: https://www.spryinterior.com/blogs/news/diy-tree-bookshelf-plans-the-most-detailed-instructions | B89: Blog | C89: 0.19 | D89: 47 | E89: 42 | F89: 0 | G89: 9 | H89: 32 | I89: 0 | J89: 1 | K89: 0 | L89: 1 | M89: 35 | N89: 0 | O89: 1 | P89: 0 | Q89: 23 | R89: gemini, google, google-ai, search-gpt | S89: how to make a tree shelf | T89: Informational | U89: 13 | V89: =VLOOKUP(S89,'Keyword cả 2 web trong top 10'!A:H,8,0) -> #N/A
A90: https://www.spryinterior.com/blogs/news/how-to-hang-a-tree-branch-on-the-wall | B90: Blog | C90: 0.18 | D90: 5 | E90: 41 | F90: 0 | G90: 0 | H90: 5 | I90: 0 | J90: 0 | K90: 0 | L90: 0 | M90: 41 | N90: 0 | O90: 0 | P90: 0 | Q90: 41 | R90: google, google-ai, search-gpt | S90: hang a tree | T90: Informational | U90: 6 | V90: =VLOOKUP(S90,'Keyword cả 2 web trong top 10'!A:H,8,0) -> #N/A
A91: https://www.spryinterior.com/blogs/news/why-are-coffee-tables-so-low | B91: Blog | C91: 0.18 | D91: 3 | E91: 40 | F91: 0 | G91: 3 | H91: 1 | I91: 0 | J91: 0 | K91: 0 | L91: 40 | M91: 0 | N91: 0 | O91: 0 | P91: 0 | Q91: 40 | R91: google-ai | S91: low coffee table | T91: Commercial | U91: 1 | V91: =VLOOKUP(S91,'Keyword cả 2 web trong top 10'!A:H,8,0) -> #N/A
A92: https://www.spryinterior.com/products/rustic-natural-solid-wood-cat-tree-wooden-stand-naturally-gift-cat-sinltt010 | B92: Product | C92: 0.18 | D92: 15 | E92: 40 | F92: 0 | G92: 11 | H92: 7 | I92: 0 | J92: 0 | K92: 0 | L92: 26 | M92: 28 | N92: 0 | O92: 0 | P92: 0 | Q92: 8 | S92: cat wood | T92: Commercial | U92: 0 | V92: =VLOOKUP(S92,'Keyword cả 2 web trong top 10'!A:H,8,0) -> #N/A
A93: https://www.spryinterior.com/blogs/news/how-much-clearance-do-you-need-above-a-sink | B93: Blog | C93: 0.17 | D93: 8 | E93: 39 | F93: 0 | G93: 2 | H93: 7 | I93: 0 | J93: 0 | K93: 0 | L93: 31 | M93: 8 | N93: 0 | O93: 0 | P93: 0 | Q93: 39 | R93: google, google-ai | S93: cabinet above sink | T93: Informational | U93: 6 | V93: =VLOOKUP(S93,'Keyword cả 2 web trong top 10'!A:H,8,0) -> #N/A
A94: https://www.spryinterior.com/blogs/news/what-is-a-shelf-in-a-wall-called | B94: Blog | C94: 0.17 | D94: 15 | E94: 39 | F94: 0 | G94: 8 | H94: 11 | I94: 0 | J94: 0 | K94: 0 | L94: 9 | M94: 35 | N94: 0 | O94: 0 | P94: 0 | Q94: -28 | R94: google, google-ai | S94: built in shelves on wall | T94: Informational | U94: 3 | V94: =VLOOKUP(S94,'Keyword cả 2 web trong top 10'!A:H,8,0) -> #N/A
A95: https://www.spryinterior.com/products/wooden-floating-bathroom-vanity-sildtbrv089 | B95: Product | C95: 0.17 | D95: 11 | E95: 38 | F95: 0 | G95: 8 | H95: 2 | I95: 0 | J95: 1 | K95: 0 | L95: 38 | M95: 0 | N95: 0 | O95: 0 | P95: 0 | Q95: 5 | S95: floating bathroom | T95: Commercial | U95: 0 | V95: =VLOOKUP(S95,'Keyword cả 2 web trong top 10'!A:H,8,0) -> #N/A
A96: https://www.spryinterior.com/products/modern-handmade-live-edge-bar-table-for-kitchen-counter-bar-counter-and-dining-nook-sithbta001 | B96: Product | C96: 0.17 | D96: 12 | E96: 38 | F96: 0 | G96: 9 | H96: 7 | I96: 0 | J96: 0 | K96: 0 | L96: 35 | M96: 24 | N96: 0 | O96: 0 | P96: 0 | Q96: 13 | S96: wood counter bar | T96: Commercial | U96: 0 | V96: =VLOOKUP(S96,'Keyword cả 2 web trong top 10'!A:H,8,0) -> #N/A
A97: https://www.spryinterior.com/products/farmhouse-console-table-home-decor-sildtcsc009 | B97: Product | C97: 0.16 | D97: 13 | E97: 37 | F97: 0 | G97: 7 | H97: 4 | I97: 0 | J97: 0 | K97: 0 | L97: 25 | M97: 14 | N97: 0 | O97: 0 | P97: 0 | Q97: 22 | S97: farmhouse console table | T97: Commercial | U97: 0 | V97: =VLOOKUP(S97,'Keyword cả 2 web trong top 10'!A:H,8,0) -> #N/A
A98: https://www.spryinterior.com/blogs/news/what-is-vintage | B98: Blog | C98: 0.16 | D98: 35 | E98: 37 | F98: 0 | G98: 8 | H98: 14 | I98: 2 | J98: 0 | K98: 0 | L98: 0 | M98: 36 | N98: 0 | O98: 0 | P98: 0 | Q98: -17 | R98: google, google-ai, search-gpt | S98: what is vintage interior design | T98: Informational | U98: 12 | V98: =VLOOKUP(S98,'Keyword cả 2 web trong top 10'!A:H,8,0) -> #N/A
A99: https://www.spryinterior.com/blogs/news/how-many-books-can-a-tree-bookshelf-hold | B99: Blog | C99: 0.16 | D99: 6 | E99: 36 | F99: 0 | G99: 1 | H99: 4 | I99: 0 | J99: 0 | K99: 0 | L99: 0 | M99: 36 | N99: 0 | O99: 0 | P99: 0 | Q99: 36 | S99: tree bookshelf | T99: Informational | U99: 0 | V99: =VLOOKUP(S99,'Keyword cả 2 web trong top 10'!A:H,8,0) -> 3
A100: https://www.spryinterior.com/products/mid-century-wooden-kitchen-countertop-for-sleek-home-kitchen-design-sildtkct013 | B100: Product | C100: 0.16 | D100: 10 | E100: 36 | F100: 0 | G100: 8 | H100: 6 | I100: 0 | J100: 1 | K100: 0 | L100: 34 | M100: 34 | N100: 0 | O100: 1 | P100: 0 | Q100: 1 | S100: wooden counters | T100: Commercial | U100: 0 | V100: =VLOOKUP(S100,'Keyword cả 2 web trong top 10'!A:H,8,0) -> #N/A
...

Sheet Ashdeco
A1: URL | B1: Content type | C1: Traffic (%) | D1: Number of Keywords | E1: Traffic | F1: Adwords Positions | G1: Positions with commercial intents in top 20 | H1: Positions with informational intents in top 20 | I1: Positions with navigational intents in top 20 | J1: Positions with transactional intents in top 20 | K1: Positions with unknown intents in top 20 | L1: Traffic with commercial intents in top 20 | M1: Traffic with informational intents in top 20 | N1: Traffic with navigational intents in top 20 | O1: Traffic with transactional intents in top 20 | P1: Traffic with unknown intents in top 20 | Q1: Traffic Change | R1: Answer Engines | S1: Top Keyword | T1: Primary Intent | U1: LLM Prompts | V1: Check ranking trùng top 10
A2: https://ashdeco.com/collections/tree-bookshelf | B2: Collection | C2: 5.39 | D2: 94 | E2: 846 | F2: 0 | G2: 28 | H2: 70 | I2: 0 | J2: 5 | K2: 0 | L2: 162 | M2: 797 | N2: 0 | O2: 8 | P2: 0 | Q2: 489 | R2: gemini, google-ai, search-gpt | S2: tree bookshelf | T2: Informational | U2: 16 | V2: =VLOOKUP(S2,'Keyword cả 2 web trong top 10'!A:G,7,0) -> 1
A3: https://ashdeco.com/collections/corner-floating-shelves | B3: Collection | C3: 1.83 | D3: 144 | E3: 287 | F3: 0 | G3: 60 | H3: 71 | I3: 0 | J3: 15 | K3: 0 | L3: 138 | M3: 162 | N3: 0 | O3: 10 | P3: 0 | Q3: 230 | R3: gemini, google, google-ai, search-gpt | S3: wood for corner shelf | T3: Informational | U3: 11 | V3: =VLOOKUP(S3,'Keyword cả 2 web trong top 10'!A:G,7,0) -> #N/A
A4: https://ashdeco.com/collections/cat-tree-towers | B4: Collection | C4: 3.22 | D4: 151 | E4: 506 | F4: 1 | G4: 77 | H4: 67 | I4: 0 | J4: 3 | K4: 0 | L4: 290 | M4: 335 | N4: 0 | O4: 3 | P4: 0 | Q4: 411 | R4: gemini, google, google-ai, search-gpt | S4: wood cat tree | T4: Commercial | U4: 9 | V4: =VLOOKUP(S4,'Keyword cả 2 web trong top 10'!A:G,7,0) -> #N/A
A5: https://ashdeco.com/collections/coat-racks-hangers | B5: Collection | C5: 3.14 | D5: 115 | E5: 493 | F5: 0 | G5: 56 | H5: 46 | I5: 2 | J5: 9 | K5: 0 | L5: 482 | M5: 35 | N5: 0 | O5: 0 | P5: 0 | Q5: 461 | R5: gemini, google, google-ai, search-gpt | S5: wooden coat rack | T5: Commercial | U5: 20 | V5: =VLOOKUP(S5,'Keyword cả 2 web trong top 10'!A:G,7,0) -> #N/A
A6: https://ashdeco.com/collections/shoe-benches | B6: Collection | C6: 2.46 | D6: 198 | E6: 386 | F6: 0 | G6: 24 | H6: 15 | I6: 0 | J6: 9 | K6: 0 | L6: 344 | M6: 24 | N6: 0 | O6: 8 | P6: 0 | Q6: 365 | R6: gemini, google-ai | S6: shoe storage bench | T6: Commercial | U6: 2 | V6: =VLOOKUP(S6,'Keyword cả 2 web trong top 10'!A:G,7,0) -> #N/A
A7: https://ashdeco.com/blogs/news/complete-guide-to-console-tables | B7: Blog | C7: 3.74 | D7: 135 | E7: 587 | F7: 0 | G7: 97 | H7: 31 | I7: 0 | J7: 0 | K7: 0 | L7: 580 | M7: 8 | N7: 0 | O7: 0 | P7: 0 | Q7: 416 | R7: gemini, google, google-ai, search-gpt | S7: sofa table | T7: Commercial | U7: 76 | V7: =VLOOKUP(S7,'Keyword cả 2 web trong top 10'!A:G,7,0) -> #N/A
A8: https://ashdeco.com/blogs/news/corner-shelf-ideas-small-spaces-apartments | B8: Blog | C8: 3.12 | D8: 11 | E8: 489 | F8: 0 | G8: 9 | H8: 2 | I8: 0 | J8: 0 | K8: 0 | L8: 489 | M8: 0 | N8: 0 | O8: 0 | P8: 0 | Q8: 489 | R8: gemini, google-ai, search-gpt | S8: corner shelf | T8: Commercial | U8: 3 | V8: =VLOOKUP(S8,'Keyword cả 2 web trong top 10'!A:G,7,0) -> #N/A
A9: https://ashdeco.com/blogs/buying-guides/floating-shelf-weight-limit-guide | B9: Blog | C9: 3.09 | D9: 111 | E9: 485 | F9: 0 | G9: 88 | H9: 47 | I9: 0 | J9: 2 | K9: 0 | L9: 356 | M9: 436 | N9: 0 | O9: 0 | P9: 0 | Q9: 250 | R9: gemini, google, google-ai, search-gpt | S9: shelves for wall | T9: Commercial | U9: 19 | V9: =VLOOKUP(S9,'Keyword cả 2 web trong top 10'!A:G,7,0) -> #N/A
A10: https://ashdeco.com/blogs/news/corner-shelf-buying-guide | B10: Blog | C10: 2.6 | D10: 59 | E10: 409 | F10: 0 | G10: 43 | H10: 19 | I10: 2 | J10: 8 | K10: 0 | L10: 407 | M10: 328 | N10: 0 | O10: 1 | P10: 0 | Q10: 221 | R10: gemini, google, google-ai, search-gpt | S10: corner shelves | T10: Commercial | U10: 61 | V10: =VLOOKUP(S10,'Keyword cả 2 web trong top 10'!A:G,7,0) -> #N/A
A11: https://ashdeco.com/blogs/buying-guides/entryway-bench-shoe-storage-guide | B11: Blog | C11: 2.38 | D11: 28 | E11: 373 | F11: 0 | G11: 27 | H11: 2 | I11: 0 | J11: 0 | K11: 0 | L11: 373 | M11: 0 | N11: 0 | O11: 0 | P11: 0 | Q11: 373 | R11: google-ai, search-gpt | S11: shoe storage bench | T11: Commercial | U11: 33 | V11: =VLOOKUP(S11,'Keyword cả 2 web trong top 10'!A:G,7,0) -> #N/A
A12: https://ashdeco.com/blogs/room-ideas/coat-hook-height-where-to-mount-for-every-room-guide | B12: Blog | C12: 2.2 | D12: 136 | E12: 346 | F12: 0 | G12: 25 | H12: 105 | I12: 0 | J12: 3 | K12: 0 | L12: 106 | M12: 278 | N12: 0 | O12: 1 | P12: 0 | Q12: 74 | R12: google, google-ai, search-gpt | S12: coat tree | T12: Informational | U12: 37 | V12: =VLOOKUP(S12,'Keyword cả 2 web trong top 10'!A:G,7,0) -> #N/A
A13: https://ashdeco.com/blogs/news/hall-tree-with-storage-buying-guide | B13: Blog | C13: 1.88 | D13: 20 | E13: 296 | F13: 0 | G13: 10 | H13: 4 | I13: 0 | J13: 0 | K13: 0 | L13: 296 | M13: 0 | N13: 0 | O13: 0 | P13: 0 | Q13: 269 | R13: gemini, google-ai, search-gpt | S13: hall tree | T13: Commercial | U13: 25 | V13: =VLOOKUP(S13,'Keyword cả 2 web trong top 10'!A:G,7,0) -> #N/A
... A28: https://ashdeco.com/blogs/news/tree-shaped-bookshelf-why-it-works | B28: Blog | C28: 1.24 | D28: 5 | E28: 195 | F28: 0 | G28: 0 | H28: 5 | I28: 0 | J28: 0 | K28: 0 | L28: 0 | M28: 195 | N28: 0 | O28: 0 | P28: 0 | Q28: 195 | R28: search-gpt | S28: tree bookcase | T28: Informational | U28: 1 | V28: =VLOOKUP(S28,'Keyword cả 2 web trong top 10'!A:G,7,0) -> 3
A29: https://ashdeco.com/blogs/buying-guides/solid-wood-dining-table-under-1500 | B29: Blog | C29: 1.21 | D29: 5 | E29: 191 | F29: 0 | G29: 4 | H29: 2 | I29: 0 | J29: 1 | K29: 0 | L29: 191 | M29: 118 | N29: 0 | O29: 0 | P29: 0 | Q29: -232 | S29: wood dinning table | T29: Commercial | U29: 0 | V29: =VLOOKUP(S29,'Keyword cả 2 web trong top 10'!A:G,7,0) -> #N/A
A30: https://ashdeco.com/collections/mushroom-floating-shelves | B30: Collection | C30: 1.18 | D30: 10 | E30: 185 | F30: 0 | G30: 3 | H30: 9 | I30: 0 | J30: 1 | K30: 0 | L30: 17 | M30: 176 | N30: 0 | O30: 2 | P30: 0 | Q30: 181 | R30: gemini, google-ai, search-gpt | S30: mushroom shelf | T30: Informational | U30: 7 | V30: =VLOOKUP(S30,'Keyword cả 2 web trong top 10'!A:G,7,0) -> 2
A31: https://ashdeco.com/blogs/news/mushroom-shelf-vs-corner-floating-shelf | B31: Blog | C31: 1.14 | D31: 2 | E31: 180 | F31: 0 | G31: 2 | H31: 0 | I31: 0 | J31: 0 | K31: 0 | L31: 180 | M31: 0 | N31: 0 | O31: 0 | P31: 0 | Q31: 180 | R31: google-ai, search-gpt | S31: corner floating shelves | T31: Commercial | U31: 3 | V31: =VLOOKUP(S31,'Keyword cả 2 web trong top 10'!A:G,7,0) -> #N/A
A32: https://ashdeco.com/blogs/buying-guides/cat-trees-for-large-cats-complete-buyers-guide-ashdeco | B32: Blog | C32: 1.11 | D32: 7 | E32: 175 | F32: 0 | G32: 6 | H32: 0 | I32: 0 | J32: 0 | K32: 0 | L32: 175 | M32: 0 | N32: 0 | O32: 0 | P32: 0 | Q32: 12 | R32: gemini, google, google-ai, search-gpt | S32: cat trees for large cats | T32: Commercial | U32: 25 | V32: =VLOOKUP(S32,'Keyword cả 2 web trong top 10'!A:G,7,0) -> #N/A
A33: https://ashdeco.com/blogs/buying-guides/corner-floating-shelf-measurement-guide | B33: Blog | C33: 1.1 | D33: 9 | E33: 173 | F33: 0 | G33: 8 | H33: 1 | I33: 0 | J33: 0 | K33: 0 | L33: 173 | M33: 0 | N33: 0 | O33: 0 | P33: 0 | Q33: -96 | R33: google-ai, search-gpt | S33: floating corner shelves | T33: Commercial | U33: 4 | V33: =VLOOKUP(S33,'Keyword cả 2 web trong top 10'!A:G,7,0) -> #N/A
A34: https://ashdeco.com/collections/record-player-stands | B34: Collection | C34: 1.07 | D34: 169 | E34: 168 | F34: 0 | G34: 57 | H34: 42 | I34: 0 | J34: 9 | K34: 0 | L34: 124 | M34: 32 | N34: 0 | O34: 1 | P34: 0 | Q34: 142 | R34: search-gpt | S34: record player table | T34: Commercial | U34: 2 | V34: =VLOOKUP(S34,'Keyword cả 2 web trong top 10'!A:G,7,0) -> #N/A
A35: https://ashdeco.com/blogs/room-ideas/floating-shelf-above-bed-ideas | B35: Blog | C35: 1.05 | D35: 44 | E35: 166 | F35: 0 | G35: 33 | H35: 19 | I35: 0 | J35: 3 | K35: 0 | L35: 121 | M35: 69 | N35: 0 | O35: 11 | P35: 0 | Q35: 118 | R35: google, google-ai, search-gpt | S35: floating bed shelf | T35: Commercial | U35: 14 | V35: =VLOOKUP(S35,'Keyword cả 2 web trong top 10'!A:G,7,0) -> #N/A
A36: https://ashdeco.com/blogs/buying-guides/tree-bookshelf-buying-guide | B36: Blog | C36: 1.05 | D36: 5 | E36: 166 | F36: 0 | G36: 0 | H36: 4 | I36: 0 | J36: 0 | K36: 0 | L36: 0 | M36: 166 | N36: 0 | O36: 0 | P36: 0 | Q36: 166 | R36: google-ai | S36: tree bookshelf | T36: Informational | U36: 2 | V36: =VLOOKUP(S36,'Keyword cả 2 web trong top 10'!A:G,7,0) -> 1
A37: https://ashdeco.com/blogs/news/bookshelf-rule-styling-guide | B37: Blog | C37: 1.01 | D37: 100 | E37: 159 | F37: 0 | G37: 44 | H37: 63 | I37: 2 | J37: 8 | K37: 0 | L37: 67 | M37: 97 | N37: 0 | O37: 15 | P37: 0 | Q37: -1047 | R37: gemini, google, google-ai, search-gpt | S37: book shelf decor | T37: Informational | U37: 32 | V37: =VLOOKUP(S37,'Keyword cả 2 web trong top 10'!A:G,7,0) -> #N/A
A38: https://ashdeco.com/blogs/buying-guides/extendable-dining-table-worth-it | B38: Blog | C38: 0.95 | D38: 16 | E38: 149 | F38: 0 | G38: 13 | H38: 5 | I38: 0 | J38: 0 | K38: 0 | L38: 70 | M38: 80 | N38: 0 | O38: 0 | P38: 0 | Q38: -239 | R38: gemini, google-ai, search-gpt | S38: expandable dining table | T38: Commercial | U38: 10 | V38: =VLOOKUP(S38,'Keyword cả 2 web trong top 10'!A:G,7,0) -> #N/A
A39: https://ashdeco.com/blogs/buying-guides/small-bathroom-vanity | B39: Blog | C39: 0.94 | D39: 7 | E39: 148 | F39: 0 | G39: 6 | H39: 1 | I39: 0 | J39: 0 | K39: 0 | L39: 148 | M39: 0 | N39: 0 | O39: 0 | P39: 0 | Q39: 148 | R39: google-ai, search-gpt | S39: small bathroom vanity | T39: Commercial | U39: 4 | V39: =VLOOKUP(S39,'Keyword cả 2 web trong top 10'!A:G,7,0) -> #N/A
A40: https://ashdeco.com/blogs/buying-guides/shoe-bench-buying-guide | B40: Blog | C40: 0.88 | D40: 16 | E40: 138 | F40: 0 | G40: 11 | H40: 4 | I40: 0 | J40: 0 | K40: 0 | L40: 133 | M40: 5 | N40: 0 | O40: 0 | P40: 0 | Q40: -120 | R40: google, google-ai, search-gpt | S40: shoe storage bench | T40: Commercial | U40: 53 | V40: =VLOOKUP(S40,'Keyword cả 2 web trong top 10'!A:G,7,0) -> #N/A
A41: https://ashdeco.com/blogs/news/glowledge-vs-ashdeco-floating-shelf | B41: Blog | C41: 0.84 | D41: 1 | E41: 132 | F41: 0 | G41: 1 | H41: 0 | I41: 0 | J41: 0 | K41: 0 | L41: 132 | M41: 0 | N41: 0 | O41: 0 | P41: 0 | Q41: 0 | R41: search-gpt | S41: glowledge floating shelf | T41: Commercial | U41: 4 | V41: =VLOOKUP(S41,'Keyword cả 2 web trong top 10'!A:G,7,0) -> #N/A
... A51: https://ashdeco.com/blogs/buying-guides/hanger-wall-hanger-types-heights-guide | B51: Blog | C51: 0.65 | D51: 35 | E51: 102 | F51: 0 | G51: 25 | H51: 13 | I51: 0 | J51: 0 | K51: 0 | L51: 100 | M51: 66 | N51: 0 | O51: 0 | P51: 0 | Q51: -17 | R51: gemini, google, google-ai, search-gpt | S51: door hooks | T51: Commercial | U51: 67 | V51: =VLOOKUP(S51,'Keyword cả 2 web trong top 10'!A:G,7,0) -> #N/A
A52: https://ashdeco.com/blogs/buying-guides/floating-shelves-cost | B52: Blog | C52: 0.65 | D52: 3 | E52: 102 | F52: 0 | G52: 2 | H52: 2 | I52: 0 | J52: 0 | K52: 0 | L52: 100 | M52: 101 | N52: 0 | O52: 0 | P52: 0 | Q52: 102 | S52: shelving unit | T52: Commercial, Informational | U52: 0 | V52: =VLOOKUP(S52,'Keyword cả 2 web trong top 10'!A:G,7,0) -> #N/A
A53: https://ashdeco.com/blogs/buying-guides/tree-bookshelf-dimensions | B53: Blog | C53: 0.61 | D53: 2 | E53: 97 | F53: 0 | G53: 0 | H53: 2 | I53: 0 | J53: 0 | K53: 0 | L53: 0 | M53: 97 | N53: 0 | O53: 0 | P53: 0 | Q53: 97 | S53: tree bookshelf | T53: Informational | U53: 0 | V53: =VLOOKUP(S53,'Keyword cả 2 web trong top 10'!A:G,7,0) -> 1
A54: https://ashdeco.com/blogs/room-ideas/rustic-corner-shelf-ideas | B54: Blog | C54: 0.61 | D54: 1 | E54: 96 | F54: 0 | G54: 1 | H54: 0 | I54: 0 | J54: 0 | K54: 0 | L54: 96 | M54: 0 | N54: 0 | O54: 0 | P54: 0 | Q54: 96 | S54: corner floating shelves | T54: Commercial | U54: 0 | V54: =VLOOKUP(S54,'Keyword cả 2 web trong top 10'!A:G,7,0) -> #N/A
A55: https://ashdeco.com/blogs/buying-guides/dining-table-size-guide | B55: Blog | C55: 0.61 | D55: 42 | E55: 96 | F55: 0 | G55: 11 | H55: 22 | I55: 0 | J55: 0 | K55: 0 | L55: 93 | M55: 17 | N55: 0 | O55: 0 | P55: 0 | Q55: 96 | R55: google, search-gpt | S55: small tables | T55: Informational | U55: 2 | V55: =VLOOKUP(S55,'Keyword cả 2 web trong top 10'!A:G,7,0) -> #N/A
A56: https://ashdeco.com/blogs/buying-guides/tree-shaped-bookshelf-kids-room | B56: Blog | C56: 0.61 | D56: 1 | E56: 96 | F56: 0 | G56: 0 | H56: 1 | I56: 0 | J56: 0 | K56: 0 | L56: 0 | M56: 96 | N56: 0 | O56: 0 | P56: 0 | Q56: 96 | R56: gemini, google-ai, search-gpt | S56: tree bookcase | T56: Informational | U56: 27 | V56: =VLOOKUP(S56,'Keyword cả 2 web trong top 10'!A:G,7,0) -> 3
A57: https://ashdeco.com/blogs/wood-knowledge/best-wood-for-closet-shelves | B57: Blog | C57: 0.56 | D57: 59 | E57: 89 | F57: 0 | G57: 45 | H57: 22 | I57: 0 | J57: 0 | K57: 0 | L57: 75 | M57: 32 | N57: 0 | O57: 0 | P57: 0 | Q57: 71 | R57: gemini, google, google-ai, search-gpt | S57: closet wood | T57: Commercial | U57: 118 | V57: =VLOOKUP(S57,'Keyword cả 2 web trong top 10'!A:G,7,0) -> #N/A
A58: https://ashdeco.com/blogs/buying-guides/floating-shelf-under-tv | B58: Blog | C58: 0.56 | D58: 15 | E58: 88 | F58: 0 | G58: 9 | H58: 9 | I58: 0 | J58: 1 | K58: 0 | L58: 85 | M58: 6 | N58: 0 | O58: 0 | P58: 0 | Q58: -122 | R58: google, search-gpt | S58: floating tv shelf | T58: Commercial, Informational | U58: 8 | V58: =VLOOKUP(S58,'Keyword cả 2 web trong top 10'!A:G,7,0) -> #N/A
A59: https://ashdeco.com/blogs/news/floating-desk-ideas | B59: Blog | C59: 0.54 | D59: 13 | E59: 86 | F59: 0 | G59: 7 | H59: 9 | I59: 0 | J59: 0 | K59: 0 | L59: 83 | M59: 84 | N59: 0 | O59: 0 | P59: 0 | Q59: -13 | R59: gemini, google, google-ai, search-gpt | S59: floating desk | T59: Informational | U59: 13 | V59: =VLOOKUP(S59,'Keyword cả 2 web trong top 10'!A:G,7,0) -> 2
A60: https://ashdeco.com/blogs/news/floating-shelf-above-toilet | B60: Blog | C60: 0.54 | D60: 29 | E60: 85 | F60: 0 | G60: 9 | H60: 14 | I60: 2 | J60: 3 | K60: 0 | L60: 79 | M60: 4 | N60: 2 | O60: 3 | P60: 0 | Q60: 85 | R60: google, search-gpt | S60: bathroom shelves over toilet | T60: Informational | U60: 9 | V60: =VLOOKUP(S60,'Keyword cả 2 web trong top 10'!A:G,7,0) -> #N/A
A61: https://ashdeco.com/blogs/news/bathroom-floating-shelves-guide | B61: Blog | C61: 0.51 | D61: 14 | E61: 80 | F61: 0 | G61: 8 | H61: 5 | I61: 0 | J61: 1 | K61: 0 | L61: 79 | M61: 80 | N61: 0 | O61: 0 | P61: 0 | Q61: -39 | R61: gemini, google, google-ai, search-gpt | S61: bathroom floating shelves | T61: Commercial | U61: 28 | V61: =VLOOKUP(S61,'Keyword cả 2 web trong top 10'!A:G,7,0) -> #N/A
A62: https://ashdeco.com/blogs/wood-knowledge/why-solid-wood-furniture-lasts-generations | B62: Blog | C62: 0.5 | D62: 1 | E62: 79 | F62: 0 | G62: 1 | H62: 0 | I62: 0 | J62: 0 | K62: 0 | L62: 79 | M62: 0 | N62: 0 | O62: 0 | P62: 0 | Q62: 79 | S62: solid wood furniture | T62: Commercial | U62: 0 | V62: =VLOOKUP(S62,'Keyword cả 2 web trong top 10'!A:G,7,0) -> #N/A
A63: https://ashdeco.com/collections/floating-desk | B63: Collection | C63: 0.44 | D63: 47 | E63: 70 | F63: 0 | G63: 22 | H63: 35 | I63: 0 | J63: 2 | K63: 0 | L63: 24 | M63: 66 | N63: 0 | O63: 1 | P63: 0 | Q63: 52 | R63: google, search-gpt | S63: floating wall desk | T63: Informational | U63: 5 | V63: =VLOOKUP(S63,'Keyword cả 2 web trong top 10'!A:G,7,0) -> 2
A64: https://ashdeco.com/blogs/news/round-coffee-table-buyers-guide | B64: Blog | C64: 0.43 | D64: 50 | E64: 68 | F64: 0 | G64: 49 | H64: 7 | I64: 0 | J64: 0 | K64: 0 | L64: 68 | M64: 0 | N64: 0 | O64: 0 | P64: 0 | Q64: -1011 | R64: google-ai, search-gpt | S64: round coffee tables | T64: Commercial | U64: 13 | V64: =VLOOKUP(S64,'Keyword cả 2 web trong top 10'!A:G,7,0) -> #N/A
A65: https://ashdeco.com/blogs/wood-knowledge/wood-species-shoe-bench | B65: Blog | C65: 0.42 | D65: 5 | E65: 66 | F65: 0 | G65: 4 | H65: 0 | I65: 0 | J65: 0 | K65: 0 | L65: 63 | M65: 0 | N65: 0 | O65: 0 | P65: 0 | Q65: 66 | R65: gemini, google-ai, search-gpt | S65: wood shoe rack | T65: Commercial | U65: 18 | V65: =VLOOKUP(S65,'Keyword cả 2 web trong top 10'!A:G,7,0) -> #N/A
A66: https://ashdeco.com/blogs/buying-guides/record-deck-stand-buying-guide | B66: Blog | C66: 0.41 | D66: 19 | E66: 65 | F66: 0 | G66: 16 | H66: 6 | I66: 0 | J66: 1 | K66: 0 | L66: 65 | M66: 29 | N66: 0 | O66: 0 | P66: 0 | Q66: 3 | R66: google-ai, search-gpt | S66: record player stand with storage | T66: Commercial | U66: 27 | V66: =VLOOKUP(S66,'Keyword cả 2 web trong top 10'!A:G,7,0) -> #N/A
A67: https://ashdeco.com/blogs/room-ideas/tree-bookshelf-for-nursery-montessori-friendly | B67: Blog | C67: 0.4 | D67: 1 | E67: 64 | F67: 0 | G67: 1 | H67: 1 | I67: 0 | J67: 0 | K67: 0 | L67: 64 | M67: 64 | N67: 0 | O67: 0 | P67: 0 | Q67: 64 | R67: google-ai, search-gpt | S67: nursery bookshelf | T67: Commercial, Informational | U67: 4 | V67: =VLOOKUP(S67,'Keyword cả 2 web trong top 10'!A:G,7,0) -> #N/A
A68: https://ashdeco.com/blogs/buying-guides/floating-shelves-bathroom-moisture-proof | B68: Blog | C68: 0.4 | D68: 8 | E68: 64 | F68: 0 | G68: 7 | H68: 4 | I68: 0 | J68: 0 | K68: 0 | L68: 64 | M68: 64 | N68: 0 | O68: 0 | P68: 0 | Q68: 64 | R68: gemini, google-ai, search-gpt | S68: floating shelves bathroom | T68: Commercial | U68: 39 | V68: =VLOOKUP(S68,'Keyword cả 2 web trong top 10'!A:G,7,0) -> #N/A
A69: https://ashdeco.com/blogs/room-ideas/wooden-mirror-frame-buying-guide | B69: Blog | C69: 0.4 | D69: 2 | E69: 63 | F69: 0 | G69: 2 | H69: 0 | I69: 0 | J69: 0 | K69: 0 | L69: 63 | M69: 0 | N69: 0 | O69: 0 | P69: 0 | Q69: 63 | R69: google, google-ai, search-gpt | S69: wood mirror | T69: Commercial | U69: 29 | V69: =VLOOKUP(S69,'Keyword cả 2 web trong top 10'!A:G,7,0) -> #N/A
A70: https://ashdeco.com/blogs/buying-guides/best-cat-trees-large-cats-2026-wood-vs-carpet | B70: Blog | C70: 0.37 | D70: 10 | E70: 58 | F70: 0 | G70: 9 | H70: 1 | I70: 0 | J70: 0 | K70: 0 | L70: 58 | M70: 0 | N70: 0 | O70: 0 | P70: 0 | Q70: 58 | R70: gemini, google, search-gpt | S70: cat tree sisal | T70: Commercial | U70: 9 | V70: =VLOOKUP(S70,'Keyword cả 2 web trong top 10'!A:G,7,0) -> #N/A
A71: https://ashdeco.com/collections/tree-hangers | B71: Collection | C71: 0.36 | D71: 36 | E71: 57 | F71: 0 | G71: 19 | H71: 21 | I71: 0 | J71: 1 | K71: 0 | L71: 16 | M71: 54 | N71: 0 | O71: 0 | P71: 0 | Q71: 52 | R71: google-ai, search-gpt | S71: hanger tree | T71: Informational | U71: 5 | V71: =VLOOKUP(S71,'Keyword cả 2 web trong top 10'!A:G,7,0) -> 2
A72: https://ashdeco.com/blogs/news/small-bookcases-for-small-spaces | B72: Blog | C72: 0.35 | D72: 49 | E72: 55 | F72: 0 | G72: 27 | H72: 9 | I72: 0 | J72: 2 | K72: 0 | L72: 43 | M72: 12 | N72: 0 | O72: 0 | P72: 0 | Q72: 55 | R72: google, google-ai, search-gpt | S72: bookcases for small spaces | T72: Commercial | U72: 31 | V72: =VLOOKUP(S72,'Keyword cả 2 web trong top 10'!A:G,7,0) -> #N/A
A73: https://ashdeco.com/blogs/room-ideas/console-table-behind-couch | B73: Blog | C73: 0.34 | D73: 36 | E73: 54 | F73: 0 | G73: 5 | H73: 21 | I73: 0 | J73: 0 | K73: 0 | L73: 42 | M73: 12 | N73: 0 | O73: 0 | P73: 0 | Q73: 54 | R73: gemini, google, google-ai, search-gpt | S73: table for behind couch | T73: Informational | U73: 11 | V73: =VLOOKUP(S73,'Keyword cả 2 web trong top 10'!A:G,7,0) -> #N/A
A74: https://ashdeco.com/collections/wall-tree-bookshelf | B74: Collection | C74: 0.33 | D74: 7 | E74: 52 | F74: 0 | G74: 3 | H74: 6 | I74: 0 | J74: 0 | K74: 0 | L74: 5 | M74: 52 | N74: 0 | O74: 0 | P74: 0 | Q74: 50 | R74: google, search-gpt | S74: tree branch shelf | T74: Informational | U74: 10 | V74: =VLOOKUP(S74,'Keyword cả 2 web trong top 10'!A:G,7,0) -> 2
A75: https://ashdeco.com/collections/corner-tree-bookshelf | B75: Collection | C75: 0.3 | D75: 17 | E75: 48 | F75: 0 | G75: 6 | H75: 12 | I75: 0 | J75: 2 | K75: 0 | L75: 23 | M75: 47 | N75: 0 | O75: 2 | P75: 0 | Q75: 6 | R75: google, google-ai, search-gpt | S75: tree corner bookshelf | T75: Informational | U75: 6 | V75: =VLOOKUP(S75,'Keyword cả 2 web trong top 10'!A:G,7,0) -> 1
A76: https://ashdeco.com/products/corner-tree-floating-bookshelf-driftwood-branch-wall-mounted-hanging-shelf-artistic-corner-furniture-decoration | B76: Product | C76: 0.29 | D76: 5 | E76: 46 | F76: 0 | G76: 3 | H76: 5 | I76: 0 | J76: 1 | K76: 0 | L76: 11 | M76: 46 | N76: 0 | O76: 0 | P76: 0 | Q76: 44 | S76: tree shelf | T76: Informational | U76: 0 | V76: =VLOOKUP(S76,'Keyword cả 2 web trong top 10'!A:G,7,0) -> 1
A77: https://ashdeco.com/blogs/news/driftwood-floor-lamp-styling-guide | B77: Blog | C77: 0.28 | D77: 3 | E77: 45 | F77: 0 | G77: 1 | H77: 2 | I77: 0 | J77: 0 | K77: 0 | L77: 42 | M77: 3 | N77: 0 | O77: 0 | P77: 0 | Q77: 42 | R77: google-ai, search-gpt | S77: wooden floor lamp | T77: Informational | U77: 3 | V77: =VLOOKUP(S77,'Keyword cả 2 web trong top 10'!A:G,7,0) -> #N/A
A78: https://ashdeco.com/blogs/news/mushroom-wall-shelfwhat-to-look-for-and-what-makes-one-worth-buying | B78: Blog | C78: 0.28 | D78: 3 | E78: 44 | F78: 0 | G78: 0 | H78: 3 | I78: 0 | J78: 1 | K78: 0 | L78: 0 | M78: 44 | N78: 0 | O78: 21 | P78: 0 | Q78: 22 | R78: google-ai, search-gpt | S78: mushroom shelf | T78: Informational | U78: 5 | V78: =VLOOKUP(S78,'Keyword cả 2 web trong top 10'!A:G,7,0) -> 2
A79: https://ashdeco.com/ | B79: Other | C79: 0.27 | D79: 7 | E79: 43 | F79: 3 | G79: 0 | H79: 2 | I79: 1 | J79: 1 | K79: 0 | L79: 0 | M79: 3 | N79: 40 | O79: 2 | P79: 0 | Q79: 43 | R79: search-gpt | S79: ashdeco | T79: Informational | U79: 1 | V79: =VLOOKUP(S79,'Keyword cả 2 web trong top 10'!A:G,7,0) -> #N/A
A80: https://ashdeco.com/collections/wall-floating-shelves | B80: Collection | C80: 0.25 | D80: 15 | E80: 40 | F80: 0 | G80: 5 | H80: 3 | I80: 0 | J80: 0 | K80: 0 | L80: 2 | M80: 37 | N80: 0 | O80: 0 | P80: 0 | Q80: 40 | R80: google, search-gpt | S80: wall mounted floating shelves | T80: Commercial | U80: 3 | V80: =VLOOKUP(S80,'Keyword cả 2 web trong top 10'!A:G,7,0) -> #N/A
A81: https://ashdeco.com/blogs/room-ideas/mid-century-bathroom-vanity | B81: Blog | C81: 0.24 | D81: 3 | E81: 39 | F81: 0 | G81: 0 | H81: 3 | I81: 0 | J81: 0 | K81: 0 | L81: 0 | M81: 39 | N81: 0 | O81: 0 | P81: 0 | Q81: 38 | R81: google, search-gpt | S81: mid century style bathroom vanity | T81: Informational | U81: 6 | V81: =VLOOKUP(S81,'Keyword cả 2 web trong top 10'!A:G,7,0) -> #N/A
A82: https://ashdeco.com/blogs/room-ideas/laundry-room-shelving-ideas-open-closed | B82: Blog | C82: 0.24 | D82: 21 | E82: 38 | F82: 0 | G82: 6 | H82: 16 | I82: 0 | J82: 0 | K82: 0 | L82: 0 | M82: 38 | N82: 0 | O82: 0 | P82: 0 | Q82: 33 | R82: google, google-ai | S82: laundry room shelf | T82: Informational | U82: 5 | V82: =VLOOKUP(S82,'Keyword cả 2 web trong top 10'!A:G,7,0) -> #N/A
A83: https://ashdeco.com/blogs/news/display-shelf-ideas-for-small-collectibles-and-curated-objects | B83: Blog | C83: 0.22 | D83: 16 | E83: 36 | F83: 0 | G83: 10 | H83: 9 | I83: 0 | J83: 2 | K83: 0 | L83: 31 | M83: 16 | N83: 0 | O83: 1 | P83: 0 | Q83: 23 | R83: google-ai, search-gpt | S83: stylish shelf for bedroom displaying collectibles | T83: Commercial | U83: 14 | V83: =VLOOKUP(S83,'Keyword cả 2 web trong top 10'!A:G,7,0) -> #N/A
A84: https://ashdeco.com/blogs/buying-guides/right-bookshelf-height-for-room | B84: Blog | C84: 0.22 | D84: 106 | E84: 36 | F84: 0 | G84: 11 | H84: 50 | I84: 0 | J84: 2 | K84: 0 | L84: 6 | M84: 31 | N84: 0 | O84: 8 | P84: 0 | Q84: -115 | R84: google, google-ai, search-gpt | S84: standard bookshelf height between shelves | T84: Informational | U84: 53 | V84: =VLOOKUP(S84,'Keyword cả 2 web trong top 10'!A:G,7,0) -> 8
A85: https://ashdeco.com/blogs/news/cat-tree-height-guide-room-ceiling | B85: Blog | C85: 0.22 | D85: 9 | E85: 35 | F85: 0 | G85: 4 | H85: 1 | I85: 0 | J85: 0 | K85: 0 | L85: 35 | M85: 0 | N85: 0 | O85: 0 | P85: 0 | Q85: -46 | R85: gemini, google-ai, search-gpt | S85: large cat tree | T85: Commercial | U85: 3 | V85: =VLOOKUP(S85,'Keyword cả 2 web trong top 10'!A:G,7,0) -> #N/A
A86: https://ashdeco.com/blogs/buying-guides/wooden-headboard-buying-guide | B86: Blog | C86: 0.21 | D86: 1 | E86: 34 | F86: 0 | G86: 1 | H86: 1 | I86: 0 | J86: 0 | K86: 0 | L86: 34 | M86: 34 | N86: 0 | O86: 0 | P86: 0 | Q86: -9 | R86: google, google-ai, search-gpt | S86: wooden headboard | T86: Commercial, Informational | U86: 51 | V86: =VLOOKUP(S86,'Keyword cả 2 web trong top 10'!A:G,7,0) -> #N/A
A87: https://ashdeco.com/blogs/room-ideas/wood-floor-lamp-styles-guide | B87: Blog | C87: 0.21 | D87: 5 | E87: 33 | F87: 0 | G87: 5 | H87: 1 | I87: 0 | J87: 0 | K87: 0 | L87: 33 | M87: 33 | N87: 0 | O87: 0 | P87: 0 | Q87: 33 | R87: search-gpt | S87: tree lamp | T87: Commercial | U87: 7 | V87: =VLOOKUP(S87,'Keyword cả 2 web trong top 10'!A:G,7,0) -> #N/A
A88: https://ashdeco.com/blogs/room-ideas/small-coffee-table-ideas-apartments | B88: Blog | C88: 0.2 | D88: 12 | E88: 32 | F88: 0 | G88: 11 | H88: 3 | I88: 0 | J88: 0 | K88: 0 | L88: 32 | M88: 12 | N88: 0 | O88: 0 | P88: 0 | Q88: 32 | R88: google, search-gpt | S88: coffee tables for small spaces | T88: Commercial | U88: 8 | V88: =VLOOKUP(S88,'Keyword cả 2 web trong top 10'!A:G,7,0) -> #N/A
... A95: https://ashdeco.com/blogs/buying-guides/eco-friendly-coat-racks-sustainable-wood | B95: Blog | C95: 0.17 | D95: 1 | E95: 27 | F95: 0 | G95: 1 | H95: 0 | I95: 0 | J95: 0 | K95: 0 | L95: 27 | M95: 0 | N95: 0 | O95: 0 | P95: 0 | Q95: 27 | R95: google-ai, search-gpt | S95: wooden coat rack | T95: Commercial | U95: 37 | V95: =VLOOKUP(S95,'Keyword cả 2 web trong top 10'!A:G,7,0) -> #N/A
A96: https://ashdeco.com/blogs/room-ideas/coat-rack-for-renters | B96: Blog | C96: 0.16 | D96: 2 | E96: 26 | F96: 0 | G96: 2 | H96: 0 | I96: 0 | J96: 0 | K96: 0 | L96: 26 | M96: 0 | N96: 0 | O96: 0 | P96: 0 | Q96: 26 | S96: coat stand | T96: Commercial | U96: 0 | V96: =VLOOKUP(S96,'Keyword cả 2 web trong top 10'!A:G,7,0) -> #N/A
A97: https://ashdeco.com/collections/floating-shelves-for-laundry-room | B97: Collection | C97: 0.16 | D97: 55 | E97: 26 | F97: 0 | G97: 4 | H97: 25 | I97: 0 | J97: 2 | K97: 0 | L97: 6 | M97: 17 | N97: 0 | O97: 0 | P97: 0 | Q97: 24 | R97: google | S97: floating shelves laundry room | T97: Informational | U97: 4 | V97: =VLOOKUP(S97,'Keyword cả 2 web trong top 10'!A:G,7,0) -> #N/A
A98: https://ashdeco.com/blogs/buying-guides/tv-cabinet-dimensions-by-screen-size | B98: Blog | C98: 0.16 | D98: 80 | E98: 26 | F98: 0 | G98: 34 | H98: 36 | I98: 0 | J98: 0 | K98: 0 | L98: 4 | M98: 22 | N98: 0 | O98: 0 | P98: 0 | Q98: -8 | R98: gemini, google, google-ai, search-gpt | S98: how wide is a 50 tv | T98: Informational | U98: 41 | V98: =VLOOKUP(S98,'Keyword cả 2 web trong top 10'!A:G,7,0) -> #N/A
A99: https://ashdeco.com/blogs/news/store-bought-vs-handmade-bookshelves | B99: Blog | C99: 0.16 | D99: 3 | E99: 26 | F99: 0 | G99: 3 | H99: 3 | I99: 0 | J99: 0 | K99: 0 | L99: 26 | M99: 26 | N99: 0 | O99: 0 | P99: 0 | Q99: 26 | R99: search-gpt | S99: store bought vs. handmade bookshelves | T99: Commercial, Informational | U99: 19 | V99: =VLOOKUP(S99,'Keyword cả 2 web trong top 10'!A:G,7,0) -> #N/A
A100: https://ashdeco.com/blogs/news/tagged/glowledge-floating-shelf | B100: Blog | C100: 0.15 | D100: 1 | E100: 24 | F100: 0 | G100: 1 | H100: 0 | I100: 0 | J100: 0 | K100: 0 | L100: 24 | M100: 0 | N100: 0 | O100: 0 | P100: 0 | Q100: 0 | S100: glowledge floating shelf | T100: Commercial | U100: 0 | V100: =VLOOKUP(S100,'Keyword cả 2 web trong top 10'!A:G,7,0) -> #N/A
A101: https://ashdeco.com/collections/desk | B101: Collection | C101: 0.15 | D101: 11 | E101: 24 | F101: 0 | G101: 1 | H101: 3 | I101: 0 | J101: 0 | K101: 0 | L101: 0 | M101: 24 | N101: 0 | O101: 0 | P101: 0 | Q101: 24 | S101: leif desk: black ash - the design tap | T101: Informational | U101: 0 | V101: =VLOOKUP(S101,'Keyword cả 2 web trong top 10'!A:G,7,0) -> #N/A
A102: https://ashdeco.com/products/artisan-sculptural-tree-plant-stand-hand-carved-solid-wood-indoor-display | B102: Product | C102: 0.15 | D102: 5 | E102: 24 | F102: 0 | G102: 3 | H102: 3 | I102: 0 | J102: 0 | K102: 0 | L102: 24 | M102: 24 | N102: 0 | O102: 0 | P102: 0 | Q102: 24 | R102: gemini, search-gpt | S102: carved wood plant stand | T102: Commercial, Informational | U102: 3 | V102: =VLOOKUP(S102,'Keyword cả 2 web trong top 10'!A:G,7,0) -> #N/A
A103: https://ashdeco.com/blogs/buying-guides/coffee-table-dimensions | B103: Blog | C103: 0.14 | D103: 106 | E103: 23 | F103: 0 | G103: 34 | H103: 4 | I103: 0 | J103: 1 | K103: 0 | L103: 16 | M103: 7 | N103: 0 | O103: 0 | P103: 0 | Q103: 23 | R103: google, google-ai, search-gpt | S103: round wooden coffee table | T103: Commercial | U103: 7 | V103: =VLOOKUP(S103,'Keyword cả 2 web trong top 10'!A:G,7,0) -> #N/A
A104: https://ashdeco.com/blogs/news/entryway-bench-storage-solid-wood-vs-particle-board | B104: Blog | C104: 0.14 | D104: 4 | E104: 22 | F104: 0 | G104: 4 | H104: 0 | I104: 0 | J104: 0 | K104: 0 | L104: 22 | M104: 0 | N104: 0 | O104: 0 | P104: 0 | Q104: 22 | R104: google-ai | S104: storage benches | T104: Commercial | U104: 2 | V104: =VLOOKUP(S104,'Keyword cả 2 web trong top 10'!A:G,7,0) -> #N/A
A105: https://ashdeco.com/blogs/buying-guides/best-cat-condo-large-cats-heavy-duty | B105: Blog | C105: 0.13 | D105: 10 | E105: 21 | F105: 0 | G105: 8 | H105: 1 | I105: 0 | J105: 0 | K105: 0 | L105: 21 | M105: 3 | N105: 0 | O105: 0 | P105: 0 | Q105: 2 | R105: google, google-ai, search-gpt | S105: best cat condo for big cats | T105: Commercial | U105: 8 | V105: =VLOOKUP(S105,'Keyword cả 2 web trong top 10'!A:G,7,0) -> #N/A
A106: https://ashdeco.com/products/driftwood-floating-shelf-rustic-tree-branch-wall-art-handmade-bookshelf | B106: Product | C106: 0.13 | D106: 9 | E106: 21 | F106: 0 | G106: 4 | H106: 6 | I106: 0 | J106: 1 | K106: 0 | L106: 21 | M106: 20 | N106: 0 | O106: 0 | P106: 0 | Q106: 21 | S106: driftwood shelves | T106: Informational | U106: 0 | V106: =VLOOKUP(S106,'Keyword cả 2 web trong top 10'!A:G,7,0) -> #N/A
A107: https://ashdeco.com/blogs/room-ideas/hallway-console-table-size | B107: Blog | C107: 0.12 | D107: 11 | E107: 20 | F107: 0 | G107: 5 | H107: 3 | I107: 0 | J107: 0 | K107: 0 | L107: 20 | M107: 0 | N107: 0 | O107: 0 | P107: 0 | Q107: 20 | R107: google, google-ai | S107: entryway console table | T107: Commercial | U107: 3 | V107: =VLOOKUP(S107,'Keyword cả 2 web trong top 10'!A:G,7,0) -> #N/A
A108: https://ashdeco.com/blogs/news/bookshelf-height-guide-2026 | B108: Blog | C108: 0.12 | D108: 99 | E108: 20 | F108: 0 | G108: 7 | H108: 21 | I108: 0 | J108: 0 | K108: 0 | L108: 3 | M108: 17 | N108: 0 | O108: 0 | P108: 0 | Q108: -179 | R108: gemini, google, google-ai, search-gpt | S108: standard bookshelf height | T108: Informational | U108: 24 | V108: =VLOOKUP(S108,'Keyword cả 2 web trong top 10'!A:G,7,0) -> 9
A109: https://ashdeco.com/blogs/room-ideas/mushroom-decor-trend-analysis | B109: Blog | C109: 0.12 | D109: 4 | E109: 19 | F109: 0 | G109: 0 | H109: 4 | I109: 0 | J109: 2 | K109: 0 | L109: 0 | M109: 19 | N109: 0 | O109: 14 | P109: 0 | Q109: 19 | R109: search-gpt | S109: mushroom kitchen decor | T109: Informational | U109: 6 | V109: =VLOOKUP(S109,'Keyword cả 2 web trong top 10'!A:G,7,0) -> #N/A
A110: https://ashdeco.com/blogs/news/unique-cat-trees-for-large-cats | B110: Blog | C110: 0.12 | D110: 12 | E110: 19 | F110: 0 | G110: 10 | H110: 0 | I110: 0 | J110: 0 | K110: 0 | L110: 19 | M110: 0 | N110: 0 | O110: 0 | P110: 0 | Q110: 0 | R110: google-ai, search-gpt | S110: unique cat trees for large cats | T110: Commercial | U110: 2 | V110: =VLOOKUP(S110,'Keyword cả 2 web trong top 10'!A:G,7,0) -> #N/A
A111: https://ashdeco.com/blogs/buying-guides/cat-tree-for-senior-cats | B111: Blog | C111: 0.11 | D111: 9 | E111: 18 | F111: 0 | G111: 9 | H111: 0 | I111: 0 | J111: 0 | K111: 0 | L111: 18 | M111: 0 | N111: 0 | O111: 0 | P111: 0 | Q111: 18 | R111: google | S111: cat trees for senior cats | T111: Commercial | U111: 4 | V111: =VLOOKUP(S111,'Keyword cả 2 web trong top 10'!A:G,7,0) -> #N/A
A112: https://ashdeco.com/products/handmade-solid-wood-tree-wall-shelf-functional-wall-art-decor | B112: Product | C112: 0.1 | D112: 3 | E112: 17 | F112: 0 | G112: 3 | H112: 3 | I112: 0 | J112: 0 | K112: 0 | L112: 17 | M112: 17 | N112: 0 | O112: 0 | P112: 0 | Q112: 15 | S112: tree wall bookshelf | T112: Commercial, Informational | U112: 0 | V112: =VLOOKUP(S112,'Keyword cả 2 web trong top 10'!A:G,7,0) -> 1
A113: https://ashdeco.com/blogs/room-ideas/floating-shelves-living-room-styling-ideas | B113: Blog | C113: 0.1 | D113: 29 | E113: 17 | F113: 0 | G113: 7 | H113: 22 | I113: 0 | J113: 2 | K113: 0 | L113: 2 | M113: 15 | N113: 0 | O113: 6 | P113: 0 | Q113: 16 | R113: gemini, google, google-ai, search-gpt | S113: floating shelf living room ideas | T113: Informational | U113: 51 | V113: =VLOOKUP(S113,'Keyword cả 2 web trong top 10'!A:G,7,0) -> 5
A114: https://ashdeco.com/collections/console-tables | B114: Collection | C114: 0.1 | D114: 37 | E114: 16 | F114: 0 | G114: 16 | H114: 9 | I114: 0 | J114: 1 | K114: 0 | L114: 10 | M114: 6 | N114: 0 | O114: 2 | P114: 0 | Q114: 9 | R114: google-ai, search-gpt | S114: solid wood console table | T114: Commercial | U114: 10 | V114: =VLOOKUP(S114,'Keyword cả 2 web trong top 10'!A:G,7,0) -> #N/A
A115: https://ashdeco.com/collections/tv-cabinets | B115: Collection | C115: 0.1 | D115: 118 | E115: 16 | F115: 0 | G115: 16 | H115: 9 | I115: 0 | J115: 2 | K115: 0 | L115: 4 | M115: 0 | N115: 0 | O115: 0 | P115: 0 | Q115: 14 | R115: google, google-ai, search-gpt | S115: tv shelf | T115: Commercial | U115: 4 | V115: =VLOOKUP(S115,'Keyword cả 2 web trong top 10'!A:G,7,0) -> #N/A
A116: https://ashdeco.com/blogs/room-ideas/coat-rack-with-shoe-storage-entryway | B116: Blog | C116: 0.09 | D116: 16 | E116: 15 | F116: 0 | G116: 11 | H116: 5 | I116: 0 | J116: 5 | K116: 0 | L116: 11 | M116: 4 | N116: 0 | O116: 4 | P116: 0 | Q116: 11 | R116: google, google-ai, search-gpt | S116: hallway coat and shoe storage | T116: Commercial | U116: 6 | V116: =VLOOKUP(S116,'Keyword cả 2 web trong top 10'!A:G,7,0) -> #N/A
A117: https://ashdeco.com/blogs/room-ideas/floating-shelves-for-kitchen-ideas-that-work | B117: Blog | C117: 0.08 | D117: 7 | E117: 14 | F117: 0 | G117: 4 | H117: 3 | I117: 0 | J117: 1 | K117: 0 | L117: 13 | M117: 1 | N117: 0 | O117: 0 | P117: 0 | Q117: 14 | S117: floating shelves kitchen | T117: Commercial | U117: 0 | V117: =VLOOKUP(S117,'Keyword cả 2 web trong top 10'!A:G,7,0) -> #N/A
A118: https://ashdeco.com/blogs/news/mushroom-decor-ideas | B118: Blog | C118: 0.08 | D118: 4 | E118: 13 | F118: 0 | G118: 1 | H118: 3 | I118: 0 | J118: 0 | K118: 0 | L118: 0 | M118: 13 | N118: 0 | O118: 0 | P118: 0 | Q118: 0 | R118: gemini, google-ai, search-gpt | S118: mushroom shelf decor | T118: Informational | U118: 16 | V118: =VLOOKUP(S118,'Keyword cả 2 web trong top 10'!A:G,7,0) -> 6
A119: https://ashdeco.com/blogs/news/behind-couch-table-console-worth-it | B119: Blog | C119: 0.08 | D119: 49 | E119: 13 | F119: 0 | G119: 11 | H119: 19 | I119: 0 | J119: 2 | K119: 0 | L119: 7 | M119: 13 | N119: 0 | O119: 1 | P119: 0 | Q119: 1 | R119: google | S119: table behind couch against wall | T119: Informational | U119: 4 | V119: =VLOOKUP(S119,'Keyword cả 2 web trong top 10'!A:G,7,0) -> #N/A
A120: https://ashdeco.com/blogs/news/custom-coat-racks-handcrafted | B120: Blog | C120: 0.08 | D120: 2 | E120: 13 | F120: 0 | G120: 1 | H120: 1 | I120: 0 | J120: 0 | K120: 0 | L120: 13 | M120: 0 | N120: 0 | O120: 0 | P120: 0 | Q120: 13 | R120: google, search-gpt | S120: wooden coat rack | T120: Commercial, Informational | U120: 9 | V120: =VLOOKUP(S120,'Keyword cả 2 web trong top 10'!A:G,7,0) -> #N/A
A121: https://ashdeco.com/blogs/buying-guides/tree-bookshelf-designs | B121: Blog | C121: 0.07 | D121: 2 | E121: 12 | F121: 0 | G121: 0 | H121: 2 | I121: 0 | J121: 0 | K121: 0 | L121: 0 | M121: 12 | N121: 0 | O121: 0 | P121: 0 | Q121: 12 | R121: google, google-ai, search-gpt | S121: tree book shelf | T121: Informational | U121: 9 | V121: =VLOOKUP(S121,'Keyword cả 2 web trong top 10'!A:G,7,0) -> 3
A122: https://ashdeco.com/blogs/room-ideas/corner-shelves-living-room-ideas | B122: Blog | C122: 0.07 | D122: 48 | E122: 11 | F122: 0 | G122: 32 | H122: 18 | I122: 0 | J122: 2 | K122: 0 | L122: 0 | M122: 11 | N122: 0 | O122: 0 | P122: 0 | Q122: 6 | R122: gemini, google, google-ai, search-gpt | S122: corner rack for living room | T122: Commercial | U122: 13 | V122: =VLOOKUP(S122,'Keyword cả 2 web trong top 10'!A:G,7,0) -> #N/A
A123: https://ashdeco.com/products/solid-wood-floating-bathroom-vanity-wave-carved | B123: Product | C123: 0.07 | D123: 1 | E123: 11 | F123: 0 | G123: 1 | H123: 1 | I123: 0 | J123: 0 | K123: 0 | L123: 11 | M123: 11 | N123: 0 | O123: 0 | P123: 0 | Q123: 11 | S123: suncharm minimalist bathroom vanities wave texture floating cabinet | T123: Commercial, Informational | U123: 0 | V123: =VLOOKUP(S123,'Keyword cả 2 web trong top 10'!A:G,7,0) -> #N/A
A124: https://ashdeco.com/blogs/news/best-record-player-stands-2026 | B124: Blog | C124: 0.06 | D124: 1 | E124: 10 | F124: 0 | G124: 1 | H124: 0 | I124: 0 | J124: 0 | K124: 0 | L124: 10 | M124: 0 | N124: 0 | O124: 0 | P124: 0 | Q124: 10 | R124: gemini, search-gpt | S124: turntable stand | T124: Commercial | U124: 6 | V124: =VLOOKUP(S124,'Keyword cả 2 web trong top 10'!A:G,7,0) -> #N/A
A125: https://ashdeco.com/collections/corner-bathroom-vanities | B125: Collection | C125: 0.06 | D125: 13 | E125: 10 | F125: 0 | G125: 7 | H125: 5 | I125: 0 | J125: 1 | K125: 0 | L125: 0 | M125: 10 | N125: 0 | O125: 1 | P125: 0 | Q125: 1 | R125: google, google-ai, search-gpt | S125: two seprate vanities kittie corner | T125: Commercial | U125: 13 | V125: =VLOOKUP(S125,'Keyword cả 2 web trong top 10'!A:G,7,0) -> 10
A126: https://ashdeco.com/blogs/news/corner-bookshelf-vs-bookcase | B126: Blog | C126: 0.06 | D126: 11 | E126: 10 | F126: 0 | G126: 7 | H126: 7 | I126: 0 | J126: 0 | K126: 0 | L126: 10 | M126: 2 | N126: 0 | O126: 0 | P126: 0 | Q126: 2 | R126: google-ai, search-gpt | S126: bookcase vs bookshelf | T126: Commercial, Informational | U126: 21 | V126: =VLOOKUP(S126,'Keyword cả 2 web trong top 10'!A:G,7,0) -> #N/A
A127: https://ashdeco.com/blogs/news/woodland-nursery-ideas-enchanted-forest-for-baby | B127: Blog | C127: 0.05 | D127: 6 | E127: 9 | F127: 0 | G127: 3 | H127: 4 | I127: 0 | J127: 0 | K127: 0 | L127: 5 | M127: 6 | N127: 0 | O127: 0 | P127: 0 | Q127: 6 | R127: gemini, google-ai, search-gpt | S127: enchanted forest nursery ideas | T127: Informational | U127: 13 | V127: =VLOOKUP(S127,'Keyword cả 2 web trong top 10'!A:G,7,0) -> #N/A
A128: https://ashdeco.com/blogs/news/corner-shelves-small-spaces | B128: Blog | C128: 0.05 | D128: 18 | E128: 9 | F128: 0 | G128: 14 | H128: 5 | I128: 0 | J128: 0 | K128: 0 | L128: 9 | M128: 0 | N128: 0 | O128: 0 | P128: 0 | Q128: 9 | R128: gemini, google, google-ai, search-gpt | S128: corner bookshelf for small spaces | T128: Commercial | U128: 31 | V128: =VLOOKUP(S128,'Keyword cả 2 web trong top 10'!A:G,7,0) -> #N/A
A129: https://ashdeco.com/blogs/buying-guides/how-tall-is-a-bathroom-vanity | B129: Blog | C129: 0.05 | D129: 58 | E129: 9 | F129: 0 | G129: 1 | H129: 40 | I129: 0 | J129: 0 | K129: 0 | L129: 0 | M129: 9 | N129: 0 | O129: 0 | P129: 0 | Q129: 3 | R129: gemini, google | S129: standard vanity height | T129: Informational | U129: 3 | V129: =VLOOKUP(S129,'Keyword cả 2 web trong top 10'!A:G,7,0) -> #N/A
...

Sheet Keyword cả 2 web trong top 10
A1: Keyword | B1: Intents | C1: Volume | D1: Keyword Difficulty | E1: CPC | F1: Competition Density | G1: ashdeco.com | H1: spryinterior.com | I1: ashdeco.com (pages) | J1: spryinterior.com (pages) | K1: Results
A2: condo for large cats | B2: Commercial | C2: 40 | D2: 20 | E2: 0,49 | F2: 1,00 | G2: 6 | H2: 9 | I2: https://ashdeco.com/blogs/buying-guides/best-cat-condo-large-cats-heavy-duty | J2: https://www.spryinterior.com/blogs/news/largest-cat-condo | K2: 189
A3: tree bookshelf measurements | B3: Informational, Transactional | C3: 70 | D3: 10 | E3: 0,00 | F3: 1,00 | G3: 5 | H3: 3 | I3: https://ashdeco.com/blogs/buying-guides/corner-tree-bookshelf-measure-guide | J3: https://www.spryinterior.com/blogs/news/diy-tree-bookshelf-plans-the-most-detailed-instructions | K3: 179
A4: weight limit for floating shelves | B4: Informational | C4: 50 | D4: 4 | E4: 0,86 | F4: 1,00 | G4: 4 | H4: 9 | I4: https://ashdeco.com/blogs/buying-guides/floating-shelf-weight-limit-guide | J4: https://www.spryinterior.com/blogs/news/can-floating-shelves-hold-a-lot-of-weight | K4: 116
A5: how to choose a coat rack | B5: Informational | C5: 70 | D5: 2 | E5: 0,00 | F5: 0,00 | G5: 1 | H5: 7 | I5: https://ashdeco.com/blogs/buying-guides/how-to-choose-coat-rack-2026 | J5: https://www.spryinterior.com/blogs/news/where-to-put-coat-rack | K5: 154
A6: floating shelf height | B6: Informational | C6: 110 | D6: 12 | E6: 0,00 | F6: 0,90 | G6: 4 | H6: 1 | I6: https://ashdeco.com/blogs/buying-guides/kitchen-shelf-spacing-height-guide | J6: https://www.spryinterior.com/blogs/news/what-is-the-rule-for-floating-shelves | K6: 186
A7: floating shelf measurements | B7: Informational | C7: 110 | D7: 20 | E7: 0,52 | F7: 0,93 | G7: 9 | H7: 8 | I7: https://ashdeco.com/blogs/buying-guides/kitchen-shelf-spacing-height-guide | J7: https://www.spryinterior.com/blogs/news/what-is-the-average-depth-of-a-floating-shelf | K7: 10800000
A8: typical shelf height | B8: Informational | C8: 110 | D8: 10 | E8: 0,00 | F8: 0,12 | G8: 3 | H8: 10 | I8: https://ashdeco.com/blogs/buying-guides/kitchen-shelf-spacing-height-guide | J8: https://www.spryinterior.com/blogs/news/what-is-the-ideal-bookshelf-shelf-spacing | K8: 128
A9: floating shelf height from floor | B9: Informational | C9: 90 | D9: 0 | E9: 0,00 | F9: 0,61 | G9: 6 | H9: 1 | I9: https://ashdeco.com/blogs/buying-guides/kitchen-shelf-spacing-height-guide | J9: https://www.spryinterior.com/blogs/news/what-is-the-rule-for-floating-shelves | K9: 140
A10: floating shelf spacing | B10: Informational | C10: 90 | D10: 13 | E10: 0,00 | F10: 0,93 | G10: 3 | H10: 10 | I10: https://ashdeco.com/blogs/buying-guides/kitchen-shelf-spacing-height-guide | J10: https://www.spryinterior.com/blogs/news/what-is-the-rule-for-floating-shelves | K10: 177
A11: floating shelves height | B11: Informational | C11: 90 | D11: 4 | E11: 0,00 | F11: 0,95 | G11: 4 | H11: 2 | I11: https://ashdeco.com/blogs/buying-guides/kitchen-shelf-spacing-height-guide | J11: https://www.spryinterior.com/blogs/news/what-is-the-rule-for-floating-shelves | K11: 182
A12: floating shelves height from floor | B12: Informational | C12: 90 | D12: 2 | E12: 0,00 | F12: 0,61 | G12: 5 | H12: 1 | I12: https://ashdeco.com/blogs/buying-guides/kitchen-shelf-spacing-height-guide | J12: https://www.spryinterior.com/blogs/news/what-is-the-rule-for-floating-shelves | K12: 162
A13: how high to hang floating shelves | B13: Informational | C13: 90 | D13: 13 | E13: 0,00 | F13: 0,06 | G13: 9 | H13: 2 | I13: https://ashdeco.com/blogs/buying-guides/kitchen-shelf-spacing-height-guide | J13: https://www.spryinterior.com/blogs/news/what-is-the-rule-for-floating-shelves | K13: 140
... A336: book tree shelves | B336: Commercial | C336: 260 | D336: 21 | E336: 0,52 | F336: 0,94 | G336: 7 | H336: 2 | I336: https://ashdeco.com/products/wood-tree-bookshelves-handmade-mahogany-floating-book-tree-with-large-shelves | J336: https://www.spryinterior.com/collections/tree-bookshelves | K336: 219

Sheet Collection tree-bookshelf
A1: Keyword | B1: Position | C1: Previous position | D1: Search Volume | E1: Keyword Difficulty | F1: CPC | G1: URL | H1: Traffic | I1: Traffic (%) | J1: Traffic Cost | K1: Competition | L1: Number of Results | M1: Trends | N1: Timestamp | O1: SERP Features by Keyword | P1: Keyword Intents | Q1: Position Type
A2: tree bookshelf | B2: 1 | C2: 3 | D2: 8100 | E2: 30 | F2: 0,52 | G2: https://ashdeco.com/collections/tree-bookshelf | H2: 194 | I2: 22,93 | J2: 100 | K2: 0,94 | L2: 216 | M2: 54, 54, 54, 66, 44, 36, 54, 54, 66, 54, 54, 100 | N2: 25/07/2026 | O2: Image pack, Sitelinks, Reviews, Video, Image, Popular products, Related searches, Short videos, Things to know, Discussions and forums | P2: informational | Q2: Organic
A3: tree branch bookshelf | B3: 1 | C3: 9 | D3: 720 | E3: 18 | F3: 0,47 | G3: https://ashdeco.com/collections/tree-bookshelf | H3: 178 | I3: 21,04 | J3: 83 | K3: 0,5 | L3: 8 | M3: 13, 13, 16, 13, 13, 13, 10, 13, 20, 13, 13, 100 | N3: 27/07/2026 | O3: Image pack, Sitelinks, People also ask, Popular products, Related searches, Discussions and forums | P3: informational | Q3: Organic
A4: tree shelf | B4: 1 | C4: 8 | D4: 1600 | E4: 27 | F4: 0,47 | G4: https://ashdeco.com/collections/tree-bookshelf | H4: 131 | I4: 15,48 | J4: 61 | K4: 1 | L4: 209 | M4: 44, 55, 34, 44, 34, 65, 55, 55, 55, 34, 44, 100 | N4: 22/07/2026 | O4: Image pack, Sitelinks, Video, Image, People also ask, Popular products, Related searches, Short videos | P4: informational | Q4: Organic
A5: tree branch shelves | B5: 1 | C5: 7 | D5: 260 | E5: 25 | F5: 0,38 | G5: https://ashdeco.com/collections/tree-bookshelf | H5: 34 | I5: 4,01 | J5: 12 | K5: 1 | L5: 229 | M5: 23, 9, 23, 19, 23, 23, 29, 36, 54, 44, 54, 100 | N5: 26/07/2026 | O5: Image pack, Sitelinks, Video, Video Carousel, People also ask, Popular products, Related searches, Short videos, Discussions and forums | P5: informational | Q5: Organic
A6: bookshelf tree | B6: 1 | C6: 9 | D6: 390 | E6: 10 | F6: 0,52 | G6: https://ashdeco.com/collections/tree-bookshelf | H6: 31 | I6: 3,66 | J6: 16 | K6: 0,94 | L6: 10 | M6: 7, 13, 3, 1, 8, 10, 1, 1, 0, 0, 1, 80 | N6: 18/07/2026 | O6: Image pack, Sitelinks, People also ask, Popular products, Related searches | P6: informational | Q6: Organic
A7: tree wall bookshelf | B7: 1 | C7: 6 | D7: 320 | E7: 22 | F7: 0,56 | G7: https://ashdeco.com/collections/tree-bookshelf | H7: 26 | I7: 3,07 | J7: 14 | K7: 0,2 | L7: 238 | M7: 2, 3, 3, 5, 3, 8, 10, 7, 8, 4, 3, 100 | N7: 24/07/2026 | O7: Image pack, Sitelinks, Reviews, Video, Popular products, Related searches, Short videos, Discussions and forums | P7: commercial, informational | Q7: Organic
A8: solid wood tree bookshelf | B8: 2 | C8: 2 | D8: 390 | E8: 22 | F8: 0,51 | G8: https://ashdeco.com/collections/tree-bookshelf | H8: 25 | I8: 2,95 | J8: 12 | K8: 0,13 | L8: 228 | M8: 0, 0, 4, 3, 2, 0, 0, 0, 1, 1, 0, 100 | N8: 30/06/2026 | O8: Sitelinks, Video, Video Carousel, Popular products, Related searches | P8: commercial | Q8: Organic
A9: floating tree bookshelf | B9: 2 | C9: 0 | D9: 140 | E9: 21 | F9: 0,42 | G9: https://ashdeco.com/collections/tree-bookshelf | H9: 18 | I9: 2,12 | J9: 7 | K9: 0,07 | L9: 246 | M9: 1, 1, 1, 1, 1, 1, 1, 1, 1, 1, 1, 100 | N9: 13/07/2026 | O9: Image pack, Sitelinks, Video, Image, Video Carousel, Popular products, Related searches, Short videos | P9: informational | Q9: Organic
A10: wooden tree bookcase | B10: 1 | C10: 9 | D10: 260 | E10: 24 | F10: 0,66 | G10: https://ashdeco.com/collections/tree-bookshelf | H10: 16 | I10: 1,89 | J10: 10 | K10: 0,45 | L10: 235 | M10: 15, 19, 19, 54, 36, 23, 23, 23, 19, 12, 19, 100 | N10: 46302 | O10: Sitelinks, Video, Video Carousel, People also ask, Popular products, Related searches, Short videos | P10: commercial | Q10: Organic
A11: tree shelves | B11: 3 | C11: 3 | D11: 210 | E11: 23 | F11: 0,52 | G11: https://ashdeco.com/collections/tree-bookshelf | H11: 13 | I11: 1,53 | J11: 6 | K11: 1 | L11: 214 | M11: 82, 82, 100, 100, 100, 66, 5, 5, 5, 23, 0, 10 | N11: 13/06/2026 | O11: Image pack, Sitelinks, Video, Image, Shopping ads, Popular products, Related searches | P11: commercial, informational | Q11: Organic
A12: wall tree bookshelf | B12: 2 | C12: 3 | D12: 170 | E12: 22 | F12: 0,56 | G12: https://ashdeco.com/collections/tree-bookshelf | H12: 13 | I12: 1,53 | J12: 7 | K12: 0,2 | L12: 261 | M12: 10, 12, 15, 15, 15, 7, 23, 12, 7, 5, 7, 100 | N12: 23/07/2026 | O12: Image pack, Sitelinks, Reviews, Video, Video Carousel, Popular products, Related searches, Short videos | P12: commercial, informational | Q12: Organic
A13: tree branch bookcase | B13: 3 | C13: 7 | D13: 170 | E13: 0 | F13: 0,47 | G13: https://ashdeco.com/collections/tree-bookshelf | H13: 11 | I13: 1,3 | J13: 5 | K13: 0,5 | L13: 9 | M13: 100, 23, 53, 53, 28, 28, 23, 66, 53, 35, 53, 35 | N13: 19/07/2026 | O13: Image pack, Sitelinks, Related searches | P13: informational | Q13: Organic
A14: wood tree bookshelf | B14: 1 | C14: 5 | D14: 140 | E14: 21 | F14: 0,66 | G14: https://ashdeco.com/collections/tree-bookshelf | H14: 11 | I14: 1,3 | J14: 7 | K14: 0,45 | L14: 236 | M14: 9, 9, 15, 19, 23, 23, 6, 6, 15, 9, 12, 100 | N14: 29/07/2026 | O14: Image pack, Sitelinks, Reviews, Video, Popular products, Related searches, Short videos, Discussions and forums | P14: informational | Q14: Organic
A15: wooden tree bookshelf | B15: 3 | C15: 6 | D15: 320 | E15: 22 | F15: 0,66 | G15: https://ashdeco.com/collections/tree-bookshelf | H15: 11 | I15: 1,3 | J15: 7 | K15: 0,45 | L15: 268 | M15: 17, 21, 26, 39, 48, 26, 21, 26, 26, 17, 21, 100 | N15: 22/07/2026 | O15: Image pack, Sitelinks, Reviews, Video, Image, Popular products, Related searches, Short videos | P15: informational | Q15: Organic
A16: tree trunk bookshelf | B16: 1 | C16: 4 | D16: 70 | E16: 9 | F16: 0,51 | G16: https://ashdeco.com/collections/tree-bookshelf | H16: 9 | I16: 1,06 | J16: 4 | K16: 1 | L16: 261 | M16: 19, 26, 19, 34, 26, 26, 19, 26, 26, 7, 42, 42 | N16: 14/07/2026 | O16: Image pack, Sitelinks, Video, Video Carousel, Popular products, Related searches, Short videos | P16: commercial, informational | Q16: Organic
A17: wooden tree shelf | B17: 3 | C17: 3 | D17: 140 | E17: 26 | F17: 0,48 | G17: https://ashdeco.com/collections/tree-bookshelf | H17: 9 | I17: 1,06 | J17: 4 | K17: 1 | L17: 261 | M17: 17, 28, 28, 35, 43, 53, 43, 53, 43, 43, 28, 35 | N17: 19/06/2026 | O17: Image pack, Sitelinks, Video, People also ask, Popular products, Related searches | P17: commercial, informational | Q17: Organic
A18: tree floating shelf | B18: 2 | C18: 8 | D18: 110 | E18: 21 | F18: 0,54 | G18: https://ashdeco.com/collections/tree-bookshelf | H18: 9 | I18: 1,06 | J18: 4 | K18: 1 | L18: 247 | M18: 64, 64, 52, 64, 82, 64, 100, 82, 82, 64, 64, 52 | N18: 46180 | O18: Image pack, Sitelinks, Video, Video Carousel, Popular products, Related searches | P18: commercial, informational | Q18: Organic
A19: wall shelf tree | B19: 2 | C19: 2 | D19: 110 | E19: 21 | F19: 0,51 | G19: https://ashdeco.com/collections/tree-bookshelf | H19: 9 | I19: 1,06 | J19: 4 | K19: 1 | L19: 266 | M19: 53, 26, 26, 19, 53, 15, 34, 100, 34, 65, 34, 19 | N19: 16/06/2026 | O19: Image pack, Sitelinks, Video, Video Carousel, Popular products, Related searches, Short videos | P19: commercial, informational | Q19: Organic
A20: branch bookshelf | B20: 2 | C20: 0 | D20: 90 | E20: 22 | F20: 0,7 | G20: https://ashdeco.com/collections/tree-bookshelf | H20: 7 | I20: 0,82 | J20: 4 | K20: 0,65 | L20: 245 | M20: 42, 26, 34, 26, 26, 26, 26, 26, 34, 26, 26, 100 | N20: 24/07/2026 | O20: Image pack, Sitelinks, Video, Image, Popular products, Related searches, Short videos, Discussions and forums | P20: commercial, informational | Q20: Organic
A21: tree bookcase | B21: 6 | C21: 5 | D21: 4400 | E21: 31 | F21: 0,52 | G21: https://ashdeco.com/collections/tree-bookshelf | H21: 6 | I21: 0,7 | J21: 3 | K21: 0,94 | L21: 212 | M21: 35, 35, 29, 29, 66, 100, 35, 66, 54, 19, 66, 66 | N21: 31/07/2026 | O21: Image pack, Sitelinks, Reviews, Video, Image, People also ask, Popular products, Related searches, Short videos, Things to know, Discussions and forums | P21: informational | Q21: Organic
A22: bookcase tree | B22: 9 | C22: 9 | D22: 720 | E22: 15 | F22: 0,54 | G22: https://ashdeco.com/collections/tree-bookshelf | H22: 6 | I22: 0,7 | J22: 3 | K22: 1 | L22: 211 | M22: 5, 7, 7, 65, 100, 3, 0, 0, 0, 0, 0, 0 | N22: 13/06/2026 | O22: Image pack, Sitelinks, Video, Image, Popular products, Related searches | P22: informational | Q22: Organic
A23: tree book shelf for wall | B23: 4 | C23: 7 | D23: 210 | E23: 20 | F23: 0,4 | G23: https://ashdeco.com/collections/tree-bookshelf | H23: 5 | I23: 0,59 | J23: 2 | K23: 1 | L23: 263 | M23: 22, 22, 43, 29, 18, 29, 43, 54, 54, 43, 43, 100 | N23: 19/07/2026 | O23: Image pack, Sitelinks, Video, Video Carousel, Popular products, Related searches, Short videos | P23: informational, transactional | Q23: Organic
A24: tree bookshelves | B24: 6 | C24: 0 | D24: 590 | E24: 2 | F24: 0,52 | G24: https://ashdeco.com/collections/tree-bookshelf | H24: 5 | I24: 0,59 | J24: 2 | K24: 0,94 | L24: 10 | M24: 34, 16, 11, 24, 2, 24, 30, 24, 0, 34, 34, 7 | N24: 23/07/2026 | O24: Image pack, Sitelinks, People also ask, Popular products, Related searches, Discussions and forums | P24: informational | Q24: Organic
A25: tree book shelf | B25: 3 | C25: 10 | D25: 1000 | E25: 26 | F25: 0,52 | G25: https://ashdeco.com/collections/tree-bookshelf | H25: 5 | I25: 0,59 | J25: 2 | K25: 0,94 | L25: 218 | M25: 16, 16, 16, 18, 13, 13, 35, 18, 24, 8, 13, 29 | N25: 17/07/2026 | O25: Image pack, Sitelinks, Reviews, Video, Image, People also ask, Popular products, Related searches, Short videos, Things to know | P25: informational | Q25: Organic
A26: tree trunk bookcase | B26: 1 | C26: 1 | D26: 70 | E26: 23 | F26: 0,51 | G26: https://ashdeco.com/collections/tree-bookshelf | H26: 5 | I26: 0,59 | J26: 2 | K26: 1 | L26: 257 | M26: 23, 33, 23, 33, 33, 33, 23, 33, 33, 9, 52, 52 | N26: 17/07/2026 | O26: Image pack, Sitelinks, Video, Video Carousel, People also ask, Popular products, Related searches, Short videos | P26: commercial, informational | Q26: Organic
A27: tree shelf wall | B27: 2 | C27: 6 | D27: 140 | E27: 18 | F27: 0,44 | G27: https://ashdeco.com/collections/tree-bookshelf | H27: 4 | I27: 0,47 | J27: 1 | K27: 1 | L27: 216 | M27: 43, 66, 2, 0, 0, 0, 100, 14, 100, 2, 8, 43 | N27: 20/07/2026 | O27: Image pack, Sitelinks, Video, Popular products, Related searches, Short videos | P27: commercial, informational | Q27: Organic
A28: tree wall shelves | B28: 2 | C28: 8 | D28: 110 | E28: 18 | F28: 0,44 | G28: https://ashdeco.com/collections/tree-bookshelf | H28: 4 | I28: 0,47 | J28: 1 | K28: 1 | L28: 235 | M28: 15, 15, 15, 6, 34, 34, 34, 28, 28, 28, 28, 100 | N28: 29/07/2026 | O28: Image pack, Sitelinks, Video, Video Carousel, Popular products, Related searches, Short videos, Discussions and forums | P28: informational | Q28: Organic
A29: trunk bookshelf | B29: 1 | C29: 1 | D29: 50 | E29: 21 | F29: 0 | G29: https://ashdeco.com/collections/tree-bookshelf | H29: 4 | I29: 0,47 | J29: 0 | K29: 0,86 | L29: 215 | M29: 11, 11, 11, 11, 64, 11, 64, 11, 82, 64, 11, 11 | N29: 46362 | O29: Image pack, Sitelinks, Reviews, Video, Image, Popular products, Related searches | P29: commercial, informational | Q29: Organic
A30: wall tree shelf | B30: 5 | C30: 5 | D30: 170 | E30: 21 | F30: 0,51 | G30: https://ashdeco.com/collections/tree-bookshelf | H30: 4 | I30: 0,47 | J30: 2 | K30: 1 | L30: 259 | M30: 53, 53, 43, 35, 17, 53, 66, 66, 43, 43, 23, 35 | N30: 22/06/2026 | O30: Image pack, Sitelinks, Video, Popular products, Related searches, Short videos | P30: informational | Q30: Organic
A31: tree bookshelf for nursery | B31: 3 | C31: 3 | D31: 140 | E31: 13 | F31: 0,53 | G31: https://ashdeco.com/collections/tree-bookshelf | H31: 4 | I31: 0,47 | J31: 2 | K31: 1 | L31: 218 | M31: 21, 21, 28, 28, 53, 43, 43, 53, 53, 81, 43, 65 | N31: 18/06/2026 | O31: Image pack, Sitelinks, Video, Image, Popular products, Related searches | P31: commercial | Q31: Organic
A32: wood tree shelf | B32: 3 | C32: 3 | D32: 90 | E32: 21 | F32: 0,38 | G32: https://ashdeco.com/collections/tree-bookshelf | H32: 3 | I32: 0,35 | J32: 1 | K32: 0,34 | L32: 230 | M32: 0, 5, 6, 4, 6, 4, 6, 5, 6, 5, 6, 100 | N32: 28/06/2026 | O32: Image pack, Sitelinks, Video, Popular products, Related searches, Short videos | P32: informational | Q32: Organic
A33: tree trunk shelves | B33: 2 | C33: 2 | D33: 50 | E33: 20 | F33: 0,39 | G33: https://ashdeco.com/collections/tree-bookshelf | H33: 3 | I33: 0,35 | J33: 1 | K33: 1 | L33: 203 | M33: 78, 78, 14, 14, 14, 14, 14, 78, 14, 78, 14, 14 | N33: 17/06/2026 | O33: Image pack, Sitelinks, Video, Image, Video Carousel, Popular products, Related searches | P33: informational | Q33: Organic
A34: bookshelf that looks like a tree | B34: 4 | C34: 4 | D34: 90 | E34: 20 | F34: 0,37 | G34: https://ashdeco.com/collections/tree-bookshelf | H34: 3 | I34: 0,35 | J34: 1 | K34: 0,76 | L34: 287 | M34: 26, 19, 34, 34, 26, 19, 34, 26, 34, 19, 26, 100 | N34: 46119 | O34: Image pack, Sitelinks, Video, Image, Video Carousel, Popular products, Related searches, Short videos | P34: informational | Q34: Organic
A35: tree wall shelving | B35: 3 | C35: 3 | D35: 70 | E35: 20 | F35: 0,51 | G35: https://ashdeco.com/collections/tree-bookshelf | H35: 3 | I35: 0,35 | J35: 1 | K35: 1 | L35: 233 | M35: 100, 100, 100, 0, 0, 0, 0, 33, 0, 33, 0, 0 | N35: 22/06/2026 | O35: Image pack, Sitelinks, Video, Image, Popular products, Related searches | P35: commercial, informational | Q35: Organic
A36: tree wood shelves | B36: 2 | C36: 6 | D36: 50 | E36: 20 | F36: 0,38 | G36: https://ashdeco.com/collections/tree-bookshelf | H36: 3 | I36: 0,35 | J36: 1 | K36: 0,34 | L36: 202 | M36: 52, 52, 0, 0, 0, 0, 33, 100, 33, 0, 0, 0 | N36: 14/07/2026 | O36: Sitelinks, Video, Video Carousel, Popular products, Related searches, Short videos | P36: commercial | Q36: Organic
A37: tree book.shelf | B37: 2 | C37: 12 | D37: 110 | E37: 24 | F37: 0,52 | G37: https://ashdeco.com/collections/tree-bookshelf | H37: 3 | I37: 0,35 | J37: 1 | K37: 0,94 | L37: 186 | M37: 0, 0, 0, 0, 0, 100, 0, 0, 0, 0, 0, 0 | N37: 46333 | O37: Sitelinks, Video, People also ask, Popular products, Short videos | P37: informational | Q37: Organic
A38: real tree bookshelf | B38: 3 | C38: 6 | D38: 140 | E38: 0 | F38: 0,61 | G38: https://ashdeco.com/collections/tree-bookshelf | H38: 3 | I38: 0,35 | J38: 1 | K38: 1 | L38: 226 | M38: 42, 42, 80, 53, 53, 3, 65, 65, 100, 53, 80, 65 | N38: 13/07/2026 | O38: Image pack, Sitelinks, Video, Image, Video Carousel, People also ask, Popular products, Related searches | P38: informational | Q38: Organic
A39: bookcase tree | B39: 10 | C39: 9 | D39: 720 | E39: 15 | F39: 0,54 | G39: https://ashdeco.com/collections/tree-bookshelf | H39: 3 | I39: 0,35 | J39: 1 | K39: 1 | L39: 211 | M39: 5, 7, 7, 65, 100, 3, 0, 0, 0, 0, 0, 0 | N39: 13/06/2026 | O39: Image pack, Sitelinks, Video, Image, Popular products, Related searches | P39: informational | Q39: Organic
A40: nursery bookshelf tree | B40: 7 | C40: 14 | D40: 140 | E40: 17 | F40: 0,51 | G40: https://ashdeco.com/collections/tree-bookshelf | H40: 2 | I40: 0,23 | J40: 1 | K40: 1 | L40: 10 | M40: 34, 26, 26, 26, 42, 53, 65, 53, 100, 53, 80, 80 | N40: 18/07/2026 | O40: Image pack, Sitelinks, Image, Popular products, Related searches | P40: informational | Q40: Organic
A41: tree bookshelf white | B41: 5 | C41: 0 | D41: 110 | E41: 0 | F41: 0,42 | G41: https://ashdeco.com/collections/tree-bookshelf | H41: 2 | I41: 0,23 | J41: 0 | K41: 1 | L41: 197 | M41: 100, 34, 34, 34, 21, 28, 34, 28, 28, 21, 28, 34 | N41: 19/07/2026 | O41: Image pack, Sitelinks, Reviews, Video, Image, Popular products, Related searches | P41: informational, transactional | Q41: Organic
A42: tree shaped shelf | B42: 2 | C42: 12 | D42: 50 | E42: 23 | F42: 0,28 | G42: https://ashdeco.com/collections/tree-bookshelf | H42: 1 | I42: 0,11 | J42: 0 | K42: 1 | L42: 244 | M42: 11, 11, 11, 11, 64, 11, 64, 82, 11, 11, 11, 11 | N42: 21/07/2026 | O42: Image pack, Sitelinks, Video, People also ask, Popular products, Related searches, Short videos | P42: informational | Q42: Organic
A43: tree book shelves | B43: 6 | C43: 6 | D43: 90 | E43: 23 | F43: 0,54 | G43: https://ashdeco.com/collections/tree-bookshelf | H43: 1 | I43: 0,11 | J43: 0 | K43: 1 | L43: 240 | M43: 0, 0, 65, 26, 34, 100, 7, 3, 100, 0, 100, 0 | N43: 17/06/2026 | O43: Image pack, Sitelinks, Video, Video Carousel, People also ask, Popular products, Related searches | P43: informational | Q43: Organic
A44: tree shaped bookshelf | B44: 16 | C44: 16 | D44: 880 | E44: 26 | F44: 0,49 | G44: https://ashdeco.com/collections/tree-bookshelf | H44: 1 | I44: 0,11 | J44: 0 | K44: 1 | L44: 244 | M44: 16, 16, 36, 100, 54, 36, 30, 24, 20, 36, 5, 36 | N44: 46209 | O44: Image pack, Sitelinks, Video, Image, People also ask, Popular products, Related searches, Short videos | P44: commercial, informational | Q44: Organic
A45: tree bookshelf nursery | B45: 3 | C45: 3 | D45: 50 | E45: 16 | F45: 0,6 | G45: https://ashdeco.com/collections/tree-bookshelf | H45: 1 | I45: 0,11 | J45: 0 | K45: 1 | L45: 216 | M45: 19, 19, 26, 19, 26, 26, 19, 7, 7, 42, 7, 7 | N45: 46332 | O45: Image pack, Sitelinks, Video, Image, Popular products, Related searches | P45: commercial | Q45: Organic
A46: tree shaped bookcase | B46: 9 | C46: 9 | D46: 880 | E46: 27 | F46: 0,52 | G46: https://ashdeco.com/collections/tree-bookshelf | H46: 1 | I46: 0,11 | J46: 0 | K46: 0,42 | L46: 215 | M46: 13, 20, 44, 44, 20, 20, 20, 11, 24, 13, 20, 100 | N46: 29/06/2026 | O46: Image pack, Sitelinks, Video, Video Carousel, Popular products, Related searches, Short videos | P46: informational | Q46: Organic
A47: tree branch shelving | B47: 4 | C47: 4 | D47: 70 | E47: 23 | F47: 0,38 | G47: https://ashdeco.com/collections/tree-bookshelf | H47: 1 | I47: 0,11 | J47: 0 | K47: 1 | L47: 238 | M47: 0, 0, 0, 0, 0, 0, 14, 18, 18, 100, 0, 0 | N47: 30/06/2026 | O47: Image pack, Sitelinks, Video, Image, Video Carousel, People also ask, Popular products, Related searches, Short videos | P47: informational | Q47: Organic
A48: tree wall shelf | B48: 7 | C48: 7 | D48: 260 | E48: 25 | F48: 0,51 | G48: https://ashdeco.com/collections/tree-bookshelf | H48: 1 | I48: 0,11 | J48: 0 | K48: 1 | L48: 258 | M48: 43, 43, 43, 54, 54, 35, 54, 66, 43, 100, 43, 66 | N48: 16/06/2026 | O48: Image pack, Sitelinks, Video, Popular products, Related searches, Short videos | P48: informational | Q48: Organic
A49: small tree bookshelf | B49: 5 | C49: 5 | D49: 70 | E49: 24 | F49: 0,54 | G49: https://ashdeco.com/collections/tree-bookshelf | H49: 1 | I49: 0,11 | J49: 0 | K49: 0,36 | L49: 225 | M49: 6, 6, 6, 34, 34, 6, 6, 6, 6, 6, 6, 100 | N49: 46029 | O49: Image pack, Sitelinks, Video, Image, Video Carousel, Popular products, Related searches | P49: informational | Q49: Organic
A50: tree bookshelf wall | B50: 2 | C50: 6 | D50: 90 | E50: 17 | F50: 0,46 | G50: https://ashdeco.com/collections/tree-bookshelf | H50: 1 | I50: 0,11 | J50: 0 | K50: 0,81 | L50: 241 | M50: 34, 34, 6, 34, 6, 6, 6, 6, 34, 6, 34, 100 | N50: 46302 | O50: Image pack, Sitelinks, Video, Video Carousel, Popular products, Related searches, Short videos | P50: informational, transactional | Q50: Organic
A51: tree branch book shelf | B51: 6 | C51: 0 | D51: 260 | E51: 24 | F51: 0,47 | G51: https://ashdeco.com/collections/tree-bookshelf | H51: 1 | I51: 0,11 | J51: 0 | K51: 0,5 | L51: 247 | M51: 0, 0, 0, 5, 0, 3, 5, 8, 16, 7, 8, 100 | N51: 46272 | O51: Image pack, Sitelinks, Video, Image, People also ask, Popular products, Related searches, Short videos | P51: commercial, informational | Q51: Organic
A52: wooden tree with shelves | B52: 3 | C52: 0 | D52: 40 | E52: 20 | F52: 0 | G52: https://ashdeco.com/collections/tree-bookshelf | H52: 1 | I52: 0,11 | J52: 0 | K52: 1 | L52: 223 | M52: 11, 100, 64, 11, 11, 11, 11, 11, 11, 11, 11, 11 | N52: 19/07/2026 | O52: Image pack, Sitelinks, Video, Video Carousel, Popular products, Related searches | P52: informational | Q52: Organic

Sheet Collection corner-floating-shel
A1: Keyword | B1: Position | C1: Previous position | D1: Search Volume | E1: Keyword Difficulty | F1: CPC | G1: URL | H1: Traffic | I1: Traffic (%) | J1: Traffic Cost | K1: Competition | L1: Number of Results | M1: Trends | N1: Timestamp | O1: SERP Features by Keyword | P1: Keyword Intents | Q1: Position Type
A2: corner shelf | B2: 6 | C2: 10 | D2: 40500 | E2: 45 | F2: 0,42 | G2: https://www.spryinterior.com/collections/corner-floating-shelves | H2: 283 | I2: 19,47 | J2: 118 | K2: 1 | L2: 248 | M2: 54, 44, 54, 81, 54, 44, 54, 54, 66, 44, 44, 44 | N2: ######## | O2: Image pack, Sitelinks, Video, Popular products, Related searches, Things to know | P2: commercial | Q2: Organic
A3: corner shelfs | B3: 3 | C3: 3 | D3: 2900 | E3: 44 | F3: 0,42 | G3: https://www.spryinterior.com/collections/corner-floating-shelves | H3: 188 | I3: 12,93 | J3: 78 | K3: 1 | L3: 254 | M3: 44, 16, 24, 24, 10, 10, 19, 16, 19, 19, 3, 19 | N3: ######## | O3: Image pack, Sitelinks, Reviews, Video, People also ask, Popular products, Related searches, Short videos, Things to know, Discussions and forums | P3: commercial | Q3: Organic
A4: wooden corner shelf | B4: 3 | C4: 5 | D4: 1300 | E4: 18 | F4: 0,44 | G4: https://www.spryinterior.com/collections/corner-floating-shelves | H4: 57 | I4: 3,92 | J4: 25 | K4: 0,79 | L4: 219 | M4: 13, 22, 43, 22, 36, 20, 20, 54, 16, 13, 13, 43 | N4: ######## | O4: Image pack, Sitelinks, Video, Video Carousel, Popular products, Related searches, Short videos | P4: commercial | Q4: Organic
A5: wall corner shelves | B5: 1 | C5: 3 | D5: 390 | E5: 34 | F5: 0,42 | G5: https://www.spryinterior.com/collections/corner-floating-shelves | H5: 51 | I5: 3,5 | J5: 21 | K5: 1 | L5: 232 | M5: 10, 6, 36, 36, 30, 36, 20, 16, 36, 20, 20, 45 | N5: ######## | O5: Image pack, Sitelinks, Video, Popular products, Related searches | P5: commercial | Q5: Organic
A6: corner wall shelf | B6: 5 | C6: 4 | D6: 5400 | E6: 41 | F6: 0,4 | G6: https://www.spryinterior.com/collections/corner-floating-shelves | H6: 48 | I6: 3,3 | J6: 19 | K6: 1 | L6: 245 | M6: 36, 36, 44, 36, 36, 44, 44, 44, 66, 44, 44, 66 | N6: ######## | O6: Image pack, Sitelinks, Video, People also ask, Popular products, Related searches, Short videos, Discussions and forums | P6: commercial | Q6: Organic
A7: corner wood shelf floating | B7: 1 | C7: 1 | D7: 320 | E7: 18 | F7: 0,54 | G7: https://www.spryinterior.com/collections/corner-floating-shelves | H7: 42 | I7: 2,89 | J7: 22 | K7: 1 | L7: 210 | M7: 44, 44, 29, 12, 19, 15, 81, 54, 5, 100, 23, 2 | N7: ######## | O7: Image pack, Sitelinks, Video, Image, Video Carousel, Popular products, Related searches | P7: commercial | Q7: Organic
A8: corner wall shelves | B8: 3 | C8: 3 | D8: 1600 | E8: 34 | F8: 0,4 | G8: https://www.spryinterior.com/collections/corner-floating-shelves | H8: 35 | I8: 2,4 | J8: 14 | K8: 1 | L8: 227 | M8: 13, 13, 36, 28, 54, 19, 28, 13, 24, 10, 28, 36 | N8: ######## | O8: Image pack, Sitelinks, Video, Popular products, Related searches, Things to know | P8: commercial | Q8: Organic
A9: wooden corner shelf floating | B9: 1 | C9: 0 | D9: 210 | E9: 15 | F9: 0,54 | G9: https://www.spryinterior.com/collections/corner-floating-shelves | H9: 27 | I9: 1,85 | J9: 14 | K9: 1 | L9: 216 | M9: 3, 8, 0, 3, 2, 1, 5, 2, 100, 2, 2, 2 | N9: ######## | O9: Image pack, Sitelinks, Video, Video Carousel, Popular products, Related searches | P9: commercial, informational | Q9: Organic
A10: corner shelving | B10: 4 | C10: 0 | D10: 2900 | E10: 41 | F10: 0,42 | G10: https://www.spryinterior.com/collections/corner-floating-shelves | H10: 26 | I10: 1,78 | J10: 10 | K10: 1 | L10: 229 | M10: 10, 13, 16, 7, 8, 8, 8, 7, 10, 8, 8, 8 | N10: ######## | O10: Image pack, Sitelinks, Video, People also ask, Popular products, Related searches, Short videos, Things to know | P10: commercial | Q10: Organic
A11: corner shelves | B11: 10 | C11: 3 | D11: 14800 | E11: 39 | F11: 0,42 | G11: https://www.spryinterior.com/collections/corner-floating-shelves | H11: 22 | I11: 1,51 | J11: 9 | K11: 1 | L11: 246 | M11: 24, 29, 36, 36, 24, 29, 44, 44, 44, 36, 36, 36 | N11: ######## | O11: Image pack, Sitelinks, Video, Image, People also ask, Popular products, Related searches, Things to know, Discussions and forums | P11: commercial, informational | Q11: Organic
A12: wall mounted corner shelves | B12: 3 | C12: 3 | D12: 480 | E12: 31 | F12: 0,41 | G12: https://www.spryinterior.com/collections/corner-floating-shelves | H12: 21 | I12: 1,44 | J12: 8 | K12: 1 | L12: 226 | M12: 5, 2, 7, 5, 66, 8, 10, 8, 79, 8, 5, 7 | N12: ######## | O12: Image pack, Sitelinks, Video, Video Carousel, Popular products, Related searches | P12: commercial | Q12: Organic
A13: corner shelves for wall | B13: 4 | C13: 4 | D13: 880 | E13: 28 | F13: 0,4 | G13: https://www.spryinterior.com/collections/corner-floating-shelves | H13: 21 | I13: 1,44 | J13: 8 | K13: 1 | L13: 246 | M13: 1, 0, 13, 5, 100, 65, 82, 82, 1, 1, 0, 3 | N13: ######## | O13: Image pack, Sitelinks, Video, People also ask, Popular products, Related searches | P13: informational | Q13: Organic
A14: wall mount corner shelf | B14: 5 | C14: 5 | D14: 880 | E14: 36 | F14: 0,4 | G14: https://www.spryinterior.com/collections/corner-floating-shelves | H14: 19 | I14: 1,3 | J14: 7 | K14: 1 | L14: 258 | M14: 0, 100, 29, 20, 2, 2, 0, 0, 0, 22, 16, 29 | N14: ######## | O14: Image pack, Sitelinks, Video, Image, People also ask, Popular products, Related searches | P14: informational | Q14: Organic
A15: wall corner shelf | B15: 4 | C15: 18 | D15: 720 | E15: 34 | F15: 0,42 | G15: https://www.spryinterior.com/collections/corner-floating-shelves | H15: 17 | I15: 1,16 | J15: 7 | K15: 1 | L15: 252 | M15: 10, 10, 18, 13, 7, 13, 13, 13, 13, 13, 13, 3 | N15: ######## | O15: Image pack, Sitelinks, Video, People also ask, Popular products, Related searches, Discussions and forums | P15: commercial | Q15: Organic
A16: shelf corner wall | B16: 4 | C16: 18 | D16: 720 | E16: 38 | F16: 0,4 | G16: https://www.spryinterior.com/collections/corner-floating-shelves | H16: 17 | I16: 1,16 | J16: 6 | K16: 1 | L16: 243 | M16: 0, 0, 0, 0, 0, 0, 0, 0, 0, 0, 100, 0 | N16: ######## | O16: Image pack, Sitelinks, Video, People also ask, Popular products, Related searches, Discussions and forums | P16: commercial | Q16: Organic
... A20: live edge corner shelf | B20: 2 | C20: 2 | D20: 320 | E20: 19 | F20: 0,59 | G20: https://www.spryinterior.com/collections/corner-floating-shelves | H20: 14 | I20: 0,96 | J20: 8 | K20: 1 | L20: 247 | M20: 66, 54, 54, 54, 66, 100, 66, 66, 81, 81, 66, 66 | N20: ######## | O20: Image pack, Sitelinks, Reviews, Video, Image, People also ask, Popular products, Related searches | P20: informational | Q20: Organic
A21: wooden corner shelves | B21: 7 | C21: 7 | D21: 720 | E21: 29 | F21: 0,44 | G21: https://www.spryinterior.com/collections/corner-floating-shelves | H21: 13 | I21: 0,89 | J21: 5 | K21: 0,79 | L21: 213 | M21: 7, 0, 37, 68, 46, 46, 46, 31, 13, 20, 20, 100 | N21: ######## | O21: Image pack, Sitelinks, Video, People also ask, Popular products, Related searches | P21: commercial | Q21: Organic
A22: living room corner shelves | B22: 2 | C22: 3 | D22: 210 | E22: 21 | F22: 0,46 | G22: https://www.spryinterior.com/collections/corner-floating-shelves | H22: 13 | I22: 0,89 | J22: 5 | K22: 1 | L22: 218 | M22: 23, 36, 19, 23, 36, 29, 44, 36, 29, 23, 36, 23 | N22: ######## | O22: Image pack, Sitelinks, Video, Popular products, Related searches, Short videos | P22: informational, transactional | Q22: Organic
A23: corner modern shelves | B23: 2 | C23: 3 | D23: 170 | E23: 25 | F23: 0,69 | G23: https://www.spryinterior.com/collections/corner-floating-shelves | H23: 13 | I23: 0,89 | J23: 8 | K23: 1 | L23: 195 | M23: 54, 54, 18, 1, 1, 5, 66, 11, 28, 44, 11, 28 | N23: ######## | O23: Sitelinks, Video, Video Carousel, Popular products, Related searches | P23: commercial | Q23: Organic
A24: corner wall mounted shelf | B24: 4 | C24: 12 | D24: 320 | E24: 31 | F24: 0,5 | G24: https://www.spryinterior.com/collections/corner-floating-shelves | H24: 11 | I24: 0,75 | J24: 5 | K24: 1 | L24: 203 | M24: 1, 1, 13, 82, 1, 1, 0, 24, 0, 0, 0, 11 | N24: ######## | O24: Image pack, Sitelinks, Video, Popular products, Related searches | P24: informational, transactional | Q24: Organic
A25: decorative corner shelves | B25: 1 | C25: 17 | D25: 140 | E25: 28 | F25: 0,41 | G25: https://www.spryinterior.com/collections/corner-floating-shelves | H25: 11 | I25: 0,75 | J25: 4 | K25: 1 | L25: 227 | M25: 81, 53, 81, 53, 34, 21, 21, 53, 28, 34, 34, 34 | N25: ######## | O25: Image pack, Sitelinks, Video, Image, Popular products, Related searches, Short videos | P25: commercial | Q25: Organic
A26: corner wall shelving | B26: 2 | C26: 2 | D26: 170 | E26: 34 | F26: 0,4 | G26: https://www.spryinterior.com/collections/corner-floating-shelves | H26: 11 | I26: 0,75 | J26: 4 | K26: 1 | L26: 225 | M26: 23, 7, 100, 12, 29, 3, 2, 12, 36, 5, 12, 12 | N26: ######## | O26: Image pack, Sitelinks, Video, People also ask, Popular products, Related searches | P26: informational | Q26: Organic
A27: corner display shelves | B27: 4 | C27: 4 | D27: 390 | E27: 32 | F27: 0,49 | G27: https://www.spryinterior.com/collections/corner-floating-shelves | H27: 11 | I27: 0,75 | J27: 5 | K27: 1 | L27: 241 | M27: 23, 5, 23, 44, 23, 23, 36, 36, 36, 67, 81, 100 | N27: ######## | O27: Image pack, Sitelinks, Video, Video Carousel, Popular products, Related searches | P27: commercial | Q27: Organic
A28: corner hanging bookshelf | B28: 1 | C28: 1 | D28: 140 | E28: 27 | F28: 0,45 | G28: https://www.spryinterior.com/collections/corner-floating-shelves | H28: 11 | I28: 0,75 | J28: 4 | K28: 1 | L28: 243 | M28: 43, 28, 43, 43, 34, 34, 81, 81, 81, 34, 34, 34 | N28: ######## | O28: Image pack, Sitelinks, Video, Video Carousel, Popular products, Related searches | P28: informational | Q28: Organic
A29: corner unit shelves wood | B29: 3 | C29: 5 | D29: 260 | E29: 17 | F29: 0,46 | G29: https://www.spryinterior.com/collections/corner-floating-shelves | H29: 9 | I29: 0,61 | J29: 4 | K29: 1 | L29: 197 | M29: 21, 14, 100, 7, 11, 17, 26, 14, 26, 17, 21, 21 | N29: ######## | O29: Sitelinks, Video, Video Carousel, Popular products, Related searches | P29: commercial | Q29: Organic
A30: coner shelf | B30: 3 | C30: 8 | D30: 140 | E30: 35 | F30: 0,42 | G30: https://www.spryinterior.com/collections/corner-floating-shelves | H30: 9 | I30: 0,61 | J30: 3 | K30: 1 | L30: 248 | M30: 4, 3, 1, 1, 0, 0, 10, 0, 0, 0, 0, 1 | N30: ######## | O30: Image pack, Sitelinks, Reviews, Video, Popular products, Related searches, Things to know | P30: commercial | Q30: Organic
A31: corner shelf wall | B31: 5 | C31: 6 | D31: 1000 | E31: 33 | F31: 0,4 | G31: https://www.spryinterior.com/collections/corner-floating-shelves | H31: 9 | I31: 0,61 | J31: 3 | K31: 1 | L31: 242 | M31: 18, 100, 35, 18, 24, 8, 8, 16, 2, 5, 2, 2 | N31: ######## | O31: Image pack, Sitelinks, Video, People also ask, Popular products, Related searches, Things to know | P31: informational | Q31: Organic
A32: corner shelf living room | B32: 2 | C32: 17 | D32: 140 | E32: 32 | F32: 0,46 | G32: https://www.spryinterior.com/collections/corner-floating-shelves | H32: 9 | I32: 0,61 | J32: 4 | K32: 1 | L32: 227 | M32: 23, 19, 100, 7, 12, 12, 23, 12, 0, 1, 0, 0 | N32: ######## | O32: Image pack, Sitelinks, Video, Image, Video Carousel, Popular products, Related searches | P32: informational | Q32: Organic
A33: floating corner shelves for living room | B33: 2 | C33: 2 | D33: 210 | E33: 17 | F33: 0,45 | G33: https://www.spryinterior.com/collections/corner-floating-shelves | H33: 9 | I33: 0,61 | J33: 4 | K33: 1 | L33: 214 | M33: 2, 5, 32, 100, 48, 21, 11, 11, 11, 14, 7, 9 | N33: ######## | O33: Image pack, Sitelinks, Video, Video Carousel, Popular products, Related searches | P33: informational | Q33: Organic
... A40: hanging corner bookshelf | B40: 1 | C40: 3 | D40: 90 | E40: 20 | F40: 0,48 | G40: https://www.spryinterior.com/collections/corner-floating-shelves | H40: 7 | I40: 0,48 | J40: 3 | K40: 1 | L40: 220 | M40: 34, 26, 34, 42, 34, 26, 34, 53, 34, 26, 26, 34 | N40: ######## | O40: Image pack, Sitelinks, Video, Video Carousel, Popular products, Related searches | P40: informational, transactional | Q40: Organic
A41: wooden shelf corner | B41: 9 | C41: 9 | D41: 720 | E41: 14 | F41: 0,44 | G41: https://www.spryinterior.com/collections/corner-floating-shelves | H41: 6 | I41: 0,41 | J41: 2 | K41: 0,79 | L41: 223 | M41: 8, 100, 2, 36, 100, 100, 4, 2, 5, 5, 5, 20 | N41: ######## | O41: Image pack, Sitelinks, Video, People also ask, Popular products, Related searches | P41: informational | Q41: Organic
A42: corner shelves wall | B42: 5 | C42: 5 | D42: 260 | E42: 21 | F42: 0,41 | G42: https://www.spryinterior.com/collections/corner-floating-shelves | H42: 6 | I42: 0,41 | J42: 2 | K42: 1 | L42: 230 | M42: 29, 12, 23, 67, 44, 29, 23, 36, 1, 100, 4, 10 | N42: ######## | O42: Image pack, Sitelinks, Video, Popular products, Related searches, Short videos | P42: informational, transactional | Q42: Organic
A43: shelves for a corner | B43: 11 | C43: 2 | D43: 1600 | E43: 38 | F43: 0,42 | G43: https://www.spryinterior.com/collections/corner-floating-shelves | H43: 6 | I43: 0,41 | J43: 2 | K43: 1 | L43: 221 | M43: 15, 2, 1, 15, 2, 100, 3, 3, 3, 3, 4, 3 | N43: ######## | O43: Image pack, Sitelinks, Video, Image, Popular products, Related searches | P43: commercial | Q43: Organic
A44: corner wooden shelf | B44: 7 | C44: 1 | D44: 880 | E44: 32 | F44: 0,44 | G44: https://www.spryinterior.com/collections/corner-floating-shelves | H44: 6 | I44: 0,41 | J44: 2 | K44: 0,79 | L44: 8 | M44: 36, 79, 66, 41, 4, 24, 10, 5, 7, 3, 30, 100 | N44: ######## | O44: Image pack, Sitelinks, Popular products, Related searches, Discussions and forums | P44: informational | Q44: Organic
A45: solid wood corner shelf | B45: 6 | C45: 6 | D45: 210 | E45: 8 | F45: 0,54 | G45: https://www.spryinterior.com/collections/corner-floating-shelves | H45: 5 | I45: 0,34 | J45: 2 | K45: 1 | L45: 235 | M45: 43, 65, 53, 65, 65, 53, 53, 81, 53, 100, 65, 53 | N45: ######## | O45: Image pack, Sitelinks, Video, Video Carousel, Popular products, Related searches | P45: informational | Q45: Organic
A46: wall corner book shelf | B46: 2 | C46: 2 | D46: 170 | E46: 30 | F46: 0,49 | G46: https://www.spryinterior.com/collections/corner-floating-shelves | H46: 5 | I46: 0,34 | J46: 2 | K46: 1 | L46: 179 | M46: 35, 17, 100, 28, 35, 23, 12, 82, 28, 82, 28, 28 | N46: ######## | O46: Image pack, Sitelinks, Popular products, Related searches, Discussions and forums | P46: informational | Q46: Organic
A47: floating corner shelf unit | B47: 2 | C47: 3 | D47: 90 | E47: 29 | F47: 0,5 | G47: https://www.spryinterior.com/collections/corner-floating-shelves | H47: 5 | I47: 0,34 | J47: 2 | K47: 1 | L47: 204 | M47: 21, 21, 53, 34, 34, 43, 34, 21, 28, 15, 15, 12 | N47: ######## | O47: Image pack, Sitelinks, Reviews, Video, Image, Video Carousel, People also ask, Popular products, Related searches | P47: commercial | Q47: Organic
A48: corner hanging wall shelf | B48: 4 | C48: 4 | D48: 170 | E48: 35 | F48: 0,49 | G48: https://www.spryinterior.com/collections/corner-floating-shelves | H48: 5 | I48: 0,34 | J48: 2 | K48: 1 | L48: 198 | M48: 12, 36, 44, 19, 2, 1, 1, 29, 2, 5, 36, 81 | N48: ######## | O48: Sitelinks, Video, Popular products, Related searches | P48: commercial | Q48: Organic
A49: wood floating corner shelf | B49: 8 | C49: 8 | D49: 390 | E49: 25 | F49: 0,54 | G49: https://www.spryinterior.com/collections/corner-floating-shelves | H49: 5 | I49: 0,34 | J49: 2 | K49: 1 | L49: 213 | M49: 45, 30, 13, 67, 100, 100, 5, 5, 5, 10, 13, 3 | N49: ######## | O49: Image pack, Sitelinks, Video, Image, Popular products, Related searches | P49: informational, transactional | Q49: Organic
A50: corner bedroom shelving | B50: 4 | C50: 0 | D50: 170 | E50: 37 | F50: 0,41 | G50: https://www.spryinterior.com/collections/corner-floating-shelves | H50: 5 | I50: 0,34 | J50: 2 | K50: 1 | L50: 228 | M50: 0, 0, 0, 0, 0, 0, 100, 0, 20, 0, 0, 0 | N50: ######## | O50: Sitelinks, Video, People also ask, Popular products, Related searches | P50: commercial | Q50: Organic
A51: floating wood corner shelves | B51: 7 | C51: 13 | D51: 210 | E51: 11 | F51: 0,54 | G51: https://www.spryinterior.com/collections/corner-floating-shelves | H51: 5 | I51: 0,34 | J51: 2 | K51: 1 | L51: 10 | M51: 14, 14, 29, 66, 66, 54, 81, 22, 100, 81, 10, 14 | N51: ######## | O51: Image pack, Sitelinks, Popular products, Related searches | P51: commercial | Q51: Organic
A52: corner wooden shelving unit | B52: 2 | C52: 2 | D52: 90 | E52: 27 | F52: 0,46 | G52: https://www.spryinterior.com/collections/corner-floating-shelves | H52: 5 | I52: 0,34 | J52: 2 | K52: 1 | L52: 198 | M52: 80, 53, 11, 3, 11, 3, 19, 3, 100, 65, 15, 26 | N52: ######## | O52: Sitelinks, Video, Video Carousel, Popular products, Related searches | P52: commercial | Q52: Organic
A53: corner wall shelving unit | B53: 2 | C53: 14 | D53: 90 | E53: 32 | F53: 0,38 | G53: https://www.spryinterior.com/collections/corner-floating-shelves | H53: 5 | I53: 0,34 | J53: 1 | K53: 1 | L53: 236 | M53: 18, 18, 14, 4, 2, 2, 14, 4, 100, 14, 2, 10 | N53: ######## | O53: Image pack, Sitelinks, Video, Video Carousel, Popular products, Related searches | P53: commercial | Q53: Organic
A54: corner room shelving | B54: 3 | C54: 3 | D54: 50 | E54: 24 | F54: 0,45 | G54: https://www.spryinterior.com/collections/corner-floating-shelves | H54: 4 | I54: 0,27 | J54: 1 | K54: 1 | L54: 196 | M54: 33, 42, 52, 33, 0, 0, 0, 19, 0, 100, 14, 4 | N54: ######## | O54: Image pack, Sitelinks, Video, Image, Related searches | P54: commercial | Q54: Organic
A55: corner floating wood shelves | B55: 7 | C55: 10 | D55: 210 | E55: 18 | F55: 0,54 | G55: https://www.spryinterior.com/collections/corner-floating-shelves | H55: 4 | I55: 0,27 | J55: 2 | K55: 1 | L55: 10 | M55: 54, 29, 5, 5, 81, 4, 44, 5, 100, 12, 4, 5 | N55: ######## | O55: Image pack, Sitelinks, Image, Popular products, Related searches | P55: informational | Q55: Organic
A56: modern corner shelf | B56: 8 | C56: 8 | D56: 320 | E56: 23 | F56: 0,69 | G56: https://www.spryinterior.com/collections/corner-floating-shelves | H56: 4 | I56: 0,27 | J56: 2 | K56: 1 | L56: 220 | M56: 30, 30, 55, 20, 24, 24, 30, 24, 20, 16, 13, 13 | N56: ######## | O56: Image pack, Sitelinks, Video, Image, People also ask, Popular products, Related searches | P56: informational | Q56: Organic
... A63: wall mounted corner shelving | B63: 2 | C63: 2 | D63: 70 | E63: 28 | F63: 0,4 | G63: https://www.spryinterior.com/collections/corner-floating-shelves | H63: 4 | I63: 0,27 | J63: 1 | K63: 1 | L63: 226 | M63: 4, 12, 2, 1, 4, 1, 5, 1, 100, 1, 0, 1 | N63: ######## | O63: Image pack, Sitelinks, Video, Popular products, Related searches | P63: informational | Q63: Organic
A64: corner shelving wood | B64: 9 | C64: 9 | D64: 480 | E64: 17 | F64: 0,44 | G64: https://www.spryinterior.com/collections/corner-floating-shelves | H64: 4 | I64: 0,27 | J64: 1 | K64: 0,79 | L64: 211 | M64: 3, 16, 22, 1, 1, 1, 8, 2, 54, 0, 0, 2 | N64: ######## | O64: Image pack, Sitelinks, Video, Popular products, Related searches | P64: informational | Q64: Organic
A65: floating corner shelf | B65: 18 | C65: 10 | D65: 5400 | E65: 17 | F65: 0,44 | G65: https://www.spryinterior.com/collections/corner-floating-shelves | H65: 3 | I65: 0,2 | J65: 1 | K65: 1 | L65: 221 | M65: 16, 54, 100, 36, 29, 24, 44, 44, 29, 29, 24, 36 | N65: ######## | O65: Image pack, Sitelinks, Reviews, Video, People also ask, Popular products, Related searches, Things to know, Discussions and forums | P65: commercial | Q65: Organic
A66: live edge corner shelves | B66: 2 | C66: 2 | D66: 90 | E66: 7 | F66: 0,59 | G66: https://www.spryinterior.com/collections/corner-floating-shelves | H66: 3 | I66: 0,2 | J66: 1 | K66: 1 | L66: 250 | M66: 23, 19, 23, 33, 52, 100, 66, 66, 100, 33, 19, 23 | N66: ######## | O66: Image pack, Sitelinks, Video, Image, People also ask, Popular products | P66: informational, transactional | Q66: Organic
A67: large corner shelf floating | B67: 2 | C67: 9 | D67: 50 | E67: 29 | F67: 0,46 | G67: https://www.spryinterior.com/collections/corner-floating-shelves | H67: 3 | I67: 0,2 | J67: 1 | K67: 1 | L67: 9 | M67: 0, 0, 78, 100, 78, 35, 21, 78, 50, 7, 7, 35 | N67: ######## | O67: Image pack, Sitelinks, People also ask, Popular products, Related searches | P67: informational, transactional | Q67: Organic
A68: wooden shelf corner | B68: 10 | C68: 9 | D68: 720 | E68: 14 | F68: 0,44 | G68: https://www.spryinterior.com/collections/corner-floating-shelves | H68: 3 | I68: 0,2 | J68: 1 | K68: 0,79 | L68: 223 | M68: 8, 100, 2, 36, 100, 100, 4, 2, 5, 5, 5, 20 | N68: ######## | O68: Image pack, Sitelinks, Video, People also ask, Popular products, Related searches | P68: informational | Q68: Organic
A69: corner shelving unit wall mounted | B69: 7 | C69: 10 | D69: 170 | E69: 29 | F69: 0,4 | G69: https://www.spryinterior.com/collections/corner-floating-shelves | H69: 3 | I69: 0,2 | J69: 1 | K69: 1 | L69: 239 | M69: 81, 23, 66, 3, 100, 1, 18, 0, 44, 0, 1, 3 | N69: ######## | O69: Image pack, Sitelinks, Video, Popular products, Related searches | P69: informational | Q69: Organic
A70: wood corner shelf unit | B70: 3 | C70: 7 | D70: 110 | E70: 24 | F70: 0,46 | G70: https://www.spryinterior.com/collections/corner-floating-shelves | H70: 3 | I70: 0,2 | J70: 1 | K70: 1 | L70: 259 | M70: 42, 26, 100, 34, 26, 34, 42, 19, 65, 42, 42, 53 | N70: ######## | O70: Image pack, Sitelinks, Video, Popular products, Related searches | P70: informational, transactional | Q70: Organic
A71: cute corner shelves | B71: 3 | C71: 3 | D71: 90 | E71: 25 | F71: 0,46 | G71: https://www.spryinterior.com/collections/corner-floating-shelves | H71: 3 | I71: 0,2 | J71: 1 | K71: 1 | L71: 225 | M71: 19, 26, 34, 42, 42, 26, 53, 34, 34, 42, 34, 26 | N71: ######## | O71: Image pack, Sitelinks, Video, Image, Video Carousel, Popular products, Related searches | P71: commercial | Q71: Organic
A72: corner shelves wall mounted | B72: 7 | C72: 8 | D72: 480 | E72: 35 | F72: 0,4 | G72: https://www.spryinterior.com/collections/corner-floating-shelves | H72: 3 | I72: 0,2 | J72: 1 | K72: 1 | L72: 231 | M72: 45, 45, 55, 100, 24, 20, 45, 16, 67, 0, 0, 30 | N72: ######## | O72: Image pack, Sitelinks, Video, Video Carousel, Popular products, Related searches | P72: informational, transactional | Q72: Organic
A73: corner wall hanging shelf | B73: 9 | C73: 9 | D73: 390 | E73: 31 | F73: 0,5 | G73: https://www.spryinterior.com/collections/corner-floating-shelves | H73: 3 | I73: 0,2 | J73: 1 | K73: 1 | L73: 250 | M73: 36, 36, 81, 54, 29, 23, 54, 29, 67, 29, 44, 44 | N73: ######## | O73: Image pack, Sitelinks, Video, Popular products, Related searches | P73: commercial, informational | Q73: Organic
A74: hanging corner shelf | B74: 12 | C74: 12 | D74: 1300 | E74: 41 | F74: 0,43 | G74: https://www.spryinterior.com/collections/corner-floating-shelves | H74: 3 | I74: 0,2 | J74: 1 | K74: 1 | L74: 234 | M74: 20, 22, 22, 43, 29, 29, 29, 29, 22, 36, 29, 22 | N74: ######## | O74: Image pack, Sitelinks, Video, People also ask, Popular products, Related searches | P74: informational | Q74: Organic
A75: shelves for corner wall | B75: 8 | C75: 17 | D75: 140 | E75: 23 | F75: 0,4 | G75: https://www.spryinterior.com/collections/corner-floating-shelves | H75: 3 | I75: 0,2 | J75: 1 | K75: 1 | L75: 223 | M75: 3, 9, 14, 14, 9, 72, 7, 3, 17, 3, 2, 17 | N75: ######## | O75: Image pack, Sitelinks, Video, Popular products, Related searches | P75: commercial | Q75: Organic
A76: modern corner shelving | B76: 4 | C76: 4 | D76: 90 | E76: 17 | F76: 0,65 | G76: https://www.spryinterior.com/collections/corner-floating-shelves | H76: 3 | I76: 0,2 | J76: 1 | K76: 1 | L76: 224 | M76: 12, 28, 12, 28, 17, 23, 23, 28, 23, 17, 17, 17 | N76: ######## | O76: Image pack, Sitelinks, Video, Popular products, Related searches | P76: commercial | Q76: Organic
A77: contemporary corner shelves | B77: 4 | C77: 4 | D77: 90 | E77: 18 | F77: 0,65 | G77: https://www.spryinterior.com/collections/corner-floating-shelves | H77: 3 | I77: 0,2 | J77: 1 | K77: 1 | L77: 207 | M77: 34, 100, 43, 3, 21, 15, 28, 43, 21, 28, 12, 21 | N77: ######## | O77: Sitelinks, Video, Popular products, Related searches, Short videos | P77: commercial | Q77: Organic
A78: corner shelf unit wood | B78: 3 | C78: 3 | D78: 90 | E78: 32 | F78: 0,46 | G78: https://www.spryinterior.com/collections/corner-floating-shelves | H78: 3 | I78: 0,2 | J78: 1 | K78: 1 | L78: 10700 | M78: 21, 15, 100, 34, 15, 15, 15, 21, 15, 21, 28, 21 | N78: ######## | O78: Image pack, Sitelinks, Video, Video Carousel, Popular products, Related searches | P78: commercial | Q78: Organic
A79: corner wall mounted shelves | B79: 8 | C79: 6 | D79: 170 | E79: 24 | F79: 0,4 | G79: https://www.spryinterior.com/collections/corner-floating-shelves | H79: 3 | I79: 0,2 | J79: 1 | K79: 1 | L79: 244 | M79: 3, 16, 100, 6, 5, 6, 5, 5, 6, 3, 8, 8 | N79: ######## | O79: Image pack, Sitelinks, Video, Popular products, Related searches | P79: commercial | Q79: Organic
A80: decorative corner shelving | B80: 5 | C80: 5 | D80: 140 | E80: 33 | F80: 0,36 | G80: https://www.spryinterior.com/collections/corner-floating-shelves | H80: 3 | I80: 0,2 | J80: 1 | K80: 1 | L80: 245 | M80: 28, 34, 21, 100, 43, 43, 28, 21, 43, 43, 53, 34 | N80: ######## | O80: Local pack, Image pack, Sitelinks, Video, Image, Popular products, Related searches | P80: commercial | Q80: Organic
... A102: shelf for corner wall | B102: 3 | C102: 27 | D102: 140 | E102: 35 | F102: 0,4 | G102: https://www.spryinterior.com/collections/corner-floating-shelves | H102: 2 | I102: 0,13 | J102: 0 | K102: 1 | L102: 221 | M102: 1, 100, 2, 3, 3, 3, 3, 3, 1, 1, 0, 3 | N102: ######## | O102: Image pack, Sitelinks, Video, Video Carousel, People also ask, Popular products, Related searches | P102: informational | Q102: Organic
A103: wood for corner shelf | B103: 16 | C103: 10 | D103: 1600 | E103: 20 | F103: 0,44 | G103: https://www.spryinterior.com/collections/corner-floating-shelves | H103: 2 | I103: 0,13 | J103: 0 | K103: 0,79 | L103: 207 | M103: 66, 66, 79, 79, 79, 79, 100, 79, 100, 0, 0, 0 | N103: ######## | O103: Image pack, Sitelinks, Video, Popular products, Related searches | P103: informational | Q103: Organic
A104: floating corner wall shelf | B104: 11 | C104: 15 | D104: 880 | E104: 15 | F104: 0,48 | G104: https://www.spryinterior.com/collections/corner-floating-shelves | H104: 2 | I104: 0,13 | J104: 0 | K104: 1 | L104: 223 | M104: 24, 45, 62, 55, 45, 45, 45, 100, 100, 62, 30, 24 | N104: ######## | O104: Image pack, Sitelinks, Video, Video Carousel, Popular products, Related searches | P104: informational | Q104: Organic
A105: corner hangign book shelf | B105: 2 | C105: 1 | D105: 50 | E105: 35 | F105: 0 | G105: https://www.spryinterior.com/collections/corner-floating-shelves | H105: 2 | I105: 0,13 | J105: 0 | K105: 0 | L105: 10 | M105: 100, 100, 0, 0, 0, 0 | N105: ######## | O105: Image pack, Sitelinks, Popular products, Related searches | P105: informational | Q105: Organic
A106: floating shelves in a corner | B106: 9 | C106: 11 | D106: 590 | E106: 18 | F106: 0,44 | G106: https://www.spryinterior.com/collections/corner-floating-shelves | H106: 2 | I106: 0,13 | J106: 0 | K106: 1 | L106: 188 | M106: 0, 0, 1, 1, 3, 3, 3, 4, 5, 100, 3, 2 | N106: ######## | O106: Image pack, Sitelinks, Reviews, Video, Video Carousel, People also ask, Popular products, Related searches | P106: informational | Q106: Organic
A107: corner book shelf wall mounted | B107: 3 | C107: 15 | D107: 70 | E107: 30 | F107: 0,45 | G107: https://www.spryinterior.com/collections/corner-floating-shelves | H107: 2 | I107: 0,13 | J107: 0 | K107: 1 | L107: 231 | M107: 26, 19, 0, 26, 34, 26, 34, 34, 42, 26, 26, 19 | N107: ######## | O107: Image pack, Sitelinks, Video, People also ask, Popular products, Related searches | P107: commercial, informational | Q107: Organic
A108: corner shelf in bedroom | B108: 10 | C108: 10 | D108: 720 | E108: 28 | F108: 0,41 | G108: https://www.spryinterior.com/collections/corner-floating-shelves | H108: 2 | I108: 0,13 | J108: 0 | K108: 1 | L108: 192 | M108: 0, 100, 6, 45, 62, 62, 13, 4, 81, 62, 62, 5 | N108: ######## | O108: Image pack, Sitelinks, Video, Image, Video Carousel, People also ask, Popular products, Related searches | P108: informational | Q108: Organic
A109: corner shelf unit wooden | B109: 4 | C109: 4 | D109: 70 | E109: 27 | F109: 0,45 | G109: https://www.spryinterior.com/collections/corner-floating-shelves | H109: 2 | I109: 0,13 | J109: 0 | K109: 1 | L109: 232 | M109: 34, 80, 53, 65, 7, 3, 0, 0, 0, 100, 0, 0 | N109: ######## | O109: Image pack, Sitelinks, Video, Video Carousel, Popular products, Related searches | P109: commercial | Q109: Organic
A110: corner shelving for bedrooms | B110: 8 | C110: 9 | D110: 110 | E110: 34 | F110: 0,41 | G110: https://www.spryinterior.com/collections/corner-floating-shelves | H110: 2 | I110: 0,13 | J110: 0 | K110: 1 | L110: 196 | M110: 35, 43, 54, 6, 10, 18, 14, 2, 18, 0, 100, 0 | N110: ######## | O110: Sitelinks, Video, Popular products, Related searches | P110: commercial | Q110: Organic
A111: corner shelf wood for room | B111: 3 | C111: 3 | D111: 40 | E111: 22 | F111: 0,49 | G111: https://www.spryinterior.com/collections/corner-floating-shelves | H111: 2 | I111: 0,13 | J111: 0 | K111: 1 | L111: 122 | M111: 14, 14, 64, 50, 50, 100, 28, 7, 0, 0, 0, 7 | N111: ######## | O111: Sitelinks, Video, Video Carousel, People also ask, Related searches, AI overview | P111: commercial | Q111: Organic
A112: mountable corner shelves | B112: 9 | C112: 11 | D112: 170 | E112: 30 | F112: 0,43 | G112: https://www.spryinterior.com/collections/corner-floating-shelves | H112: 2 | I112: 0,13 | J112: 0 | K112: 1 | L112: 199 | M112: 53, 43, 100, 53, 43, 53, 65, 21, 65, 43, 21, 28 | N112: ######## | O112: Sitelinks, Video, Popular products, Related searches | P112: commercial | Q112: Organic
A113: book shelf wall corner | B113: 2 | C113: 2 | D113: 70 | E113: 29 | F113: 0,64 | G113: https://www.spryinterior.com/collections/corner-floating-shelves | H113: 2 | I113: 0,13 | J113: 1 | K113: 1 | L113: 244 | M113: 35, 35, 100, 50, 50, 50, 50, 50, 50, 50, 50, 50 | N113: ######## | O113: Image pack, Sitelinks, Video, People also ask, Popular products, Related searches | P113: informational | Q113: Organic
A114: individual corner shelves | B114: 6 | C114: 15 | D114: 90 | E114: 30 | F114: 0,42 | G114: https://www.spryinterior.com/collections/corner-floating-shelves | H114: 2 | I114: 0,13 | J114: 0 | K114: 1 | L114: 8 | M114: 64, 52, 41, 82, 64, 64, 64, 41, 52, 41, 64, 52 | N114: ######## | O114: Sitelinks, Popular products, Related searches | P114: commercial | Q114: Organic
A115: wall mounted corner shelf | B115: 8 | C115: 8 | D115: 880 | E115: 33 | F115: 0,4 | G115: https://www.spryinterior.com/collections/corner-floating-shelves | H115: 2 | I115: 0,13 | J115: 0 | K115: 1 | L115: 251 | M115: 10, 5, 10, 22, 8, 36, 8, 36, 16, 43, 7, 16 | N115: ######## | O115: Image pack, Sitelinks, Video, Image, People also ask, Popular products, Related searches, Short videos | P115: commercial | Q115: Organic
A116: corner dining room shelf | B116: 4 | C116: 10 | D116: 50 | E116: 22 | F116: 0,45 | G116: https://www.spryinterior.com/collections/corner-floating-shelves | H116: 2 | I116: 0,13 | J116: 0 | K116: 1 | L116: 195 | M116: 43, 28, 2, 5, 2, 2, 12, 7, 23, 12, 23, 5 | N116: ######## | O116: Image pack, Sitelinks, Video, Image, People also ask, Related searches | P116: informational, transactional | Q116: Organic
A117: corner wall mounted bookshelves | B117: 2 | C117: 0 | D117: 40 | E117: 28 | F117: 0,46 | G117: https://www.spryinterior.com/collections/corner-floating-shelves | H117: 2 | I117: 0,13 | J117: 0 | K117: 1 | L117: 229 | M117: 0, 0, 0, 0, 0, 0, 100, 4, 80, 0, 0, 0 | N117: ######## | O117: Image pack, Sitelinks, Video, Popular products, Related searches | P117: informational | Q117: Organic
... A134: corner shelves for living room | B134: 23 | C134: 11 | D134: 1000 | E134: 33 | F134: 0,46 | G134: https://www.spryinterior.com/collections/corner-floating-shelves | H134: 1 | I134: 0,06 | J134: 0 | K134: 1 | L134: 233 | M134: 54, 16, 54, 66, 36, 41, 100, 54, 79, 36, 24, 13 | N134: ######## | O134: Image pack, Sitelinks, Video, Image, Popular products, Related searches | P134: commercial | Q134: Organic
A135: wall mounted corner shelving unit | B135: 5 | C135: 5 | D135: 40 | E135: 25 | F135: 0 | G135: https://www.spryinterior.com/collections/corner-floating-shelves | H135: 1 | I135: 0,06 | J135: 0 | K135: 1 | L135: 197 | M135: 18, 18, 100, 100, 18, 18, 18, 18, 18, 18, 18, 18 | N135: ######## | O135: Image pack, Sitelinks, Video, Video Carousel, Related searches | P135: informational | Q135: Organic
A136: corner shelf white floating | B136: 9 | C136: 25 | D136: 170 | E136: 23 | F136: 0,55 | G136: https://www.spryinterior.com/collections/corner-floating-shelves | H136: 1 | I136: 0,06 | J136: 0 | K136: 1 | L136: 9 | M136: 54, 54, 100, 2, 6, 9, 15, 5, 12, 5, 6, 2 | N136: ######## | O136: Image pack, Sitelinks, People also ask, Popular products, Related searches | P136: informational, transactional | Q136: Organic
A137: wall mounted corner bookshelf | B137: 7 | C137: 7 | D137: 90 | E137: 29 | F137: 0,61 | G137: https://www.spryinterior.com/collections/corner-floating-shelves | H137: 1 | I137: 0,06 | J137: 0 | K137: 1 | L137: 234 | M137: 34, 26, 34, 34, 42, 42, 42, 34, 34, 34, 26, 26 | N137: ######## | O137: Image pack, Sitelinks, Video, Video Carousel, Popular products, Related searches | P137: commercial | Q137: Organic
A138: wall corner wooden shelf | B138: 5 | C138: 0 | D138: 50 | E138: 27 | F138: 0,44 | G138: https://www.spryinterior.com/collections/corner-floating-shelves | H138: 1 | I138: 0,06 | J138: 0 | K138: 1 | L138: 255 | M138: 0, 0, 0, 0, 0, 0, 100, 0, 100, 0, 65, 3 | N138: ######## | O138: Image pack, Sitelinks, Video, Video Carousel, Popular products, Related searches | P138: informational | Q138: Organic
A139: corner mount wall shelf | B139: 10 | C139: 16 | D139: 110 | E139: 32 | F139: 0,4 | G139: https://www.spryinterior.com/collections/corner-floating-shelves | H139: 1 | I139: 0,06 | J139: 0 | K139: 1 | L139: 195 | M139: 29, 35, 43, 2, 4, 0, 66, 0, 100, 0, 0, 0 | N139: ######## | O139: Image pack, Sitelinks, Video, Related searches | P139: informational | Q139: Organic
A140: corner sheld | B140: 4 | C140: 18 | D140: 40 | E140: 40 | F140: 0,42 | G140: https://www.spryinterior.com/collections/corner-floating-shelves | H140: 1 | I140: 0,06 | J140: 0 | K140: 1 | L140: 258 | M140: 23, 0, 15, 15, 6, 6, 1, 0, 1, 1, 6, 11 | N140: ######## | O140: Image pack, Sitelinks, Video, People also ask, Popular products, Related searches, Things to know | P140: commercial | Q140: Organic
A141: wall corner shelf unit | B141: 3 | C141: 3 | D141: 40 | E141: 29 | F141: 0,56 | G141: https://www.spryinterior.com/collections/corner-floating-shelves | H141: 1 | I141: 0,06 | J141: 0 | K141: 1 | L141: 229 | M141: 12, 28, 12, 5, 0, 5, 7, 23, 7, 28, 2, 0 | N141: ######## | O141: Image pack, Sitelinks, Video, Video Carousel, Popular products, Related searches | P141: commercial | Q141: Organic
A142: small corner floating shelves | B142: 6 | C142: 6 | D142: 50 | E142: 19 | F142: 0,4 | G142: https://www.spryinterior.com/collections/corner-floating-shelves | H142: 1 | I142: 0,06 | J142: 0 | K142: 1 | L142: 216 | M142: 0, 0, 100, 55, 55, 33, 55, 44, 77, 77, 77, 77 | N142: ######## | O142: Image pack, Sitelinks, Video, Popular products, Related searches | P142: commercial | Q142: Organic
A143: corner floating wall shelf | B143: 9 | C143: 9 | D143: 390 | E143: 13 | F143: 0,48 | G143: https://www.spryinterior.com/collections/corner-floating-shelves | H143: 1 | I143: 0,06 | J143: 0 | K143: 1 | L143: 215 | M143: 23, 54, 54, 100, 66, 29, 29, 66, 81, 81, 23, 15 | N143: ######## | O143: Image pack, Sitelinks, Reviews, Video, Image, Video Carousel, Popular products, Related searches | P143: informational | Q143: Organic
A144: corner shelf floating wood | B144: 13 | C144: 13 | D144: 480 | E144: 20 | F144: 0,54 | G144: https://www.spryinterior.com/collections/corner-floating-shelves | H144: 1 | I144: 0,06 | J144: 0 | K144: 1 | L144: 189 | M144: 25, 31, 25, 52, 1, 1, 0, 84, 1, 100, 1, 1 | N144: ######## | O144: Sitelinks, Reviews, Video, Popular products, Related searches | P144: commercial, informational | Q144: Organic
A145: corner shelfing | B145: 3 | C145: 3 | D145: 90 | E145: 26 | F145: 0,46 | G145: https://www.spryinterior.com/collections/corner-floating-shelves | H145: 1 | I145: 0,06 | J145: 0 | K145: 1 | L145: 223 | M145: 0, 0, 0, 22, 1, 0, 0, 0, 0, 0, 0, 0 | N145: ######## | O145: Image pack, Sitelinks, Video, Popular products, Related searches, Things to know | P145: informational, transactional | Q145: Organic
A146: corner wall shelf wood | B146: 8 | C146: 10 | D146: 110 | E146: 23 | F146: 0,44 | G146: https://www.spryinterior.com/collections/corner-floating-shelves | H146: 1 | I146: 0,06 | J146: 0 | K146: 1 | L146: 197 | M146: 0, 1, 100, 3, 1, 2, 2, 3, 2, 1, 1, 2 | N146: ######## | O146: Image pack, Sitelinks, Video, Video Carousel, Popular products, Related searches | P146: informational | Q146: Organic
A147: wall corner stand | B147: 6 | C147: 12 | D147: 50 | E147: 34 | F147: 0,41 | G147: https://www.spryinterior.com/collections/corner-floating-shelves | H147: 1 | I147: 0,06 | J147: 0 | K147: 1 | L147: 238 | M147: 18, 18, 9, 63, 45, 45, 63, 63, 100, 63, 18, 18 | N147: ######## | O147: Image pack, Sitelinks, Video, Video Carousel, Popular products, Related searches | P147: commercial | Q147: Organic
A148: corner wall shelving units | B148: 4 | C148: 6 | D148: 50 | E148: 30 | F148: 0,38 | G148: https://www.spryinterior.com/collections/corner-floating-shelves | H148: 1 | I148: 0,06 | J148: 0 | K148: 1 | L148: 206 | M148: 17, 17, 53, 2, 10, 5, 2, 5, 17, 0, 2, 2 | N148: ######## | O148: Sitelinks, Video, Video Carousel, Popular products, Related searches | P148: commercial | Q148: Organic
A149: wall corner book shelf design | B149: 3 | C149: 0 | D149: 40 | E149: 30 | F149: 0 | G149: https://www.spryinterior.com/collections/corner-floating-shelves | H149: 1 | I149: 0,06 | J149: 0 | K149: 1 | L149: 218 | M149: 50, 14, 28, 14, 14, 100, 14, 14, 14, 14, 14, 14 | N149: ######## | O149: Image pack, Sitelinks, Video, Video Carousel, Popular products, Related searches, Short videos | P149: commercial | Q149: Organic
A150: living room corner shelving | B150: 5 | C150: 5 | D150: 50 | E150: 23 | F150: 0,46 | G150: https://www.spryinterior.com/collections/corner-floating-shelves | H150: 1 | I150: 0,06 | J150: 0 | K150: 1 | L150: 234 | M150: 10, 0, 29, 0, 0, 0, 54, 2, 35, 0, 0, 0 | N150: ######## | O150: Image pack, Sitelinks, Video, Video Carousel, Popular products, Related searches | P150: informational | Q150: Organic
A151: corner+shelving | B151: 3 | C151: 0 | D151: 40 | E151: 35 | F151: 0,42 | G151: https://www.spryinterior.com/collections/corner-floating-shelves | H151: 1 | I151: 0,06 | J151: 0 | K151: 1 | L151: 203 | M151: 71, 71, 71, 100, 71, 71, 100, 100, 100, 0, 0, 0 | N151: ######## | O151: Sitelinks, Video, People also ask, Popular products, Related searches | P151: commercial | Q151: Organic
A152: small floating corner shelves | B152: 5 | C152: 5 | D152: 50 | E152: 19 | F152: 0,4 | G152: https://www.spryinterior.com/collections/corner-floating-shelves | H152: 1 | I152: 0,06 | J152: 0 | K152: 1 | L152: 222 | M152: 55, 44, 55, 100, 77, 33, 44, 55, 77, 33, 55, 77 | N152: ######## | O152: Image pack, Sitelinks, Video, Video Carousel, Popular products, Related searches | P152: commercial | Q152: Organic
...

Sheet Keyword Blog
A1: Dòng sản phẩm | B1: Dạng nội dung | C1: Phễu | D1: Ưu tiên | E1: Title SEO (Tiếng Anh) | F1: Title (Tiếng Việt) | G1: Nguồn | H1: Keyword target (tối đa 3, không trùng bài khác)
A2: Tree Bookshelf | B2: Buying Guide | C2: Đáy phễu (sẵn sàng mua) | D2: Cao | E2: Tree Bookshelf Buying Guide: Sizes, Wood Types & What to Check Before You Buy | F2: Hướng dẫn mua kệ sách hình cây: kích thước, loại gỗ và những điều cần kiểm tra | G2: Ashdeco
A3: Tree Bookshelf | B3: Buying Guide | C3: Đáy phễu (sẵn sàng mua) | D3: Cao | E3: Tree Bookshelf Dimensions: A Sizing Chart for Every Room | F3: Kích thước kệ sách hình cây: bảng tra cứu cho từng loại phòng | G3: Ashdeco & Spry | H3: tree bookshelf measurements (70) tree bookshelf dimensions (20)
A4: Tree Bookshelf | B4: Room Ideas | C4: Giữa phễu (cân nhắc) | D4: Trung bình | E4: Tree Bookshelf Ideas for Kids' Rooms & Nurseries | F4: Ý tưởng bố trí kệ sách hình cây cho phòng trẻ em | G4: Ashdeco & Spry | H4: tree bookshelf for nursery (140) nursery bookshelf tree (90) tree bookshelf nursery (50)
A5: Tree Bookshelf | B5: Room Ideas | C5: Đỉnh phễu (cảm hứng) | D5: Trung bình | E5: Where to Place a Tree Bookshelf: Living Room vs Bedroom vs Reading Corner | F5: Nên đặt kệ sách hình cây ở đâu: phòng khách, phòng ngủ hay góc đọc sách | G5: Ashdeco | H5: best place to put Tree Bookshelf
A6: Tree Bookshelf | B6: Wood Knowledge | C6: Đỉnh phễu (xây thẩm quyền) | D6: Cao | E6: How a Tree Bookshelf Is Hand-Carved: From Log to Sculptural Shelf | F6: Quy trình chế tác thủ công kệ sách hình cây: từ khúc gỗ đến tác phẩm điêu khắc | G6: Ashdeco | H6: How a Tree Bookshelf made
A7: Tree Bookshelf | B7: DIY Tutorial | C7: Giữa phễu (gỡ rào cản) | D7: Thấp | E7: Tree Bookshelf Assembly: Step-by-Step in Under 30 Minutes | F7: Lắp ráp kệ sách hình cây trong 30 phút | G7: Ashdeco | H7: tree bookshelf diy (260) tree bookshelf instructions (20)
A8: Tree Bookshelf | B8: Comparison | C8: Giữa phễu (cân nhắc) | D8: Trung bình | E8: Tree Branch Bookshelf vs Tree Bookcase: What's the Real Difference? | F8: Kệ cành cây và tủ sách hình cây khác nhau thế nào | G8: Ashdeco
A9: Tree Bookshelf | B9: Safety Guide | C9: Giữa phễu (gỡ rào cản) | D9: Cao | E9: Is a Tree Bookshelf Safe for Kids? Anti-Tip Anchoring Explained | F9: Kệ sách hình cây có an toàn cho trẻ nhỏ? Hướng dẫn neo chống lật | G9: Claude
A10: Tree Bookshelf | B10: Sustainability/Sourcing | C10: Đỉnh phễu (xây thẩm quyền) | D10: Cao | E10: Where Does Wrydeco's Wood Come From? Sourcing Behind Every Tree Bookshelf | F10: Gỗ làm kệ sách hình cây của Wrydeco đến từ đâu? Câu chuyện nguồn gốc | G10: Claude
A11: Tree Bookshelf | B11: Value/Price Guide | C11: Giữa-đáy phễu | D11: Trung bình | E11: Why a Handcrafted Tree Bookshelf Costs More Than a Flat-Pack Shelf | F11: Vì sao kệ sách hình cây thủ công đắt hơn kệ lắp ráp công nghiệp | G11: Claude | H11: tree bookshelf price (10)
A12: Tree Bookshelf | B12: Durability Guide | C12: Giữa phễu (cân nhắc) | D12: Trung bình | E12: How Long Does a Solid Wood Tree Bookshelf Last? | F12: Kệ sách hình cây gỗ tự nhiên dùng được bao lâu? | G12: Claude
A13: Tree Bookshelf | B13: Care & Maintenance | C13: Sau mua (giữ chân khách) | D13: Trung bình | E13: Caring for Your Solid Wood Tree Bookshelf: Cleaning & Long-Term Care | F13: Cách chăm sóc và bảo quản kệ sách hình cây gỗ tự nhiên | G13: Claude
A14: Floating Bookshelf | B14: Buying Guide | C14: Đáy phễu (sẵn sàng mua) | D14: Cao | E14: Floating Shelf Weight Limit Guide: How Much Can Yours Hold? | F14: Hướng dẫn tải trọng kệ treo tường: kệ chịu được bao nhiêu kg | G14: Ashdeco & Spry
A15: Floating Bookshelf | B15: Buying Guide | C15: Đáy phễu (sẵn sàng mua) | D15: Cao | E15: Corner Floating Shelf Measurement Guide: Getting the Fit Right | F15: Hướng dẫn đo kích thước kệ góc treo tường | G15: Ashdeco
A16: Floating Bookshelf | B16: Room Ideas | C16: Đỉnh phễu (cảm hứng) | D16: Cao | E16: Staggered Floating Shelves: Layout Ideas for Every Room | F16: Ý tưởng bố trí kệ treo tường so le cho mọi không gian | G16: Ashdeco
A17: Floating Bookshelf | B17: Room Ideas | C17: Giữa phễu (cân nhắc) | D17: Trung bình | E17: Floating Shelves Above the Bed: Styling Ideas That Work | F17: Ý tưởng trang trí kệ treo tường phía trên giường | G17: Ashdeco & Spry
A18: Floating Bookshelf | B18: DIY Tutorial | C18: Giữa phễu (gỡ rào cản) | D18: Cao | E18: How to Mount Floating Shelves Without Damaging Your Wall | F18: Cách lắp kệ treo tường không làm hỏng tường | G18: Ashdeco & Spry | H18: how to put up floating corner shelves (20) Chưa có trong bộ từ khóa hiện có Chưa có trong bộ từ khóa hiện có
A19: Floating Bookshelf | B19: Wood Knowledge | C19: Đỉnh phễu (xây thẩm quyền) | D19: Trung bình | E19: Solid Wood vs Engineered Wood Floating Shelves: What Lasts Longer? | F19: Kệ treo tường gỗ tự nhiên và gỗ công nghiệp: loại nào bền hơn | G19: Spry
A20: Floating Bookshelf | B20: Sustainability/Sourcing | C20: Đỉnh phễu (xây thẩm quyền) | D20: Cao | E20: The Wood Behind Every Wrydeco Floating Shelf: Sourcing & Sustainability | F20: Câu chuyện nguồn gốc gỗ đằng sau mỗi kệ treo tường của Wrydeco | G20: Claude
A21: Floating Bookshelf | B21: Value/Price Guide | C21: Giữa-đáy phễu | D21: Trung bình | E21: Handcrafted vs Mass-Produced Floating Shelves: What You're Paying For | F21: Kệ treo tường thủ công và kệ sản xuất hàng loạt: khác nhau ở đâu | G21: Claude
A22: Floating Bookshelf | B22: Care & Maintenance | C22: Sau mua (giữ chân khách) | D22: Trung bình | E22: How to Clean and Care for Solid Wood Floating Shelves | F22: Cách vệ sinh và bảo quản kệ treo tường gỗ tự nhiên | G22: Claude
A23: Corner Bookshelf | B23: Room Ideas | C23: Đỉnh phễu (cảm hứng) | D23: Cao | E23: Corner Bookshelf Ideas for Small Apartments | F23: Ý tưởng kệ sách góc cho căn hộ nhỏ | G23: Ashdeco | H23: are corner shelves a good idea (20) how to decorate a corner bookshelf (20) what to put on a corner shelf (20)
A24: Corner Bookshelf | B24: Buying Guide | C24: Đáy phễu (sẵn sàng mua) | D24: Cao | E24: Corner Bookshelf Buying Guide: Finding the Right Fit for Your Corner | F24: Hướng dẫn mua kệ sách góc: chọn đúng kích thước cho góc nhà | G24: Ashdeco | H24: are there bookshelves that stand in the corner (320) Chưa có trong bộ từ khóa hiện có Chưa có trong bộ từ khóa hiện có
A25: Corner Bookshelf | B25: Room Ideas | C25: Giữa phễu (cân nhắc) | D25: Trung bình | E25: Corner Bookshelf Styling Ideas for the Living Room | F25: Ý tưởng bố trí kệ sách góc trong phòng khách | G25: Ashdeco & Spry | H25: how to decorate a corner shelf (90) how to decorate corner shelves (70) how to style corner shelves (20)
A26: Corner Bookshelf | B26: Comparison | C26: Giữa phễu (cân nhắc) | D26: Trung bình | E26: Corner Bookshelf vs Corner Bookcase: What's the Difference? | F26: Kệ sách góc và tủ sách góc khác nhau ra sao | G26: Ashdeco | H26: are bookcases and bookshelves the same (320) what is the difference between a bookshelf and a bookcase (30) Chưa có trong bộ từ khóa hiện có
A27: Corner Bookshelf | B27: DIY Tutorial | C27: Giữa phễu (gỡ rào cản) | D27: Thấp | E27: How to Measure Your Corner Before Buying a Corner Bookshelf | F27: Cách đo góc nhà trước khi mua kệ sách góc | G27: Claude
A28: Corner Bookshelf | B28: Wood Knowledge | C28: Đỉnh phễu (xây thẩm quyền) | D28: Thấp | E28: Why Corner Bookshelves Make the Most of Dead Space | F28: Vì sao kệ sách góc tận dụng không gian chết hiệu quả nhất | G28: Ashdeco
A29: Corner Bookshelf | B29: Safety Guide | C29: Giữa phễu (gỡ rào cản) | D29: Cao | E29: Is a Corner Bookshelf Safe for Kids? How to Anchor It Properly | F29: Kệ sách góc có an toàn cho trẻ nhỏ? Cách neo chống lật đúng cách | G29: Claude
A30: Corner Bookshelf | B30: Sustainability/Sourcing | C30: Đỉnh phễu (xây thẩm quyền) | D30: Cao | E30: The Wood Behind Every Wrydeco Corner Bookshelf: Sourcing Story | F30: Câu chuyện nguồn gốc gỗ đằng sau mỗi kệ sách góc của Wrydeco | G30: Claude
A31: Corner Bookshelf | B31: Value/Price Guide | C31: Giữa-đáy phễu | D31: Trung bình | E31: Why a Handcrafted Corner Bookshelf Is Worth the Price | F31: Vì sao kệ sách góc thủ công xứng đáng với mức giá | G31: Claude | H31: how much should a bookcase cost (90) how much does a bookcase cost (70) Chưa có trong bộ từ khóa hiện có
A32: Corner Bookshelf | B32: Care & Maintenance | C32: Sau mua (giữ chân khách) | D32: Trung bình | E32: Caring for Your Solid Wood Corner Bookshelf | F32: Cách chăm sóc và bảo quản kệ sách góc gỗ tự nhiên | G32: Claude
A33: TV Stand/TV Shelf | B33: Buying Guide | C33: Đáy phễu (sẵn sàng mua) | D33: Cao | E33: TV Stand Buying Guide: Sizing It to Your Screen and Room | F33: Hướng dẫn mua kệ tivi: chọn kích thước theo màn hình và phòng | G33: Ashdeco | H33: how to choose a tv stand (320) what is a tv stand (90) Chưa có trong bộ từ khóa hiện có
A34: TV Stand/TV Shelf | B34: Buying Guide | C34: Đáy phễu (sẵn sàng mua) | D34: Trung bình | E34: TV Cabinet Dimensions by Screen Size: A Quick Reference | F34: Kích thước tủ/kệ tivi theo kích cỡ màn hình | G34: Ashdeco
A35: TV Stand/TV Shelf | B35: Room Ideas | C35: Giữa phễu (cân nhắc) | D35: Trung bình | E35: Floating Shelf Under TV: A Minimalist Alternative to a TV Stand | F35: Kệ treo tường dưới tivi: giải pháp tối giản thay cho kệ tivi truyền thống | G35: Ashdeco & Spry | H35: what to put under a mounted tv (320) what to put under tv on wall (110) Chưa có trong bộ từ khóa hiện có
A36: TV Stand/TV Shelf | B36: Comparison | C36: Giữa phễu (cân nhắc) | D36: Cao | E36: TV Stand or Console Table? Choosing Media Furniture That Fits | F36: Kệ tivi hay bàn console? Chọn nội thất media phù hợp | G36: Claude | H36: what is a console table (3.600) what is a tv console (110) what is an entertainment center (110)
A37: TV Stand/TV Shelf | B37: Wood Knowledge | C37: Đỉnh phễu (xây thẩm quyền) | D37: Thấp | E37: Solid Wood TV Stands vs Engineered Wood: Durability Compared | F37: Kệ tivi gỗ tự nhiên và gỗ công nghiệp: so sánh độ bền | G37: Claude
A38: TV Stand/TV Shelf | B38: Cable Management Guide | C38: Giữa phễu (cân nhắc) | D38: Cao | E38: TV Stand Cable Management: How to Hide Cords for a Clean Setup | F38: Quản lý dây cáp cho kệ tivi: cách giấu dây gọn gàng | G38: Claude | H38: how to hide tv wires with floating shelf (20) Chưa có trong bộ từ khóa hiện có Chưa có trong bộ từ khóa hiện có
A39: TV Stand/TV Shelf | B39: Safety Guide | C39: Giữa phễu (gỡ rào cản) | D39: Cao | E39: TV Stand Safety: Anti-Tip Anchoring to Prevent Tip-Over Accidents | F39: An toàn kệ tivi: cách neo chống lật để phòng tai nạn | G39: Claude
A40: TV Stand/TV Shelf | B40: Comparison | C40: Đỉnh phễu (quyết định đầu tiên) | D40: Trung bình | E40: TV Stand vs Wall Mount: Which Is Right for Your Room? | F40: Kệ tivi hay treo tường: lựa chọn nào phù hợp với phòng bạn | G40: Claude
A41: TV Stand/TV Shelf | B41: Value/Price Guide | C41: Giữa-đáy phễu | D41: Trung bình | E41: Why a Handcrafted TV Stand Costs More Than a Big-Box Console | F41: Vì sao kệ tivi thủ công đắt hơn kệ tivi công nghiệp | G41: Claude | H41: how much is a tv stand (90) Chưa có trong bộ từ khóa hiện có Chưa có trong bộ từ khóa hiện có

Sheet Sheet12

Sheet Thống kê theo silo

Sheet tree bookshelf
A1: Keyword | B1: Volume | C1: Competitive Density
A2: tree bookshelf | B2: 8100 | C2: 0,94
A3: tree shaped bookshelf | B3: 880 | C3: 1
A4: casacomoda 6-tier tree bookshelf for corner | B4: 590 | C4: 0
A5: costway 8-tier free standing tree bookshelf | B5: 590 | C5: 0
A6: tree branch bookshelf | B6: 480 | C6: 1
A7: corner tree bookshelf | B7: 390 | C7: 1
A8: costco tree bookshelf | B8: 390 | C8: 1
A9: solid wood tree bookshelf | B9: 390 | C9: 0,13
A10: bookshelf cat tree | B10: 260 | C10: 1
A11: bookshelf tree | B11: 260 | C11: 1
A12: cat tree bookshelf | B12: 260 | C12: 1
A13: childrens tree bookshelf | B13: 260 | C13: 1
A14: tree bookshelf diy | B14: 260 | C14: 0,99
A15: tree bookshelf ikea | B15: 260 | C15: 1
A16: wooden tree bookshelf | B16: 260 | C16: 1
A17: diy tree bookshelf | B17: 210 | C17: 0,93
A18: tree bookshelf costco | B18: 210 | C18: 1
A19: walmart casacomoda tree bookshelf | B19: 170 | C19: 0,48
A20: floating tree bookshelf | B20: 140 | C20: 0,07
A21: real tree bookshelf | B21: 140 | C21: 1
A22: tree bookshelf for nursery | B22: 140 | C22: 1
A23: tree bookshelf white | B23: 140 | C23: 1
A24: tree wall bookshelf | B24: 140 | C24: 1
A25: babyletto tree bookshelf | B25: 110 | C25: 1
A26: etsy tree bookshelf | B26: 110 | C26: 1
A27: haunted tree bookshelf | B27: 110 | C27: 0
A28: realistic tree bookshelf | B28: 110 | C28: 1
A29: tree corner bookshelf | B29: 110 | C29: 1
A30: vasagle tree bookshelf | B30: 110 | C30: 1
A31: wall tree bookshelf | B31: 110 | C31: 1
A32: white tree bookshelf | B32: 110 | C32: 1
A33: bookshelf that looks like a tree | B33: 90 | C33: 0,76
A34: christmas tree bookshelf | B34: 90 | C34: 0,75
A35: nursery bookshelf tree | B35: 90 | C35: 1
A36: sunmory 6 tier tree bookshelf | B36: 90 | C36: 0,22
A37: tier tree bookshelf | B37: 90 | C37: 1
A38: tree bookshelf wall | B38: 90 | C38: 0,81
A39: walmart casacomoda tree bookshelf sale | B39: 90 | C39: 1
A40: wood tree bookshelf | B40: 90 | C40: 1
A41: babyletto spruce tree bookshelf | B41: 70 | C41: 1
A42: black tree bookshelf | B42: 70 | C42: 0,99
A43: book tree bookshelf | B43: 70 | C43: 1
A44: bookshelf tree design | B44: 70 | C44: 1
A45: free standing tree bookshelf | B45: 70 | C45: 1
A46: how to make a tree bookshelf | B46: 70 | C46: 0,85
A47: small tree bookshelf | B47: 70 | C47: 0,36
A48: tree bookshelf amazon | B48: 70 | C48: 1
A49: tree bookshelf measurements | B49: 70 | C49: 1
A50: tree branch bookshelf diy | B50: 70 | C50: 0,98
A51: tree style bookshelf | B51: 70 | C51: 0,59
A52: tree trunk bookshelf | B52: 70 | C52: 1
A53: 6 tier tree bookshelf | B53: 50 | C53: 1
A54: delta tree bookshelf | B54: 50 | C54: 1
A55: how to make tree bookshelf | B55: 50 | C55: 0,63
A56: tree bookshelf nursery | B56: 50 | C56: 1
A57: tree shape bookshelf | B57: 50 | C57: 0,42
A58: wall mounted tree bookshelf | B58: 50 | C58: 1
A59: yoobure tree bookshelf | B59: 50 | C59: 0,99
A60: 4 tier tree bookshelf | B60: 40 | C60: 1
A61: how to build tree bookshelf | B61: 40 | C61: 0,85
A62: tree bookshelf plans | B62: 40 | C62: 0,81
A63: wayfair tree bookshelf | B63: 40 | C63: 1
A64: 9 tier tree bookshelf | B64: 30 | C64: 1
A65: amazon tree bookshelf | B65: 30 | C65: 1
A66: bookshelf tree plans | B66: 30 | C66: 0,63
A67: clifford cat tree bookshelf | B67: 30 | C67: 0,99
A68: tree bookshelf diy template | B68: 30 | C68: 0,56
A69: 8 tier tree bookshelf | B69: 20 | C69: 0,93
A70: 9 shelf tree bookshelf | B70: 20 | C70: 1
A71: babyletto bookshelf tree | B71: 20 | C71: 1
A72: bamboo tree bookshelf | B72: 20 | C72: 1
A73: best tree bookshelf | B73: 20 | C73: 1
A74: birch tree bookshelf | B74: 20 | C74: 0,9
A75: bookshelf cat tree diy | B75: 20 | C75: 1
A76: bookshelf shaped like a tree | B76: 20 | C76: 1
A77: bookshelf tree costco | B77: 20 | C77: 1
A78: bookshelf tree shape | B78: 20 | C78: 1
A79: buy tree bookshelf | B79: 20 | C79: 1
A80: cat bookshelf tree | B80: 20 | C80: 1
A81: cat tree and bookshelf | B81: 20 | C81: 1
A82: cat tree bookshelf combo | B82: 20 | C82: 1
A83: cheap tree bookshelf | B83: 20 | C83: 0,96
A84: christmas tree in front of bookshelf | B84: 20 | C84: 0,33
A85: christmas tree shaped bookshelf | B85: 20 | C85: 1
A86: christmas tree shop bookshelf | B86: 20 | C86: 1
A87: costco bookshelf tree | B87: 20 | C87: 0,94
A88: costway tree bookshelf | B88: 20 | C88: 0,99
A89: desktop tree bookshelf | B89: 20 | C89: 0,99
A90: diy bookshelf cat tree | B90: 20 | C90: 0,94
A91: diy bookshelf dollar tree | B91: 20 | C91: 0,07
A92: diy cat tree from bookshelf | B92: 20 | C92: 0,33
A93: diy corner tree bookshelf | B93: 20 | C93: 1
A94: diy dollar tree bookshelf | B94: 20 | C94: 0,33
A95: diy tree bookshelf plans | B95: 20 | C95: 0,97
A96: dollar tree bookshelf | B96: 20 | C96: 0,92
A97: dollar tree diy bookshelf | B97: 20 | C97: 0,29
A98: easy diy tree bookshelf | B98: 20 | C98: 0,78
A99: etsy tree branch bookshelf | B99: 20 | C99: 1
A100: furinno tree bookshelf 9-tier floor standing tree bookcase | B100: 20 | C100: 0
...

Sheet tv shelf
A1: Keyword | B1: Volume | C1: Competitive Density
A2: where to buy tv stands | B2: 390 | C2: 1
A3: what to put under a mounted tv | B3: 320 | C3: 1
A4: what to put under tv hanging on wall | B4: 320 | C4: 1
A5: where can i buy a tv stand | B5: 170 | C5: 1
A6: where to buy tv stand | B6: 170 | C6: 1
A7: a v component shelving | B7: 140 | C7: 1
A8: what is a tv console | B8: 110 | C8: 0,94
A9: what is an entertainment center | B9: 110 | C9: 0,49
A10: what to put under tv on wall | B10: 110 | C10: 1
A11: where to buy entertainment center | B11: 110 | C11: 1
A12: does ikea sell televisions | B12: 90 | C12: 0,57
A13: does ikea sell tvs | B13: 90 | C13: 0,66
A14: how much is a tv stand | B14: 90 | C14: 0,83
A15: what is a tv stand | B15: 90 | C15: 0,51
A16: what to put next to a tv stand | B16: 90 | C16: 1
A17: what to put under a hanging tv | B17: 90 | C17: 1
A18: what to put underneath a mounted tv | B18: 90 | C18: 1
A19: where can i get a tv stand | B19: 90 | C19: 0,99
A20: where to buy tv stands near me | B20: 90 | C20: 1
A21: where to get tv stands | B21: 90 | C21: 0,73
A22: do ikea sell tvs | B22: 70 | C22: 0,47
A23: is television a furniture | B23: 70 | C23: 0,06
A24: where can i buy a tv stand near me | B24: 70 | C24: 1
A25: where can i find a tv stand | B25: 70 | C25: 0,99
A26: where to buy fully assembled tv stands | B26: 70 | C26: 1
A27: how to style tv console | B27: 50 | C27: 1
A28: is tv furniture | B28: 50 | C28: 0,13
A29: what is a tv stand called | B29: 50 | C29: 0,81
A30: what to put under wall mounted tv in bedroom | B30: 50 | C30: 1
A31: how much is television stand | B31: 40 | C31: 0,83
A32: how to style a tv console | B32: 40 | C32: 0,95
A33: where can i find tv stands | B33: 40 | C33: 0,99
A34: can a floating shelf hold a tv | B34: 20 | C34: 0,4
A35: can a shelf hold a tv | B35: 20 | C35: 1
A36: can i put a tv on a floating shelf | B36: 20 | C36: 0,71
A37: can you put a tv on a floating shelf | B37: 20 | C37: 1
A38: can you put a tv on a shelf | B38: 20 | C38: 0,99
A39: can you put a tv on a wall shelf | B39: 20 | C39: 0,36
A40: how to add a shelf to a tv cabinet | B40: 20 | C40: 0,63
A41: how to build a corner shelf for tv | B41: 20 | C41: 0,6
A42: how to build a floating shelf for a tv | B42: 20 | C42: 0,95
A43: how to build a floating shelf under tv | B43: 20 | C43: 1
A44: how to build a floating tv shelf | B44: 20 | C44: 0,95
A45: how to build a shelf for a tv | B45: 20 | C45: 0,33
A46: how to build a tv shelf | B46: 20 | C46: 0,33
A47: how to build a tv shelf on the wall | B47: 20 | C47: 0,95
A48: how to decorate shelf above tv | B48: 20 | C48: 0,17
A49: how to decorate shelf under tv | B49: 20 | C49: 0,84
A50: how to decorate tv shelf | B50: 20 | C50: 0,33
A51: how to hide tv wires with floating shelf | B51: 20 | C51: 0,5
A52: how to make a corner shelf for a tv | B52: 20 | C52: 0,6
A53: how to make a corner tv shelf | B53: 20 | C53: 0,6
A54: how to make a floating tv shelf | B54: 20 | C54: 0,95
A55: how to make a pull out tv shelf | B55: 20 | C55: 0,04
A56: how to make a tv shelf | B56: 20 | C56: 0,5
A57: what to put on shelf above tv | B57: 20 | C57: 1
A58: how to put elf on the shelf on tv | B58: 10 | C58: 0,33
A59: when is elf on shelf on tv | B59: 10 | C59: 0,33
A60: when is elf on the shelf on tv | B60: 10 | C60: 0,33
A61: a shelf to put 40 tv on | B61: 0 | C61: 0
A62: a tv shelf | B62: 0 | C62: 0
A63: a v shelf attaches to tv | B63: 0 | C63: 0
A64: are wall tv mounting shelf universal for tv | B64: 0 | C64: 0
A65: can a wall shelf hold a tv | B65: 0 | C65: 0
A66: can i put my flat screen tv on a shelf | B66: 0 | C66: 0
A67: can i use a shelf as a tv stand | B67: 0 | C67: 0
A68: can you hide tv cords behind a 2 shelf unit | B68: 0 | C68: 0
A69: can you hide tv cords behind a floating shelf unit | B69: 0 | C69: 0
A70: does having a tv on metal shelf cause issues | B70: 0 | C70: 0
A71: how close should wall media shelf be to tv | B71: 0 | C71: 0
A72: how far floating shelf from tv | B72: 0 | C72: 0
... A109: how to get a heavy tv on a shelf alone | B109: 0 | C109: 0
A110: how to get elf on shelf on tv | B110: 0 | C110: 0,33
A111: how to get elf on shelf stuck in tv | B111: 0 | C111: 0,33
A112: how to get elf on the shelf on tv | B112: 0 | C112: 0,33
A113: how to get elf on the shelf out of tv | B113: 0 | C113: 0
A114: how to get elf on the shelf stuck in tv | B114: 0 | C114: 0,33
A115: how to get elf on the shelf trapped in tv | B115: 0 | C115: 0
A116: how to hang floating tv shelf | B116: 0 | C116: 0
A117: how to hide cords with tv wall shelf | B117: 0 | C117: 0
A118: how to hide the vcr shelf on the tv console | B118: 0 | C118: 0
A119: how to instal shelf beneath tv wall mount | B119: 0 | C119: 0
A120: how to make a floating corner tv shelf | B120: 0 | C120: 0
A121: how to make a shelf for a tv | B121: 0 | C121: 0
A122: how to make a sliding shelf for tv | B122: 0 | C122: 0
A123: how to make a sliding tv shelf | B123: 0 | C123: 0
A124: how to make a swivel shelf for tv | B124: 0 | C124: 0
A125: how to make a tv wall shelf | B125: 0 | C125: 0
A126: how to make a wall shelf for tv | B126: 0 | C126: 0
... A157: what tv will fit on a 29 27 shelf | B157: 0 | C157: 0
A158: when does elf on a shelf come on tv | B158: 0 | C158: 0,33
A159: when does elf on shelf come on tv | B159: 0 | C159: 0
A160: when does elf on the shelf air on tv 2019 | B160: 0 | C160: 0
A161: when does elf on the shelf come back on tv | B161: 0 | C161: 0
A162: when does elf on the shelf come on tv | B162: 0 | C162: 0,33
A163: when does elf on the shelf come on tv 2016 | B163: 0 | C163: 0
A164: when does elf on the shelf come on tv 2017 | B164: 0 | C164: 0
A165: when does elf on the shelf come on tv 2018 | B165: 0 | C165: 0
A166: when does elf on the shelf play on tv | B166: 0 | C166: 0
...

Sheet corner shelf
A1: Keyword | B1: Relevance | C1: Volume | D1: Competitive Density
A2: a frame shelf | B2: 53 | C2: 480 | D2: 1
A3: a shelf | B3: 55 | C3: 390 | D3: 0,8
A4: where to buy bookcases | B4: 39 | C4: 390 | D4: 1
A5: where to buy bookshelves | B5: 44 | C5: 390 | D5: 1
A6: where to buy shelves | B6: 52 | C6: 390 | D6: 0,99
A7: are bookcases and bookshelves the same | B7: 53 | C7: 320 | D7: 0
A8: are there bookshelves that stand in the corner | B8: 66 | C8: 320 | D8: 0
A9: what are high end tables | B9: 33 | C9: 320 | D9: 0
A10: what is shelving | B10: 62 | C10: 320 | D10: 0,01
A11: where can i buy shelves | B11: 53 | C11: 320 | D11: 0,99
A12: a bookshelf | B12: 48 | C12: 260 | D12: 0,99
A13: a frame bookcase | B13: 53 | C13: 260 | D13: 1
A14: a frame bookshelf | B14: 45 | C14: 260 | D14: 1
A15: a frame ladder shelf | B15: 40 | C15: 260 | D15: 1
A16: how to replace 55 x 16 shelf | B16: 55 | C16: 260 | D16: 0
A17: what is a nightstand | B17: 55 | C17: 260 | D17: 0,24
A18: where to buy nightstands | B18: 36 | C18: 260 | D18: 1
A19: a corner | B19: 56 | C19: 210 | D19: 0,33
A20: how many bookshelves | B20: 62 | C20: 210 | D20: 0,02
A21: where to buy extra shelves for kitchen cabinets | B21: 41 | C21: 210 | D21: 1
A22: a bookcase | B22: 44 | C22: 170 | D22: 0
A23: where can i buy a bookcase | B23: 42 | C23: 170 | D23: 1
A24: where can i buy a bookshelf | B24: 46 | C24: 170 | D24: 1
A25: a frame shelf ladder | B25: 45 | C25: 140 | D25: 1
A26: a frame shelves | B26: 56 | C26: 140 | D26: 1
A27: how to build a corner bookshelf | B27: 43 | C27: 140 | D27: 0,83
A28: is it shelfs or shelves | B28: 62 | C28: 140 | D28: 0,33
A29: what is bookshelf | B29: 44 | C29: 140 | D29: 0,22
A30: where to buy a book shelf | B30: 47 | C30: 140 | D30: 1
A31: where to purchase floating shelves | B31: 44 | C31: 140 | D31: 1
A32: a frame book shelf | B32: 54 | C32: 110 | D32: 1
A33: a frame ladder bookcase | B33: 53 | C33: 110 | D33: 1
A34: a frame wood ladder | B34: 35 | C34: 110 | D34: 1
A35: how to organise shoes in a small space | B35: 56 | C35: 110 | D35: 1
A36: how to organize shoes in a small space | B36: 56 | C36: 110 | D36: 1
A37: how to store shoes in a small space | B37: 56 | C37: 110 | D37: 1
A38: is bookshelf one word | B38: 37 | C38: 110 | D38: 0,33
A39: what is a book shelf | B39: 49 | C39: 110 | D39: 0,17
A40: what is a bookcase | B40: 40 | C40: 110 | D40: 0,17
A41: where can i buy a nightstand | B41: 37 | C41: 110 | D41: 1
A42: a night stand | B42: 35 | C42: 90 | D42: 0,91
A43: a nightstand | B43: 39 | C43: 90 | D43: 0,88
A44: a small table | B44: 49 | C44: 90 | D44: 0,9
A45: how much do shelves cost | B45: 46 | C45: 90 | D45: 0,32
A46: how much should a bookcase cost | B46: 32 | C46: 90 | D46: 1
A47: how to build a corner closet | B47: 54 | C47: 90 | D47: 1
A48: how to build corner bookshelf | B48: 43 | C48: 90 | D48: 0,83
A49: how to decorate a corner shelf | B49: 52 | C49: 90 | D49: 0,96
A50: how to furnish a corner | B50: 56 | C50: 90 | D50: 1
A51: might stand | B51: 39 | C51: 90 | D51: 1
A52: what is the plural of shelf | B52: 62 | C52: 90 | D52: 0,33
A53: where to buy bookcase | B53: 42 | C53: 90 | D53: 1
A54: where to buy bookshelf | B54: 53 | C54: 90 | D54: 1
A55: where to buy bookshelves near me | B55: 46 | C55: 90 | D55: 1
A56: a book shelf | B56: 49 | C56: 70 | D56: 0,99
A57: a night table | B57: 42 | C57: 70 | D57: 0,96
A58: a shaped bookcase | B58: 43 | C58: 70 | D58: 1
A59: can shelves | B59: 62 | C59: 70 | D59: 1
A60: how many book shelves | B60: 62 | C60: 70 | D60: 0,02
A61: how much are shelves | B61: 55 | C61: 70 | D61: 0,35
A62: how much does a bookcase cost | B62: 36 | C62: 70 | D62: 0,48
A63: how much does a bookshelf cost | B63: 40 | C63: 70 | D63: 0,48
A64: how much is a bookshelf | B64: 44 | C64: 70 | D64: 0,61
A65: how much is a shelf | B65: 51 | C65: 70 | D65: 0,35
A66: how to build corner bookcase | B66: 40 | C66: 70 | D66: 1
A67: how to decorate corner shelves | B67: 56 | C67: 70 | D67: 1
A68: how to make a corner closet | B68: 40 | C68: 70 | D68: 1
A69: how wide are bedside tables | B69: 38 | C69: 70 | D69: 0,98
A70: what are narrow domestic walls | B70: 57 | C70: 70 | D70: 0,33
A71: what are shelves | B71: 62 | C71: 70 | D71: 0,12
A72: what is a night stand | B72: 31 | C72: 70 | D72: 0,22
A73: what is a shelves | B73: 62 | C73: 70 | D73: 0,02
A74: what is the plural for shelf | B74: 62 | C74: 70 | D74: 0,33
A75: what shelf | B75: 62 | C75: 70 | D75: 0,12
A76: what's a nightstand | B76: 55 | C76: 70 | D76: 0,1
A77: where can i buy shelving | B77: 61 | C77: 70 | D77: 1
A78: where to buy shelves near me | B78: 49 | C78: 70 | D78: 1
A79: where to buy wall shelves | B79: 46 | C79: 70 | D79: 1
A80: a shaped bookshelf | B80: 49 | C80: 50 | D80: 1
A81: a storage cabinet | B81: 48 | C81: 50 | D81: 1
A82: how to organize shoes in small spaces | B82: 56 | C82: 50 | D82: 0,98
A83: where can i buy wall shelves | B83: 49 | C83: 50 | D83: 1
A84: where to buy a bookshelf | B84: 49 | C84: 50 | D84: 1
A85: where to buy end tables | B85: 39 | C85: 50 | D85: 1
A86: where to buy wood shelves | B86: 47 | C86: 50 | D86: 1
A87: a frame shelving | B87: 39 | C87: 40 | D87: 1
A88: a frame wood shelf | B88: 53 | C88: 40 | D88: 1
A89: a shelving unit | B89: 57 | C89: 40 | D89: 1
A90: how to build a closet in corner of room | B90: 38 | C90: 40 | D90: 0,8
A91: how to store shoes in small space | B91: 56 | C91: 40 | D91: 1
A92: what is a bookshelf | B92: 62 | C92: 40 | D92: 0,22
A93: what is the definition of shelves | B93: 62 | C93: 40 | D93: 0,33
A94: where to buy a bookshelf near me | B94: 49 | C94: 40 | D94: 1
A95: where to buy bookcases near me | B95: 44 | C95: 40 | D95: 1
A96: a frame display shelf | B96: 47 | C96: 30 | D96: 1
A97: a frame shelf unit | B97: 51 | C97: 30 | D97: 1
A98: a frame wooden ladder shelf | B98: 54 | C98: 30 | D98: 1
A99: a storage bin in the corner of joe's room | B99: 55 | C99: 30 | D99: 0,33
A100: a white shelf | B100: 54 | C100: 30 | D100: 0,82
...

Sheet console table
A1: Keyword | B1: Relevance | C1: Volume | D1: Competitive Density
A2: what is a console table | B2: 67 | C2: 3600 | D2: 0,91
A3: what is a sofa table | B3: 67 | C3: 390 | D3: 0,91
A4: what's a console table | B4: 67 | C4: 140 | D4: 0,99
A5: what is the table called that goes behind a couch | B5: 67 | C5: 90 | D5: 1
A6: a frame console table | B6: 67 | C6: 70 | D6: 1
A7: what is the table called that goes behind the couch | B7: 67 | C7: 70 | D7: 1
A8: what is console table | B8: 67 | C8: 50 | D8: 0,93
A9: where to place console table | B9: 67 | C9: 40 | D9: 0,71
A10: where to put a console table | B10: 67 | C10: 30 | D10: 0,93
A11: where to put console table | B11: 67 | C11: 30 | D11: 0,93
A12: a console table | B12: 67 | C12: 20 | D12: 1
A13: can you put a console table in the bedroom | B13: 67 | C13: 20 | D13: 0,83
A14: can you put a console table in the living room | B14: 67 | C14: 20 | D14: 1
A15: can you put tv on console table | B15: 67 | C15: 20 | D15: 0,76
A16: how to choose a console table | B16: 67 | C16: 20 | D16: 0,33
A17: how to use a console table | B17: 67 | C17: 20 | D17: 0,87
A18: how wide is a console table | B18: 67 | C18: 20 | D18: 1
A19: what are console tables | B19: 67 | C19: 20 | D19: 0,91
A20: what are console tables for | B20: 67 | C20: 20 | D20: 0,23
A21: what do you call a narrow table behind a couch | B21: 67 | C21: 20 | D21: 1
A22: what does console table mean | B22: 67 | C22: 20 | D22: 0,91
A23: what is a console table tv | B23: 67 | C23: 20 | D23: 0,63
A24: what is a sofa table called | B24: 67 | C24: 20 | D24: 0,32
A25: what is a sofa table used for | B25: 67 | C25: 20 | D25: 0,59
A26: what is a table called that goes behind a couch | B26: 67 | C26: 20 | D26: 0,96
A27: what is the long table behind a couch called | B27: 67 | C27: 20 | D27: 1
A28: what is the purpose of a sofa table | B28: 67 | C28: 20 | D28: 0,56
A29: what to use instead of a console table | B29: 67 | C29: 20 | D29: 0,92
A30: what's a sofa table | B30: 67 | C30: 20 | D30: 0,83
A31: when to use a sofa table | B31: 67 | C31: 20 | D31: 0,57
A32: where do console tables go | B32: 67 | C32: 20 | D32: 1
A33: where do you put a sofa table | B33: 67 | C33: 20 | D33: 0,1
A34: where do you put console tables | B34: 67 | C34: 20 | D34: 0,14
A35: where does a console table go | B35: 67 | C35: 20 | D35: 0,22
A36: where to place a console table | B36: 67 | C36: 20 | D36: 0,67
A37: where to put a sofa table | B37: 67 | C37: 20 | D37: 0,39
A38: where to put console table in living room | B38: 67 | C38: 20 | D38: 1
A39: why are console tables so short | B39: 67 | C39: 20 | D39: 0,46
A40: must console table | B40: 67 | C40: 10 | D40: 1
A41: what is a console table for living room | B41: 67 | C41: 10 | D41: 1
A42: where can i buy a console table | B42: 67 | C42: 10 | D42: 1
A43: where do you put a console table | B43: 67 | C43: 10 | D43: 0,93
A44: where to buy a console table | B44: 67 | C44: 10 | D44: 1
A45: a base console sofa tables a leg console sofa tables | B45: 67 | C45: 0 | D45: 0
A46: a console table meaning | B46: 67 | C46: 0 | D46: 0
A47: a line console sofa tables | B47: 67 | C47: 0 | D47: 0
A48: a shape console sofa tables | B48: 67 | C48: 0 | D48: 0
A49: a shaped console sofa tables | B49: 67 | C49: 0 | D49: 0
A50: are console tables and sofa tables the same | B50: 67 | C50: 0 | D50: 0
A51: can console table | B51: 67 | C51: 0 | D51: 0
A52: can i use console table | B52: 67 | C52: 0 | D52: 0
A53: can you put a console table behind two chairs | B53: 67 | C53: 0 | D53: 0
A54: can you put a console table in a bedroom | B54: 67 | C54: 0 | D54: 0
A55: can you use a console table as a sofa table | B55: 67 | C55: 0 | D55: 0
... A92: what do you call thin entry table | B92: 67 | C92: 0 | D92: 0
A93: what does a console table look like | B93: 67 | C93: 0 | D93: 0,91
A94: what is a c onsole table | B94: 67 | C94: 0 | D94: 0
A95: what is a consol table | B95: 67 | C95: 0 | D95: 0,91
A96: what is a console end table | B96: 67 | C96: 0 | D96: 0
A97: what is a console sofa table | B97: 67 | C97: 0 | D97: 0
A98: what is a console tabel | B98: 67 | C98: 0 | D98: 0
A99: what is a console table and wedge | B99: 67 | C99: 0 | D99: 0
A100: what is a console table wiki | B100: 67 | C100: 0 | D100: 0
A101: what is a dining room console | B101: 67 | C101: 0 | D101: 0
A102: what is a long end table called | B102: 67 | C102: 0 | D102: 0
A103: what is a passage console table | B103: 67 | C103: 0 | D103: 0
A104: what is a short table in front of couch called | B104: 67 | C104: 0 | D104: 0
A105: what is a sofa table for | B105: 67 | C105: 0 | D105: 0
A106: what is a table called that goes behind a sofa | B106: 67 | C106: 0 | D106: 0
A107: what is a table called thst goes behind a sofa | B107: 67 | C107: 0 | D107: 0
... A135: where to place sofa table | B135: 67 | C135: 0 | D135: 0
A136: where to put sofa table | B136: 67 | C136: 0 | D136: 0,39
A137: will my console table fit | B137: 67 | C137: 0 | D137: 0
A138: what is a nightstand | B138: 61 | C138: 260 | D138: 0,24
A139: a nightstand | B139: 61 | C139: 90 | D139: 0,88
A140: a night table | B140: 61 | C140: 70 | D140: 0,96
A141: what's a nightstand | B141: 61 | C141: 70 | D141: 0,1
A142: can a nightstand be used as an end table | B142: 61 | C142: 20 | D142: 0,71
A143: can end tables be used as nightstands | B143: 61 | C143: 20 | D143: 1
A144: can i use a nightstand as an end table | B144: 61 | C144: 20 | D144: 1
A145: can nightstand | B145: 61 | C145: 20 | D145: 1
A146: can nightstands be used as end tables | B146: 61 | C146: 20 | D146: 0,75
A147: can you use a side table as a nightstand | B147: 61 | C147: 20 | D147: 0,88
A148: can you use end tables as nightstands | B148: 61 | C148: 20 | D148: 0,83
A149: can you use night stands as end tables | B149: 61 | C149: 20 | D149: 0,83
A150: can you use nightstands as end tables | B150: 61 | C150: 20 | D150: 0,76
A151: how much does a nightstand weigh | B151: 61 | C151: 20 | D151: 0,33
A152: what are nightstands | B152: 61 | C152: 20 | D152: 0,31
A153: what are nightstands used for | B153: 61 | C153: 20 | D153: 0,02
A154: what is a night table | B154: 61 | C154: 20 | D154: 0,09
A155: why is it called a nightstand | B155: 61 | C155: 20 | D155: 0,33
A156: a rollie night table | B156: 61 | C156: 0 | D156: 0
A157: are side tables and night stands the same thing | B157: 61 | C157: 0 | D157: 0
A158: can i use a nightstand as a side table | B158: 61 | C158: 0 | D158: 0
A159: can i use nightstand as end tables | B159: 61 | C159: 0 | D159: 0
A160: can you out an end table in a bedroom | B160: 61 | C160: 0 | D160: 0
A161: can you put an end table in a bedroom | B161: 61 | C161: 0 | D161: 0
A162: can you use nightstand as end tables | B162: 61 | C162: 0 | D162: 0
A163: do end tables have to be next to the bed | B163: 61 | C163: 0 | D163: 0
...
